Workbook

Sheet Raw Data
A1: RAW DATA
C21: Table 1 | E21: Table 2 | G21: Table 3
C23: Sales_Data | E23: Product_Master | G23: Custumer_Master

Sheet Sales_data
A1: Order_ID | B1: Customer_ID | C1: Product_ID | D1: Order_Date | E1: Delivery_Date | F1: Customer_Name | G1: Gender | H1: DOB | I1: City | J1: Region | K1: Category | L1: Product_Name | M1: Quantity | N1: Unit_Price | O1: Discount_% | P1: Sales | Q1: Rating | R1: Payment_Mode | S1: Salesperson | T1: Email | U1: Phone | V1: Order_Status
A2: ORD10001 | B2: C008 | C2: P202 | D2: 18/09/2025 | E2: 22/09/2025 | F2: Kavya Nair | G2: Female | H2: 01/08/1976 | I2: Hyderabad | J2: South | K2: Home Appliances | L2: Iron | M2: 4 | N2: 2200 | O2: 10 | P2: 7920 | Q2: 4 | R2: Cash | S2: Ritika | T2: KAvya.nair@company.com | U2: 9431429797 | V2: Completed
A3: ORD10002 | B3: C008 | C3: P104 | D3: 27/04/2025 | E3: 04/05/2025 | F3: Kavya Nair | G3: Female | H3: 16/10/2000 | I3: Delhi | J3: North | K3: Electronics | L3: Monitor | M3: 17 | N3: 12000 | O3: 10 | P3: 183600 | Q3: 1 | R3: NetBanking | S3: Rahul | T3: kavya.nair@company.com | U3: 9129865339 | V3: Completed
A4: ORD10003 | B4: C010 | C4: P101 | D4: 03/09/2025 | E4: 14/09/2025 | F4: pooja shah | G4: Female | H4: 16/09/1994 | I4: Bengaluru | J4: South | K4: Electronics | L4: Laptop | M4: 5 | N4: 55000 | O4: 5 | P4: 261250 | Q4: 3 | R4: NetBanking | S4: Aisha | T4: pooja.shah@company.com | U4: 9380975626 | V4: Pending
A5: ORD10002 | B5: C008 | C5: P202 | D5: 21/03/2026 | E5: 02/04/2026 | F5: Kavya Nair | G5: Female | H5: 07/03/2004 | I5: Bengaluru | J5: South | K5: Home Appliances | L5: Iron | M5: 5 | N5: 2200 | O5: 5 | P5: 10450 | Q5: 5 | R5: NetBanking | S5: Aisha | T5: kavya.nair@company.com | U5: 9600261125 | V5: Cancelled
A6: ORD10005 | B6: C009 | C6: P103 | D6: 27/09/2025 | E6: 07/10/2025 | F6: Mohit Verma | G6: Male | H6: 13/04/1976 | I6: Delhi | J6: North | K6: Electronics | L6: Keyboard | M6: 8 | N6: 1200 | O6: 5 | P6: 9120 | Q6: 2 | R6: Card | S6: Aisha | T6: mohit.verma@company.com | U6: 9724635978 | V6: Pending
A7: ORD10006 | B7: C007 | C7: P202 | D7: 04/01/2026 | E7: 12/01/2026 | F7: arjun Rao | G7: Male | H7: 07/02/1988 | I7: Hyderabad | J7: South | K7: Home Appliances | L7: Iron | M7: 4 | N7: 2200 | O7: 0 | P7: 8800 | Q7: 1 | R7: UPI | S7: Ritika | T7: arjun.rao@company.com | U7: 9780584905 | V7: Completed
A8: ORD10007 | B8: C008 | C8: P201 | D8: 31/02/2025 | E8: 25/02/2026 | F8: Kavya Nair | G8: Female | H8: 20/03/2003 | I8: Hyderabad | J8: South | K8: Home Appliances | L8: Mixer | M8: 2 | N8: 3500 | O8: 5 | P8: 6650 | Q8: 1 | R8: UPI | S8: Ritika | T8: kavya.nair@company.com | U8: 9958252176 | V8: Completed
A9: ORD10008 | B9: C002 | C9: P104 | D9: 13/04/2025 | E9: 19/04/2025 | F9: Priya Patel | G9: Female | H9: 07/03/1995 | I9: Mumbai | J9: West | K9: Electronics | L9: Monitor | M9: 14 | N9: 12000 | O9: 15 | P9: 142800 | Q9: 4 | R9: NetBanking | S9: Ritika | T9: priYa.patel@company.com | U9: 9705521654 | V9: Completed
A10: ORD10009 | B10: C008 | C10: P104 | D10: 31/01/2026 | E10: 02/02/2026 | F10: kavya Nair | G10: Female | H10: 06/04/1997 | I10: Pune | J10: West | K10: Electronics | L10: Monitor | M10: 4 | N10: 12000 | O10: 15 | P10: 40800 | Q10: 4 | R10: UPI | S10: Neha | T10: kavya.nair@company.com | U10: 9588041011 | V10: Completed
A11: ORD10010 | B11: C002 | C11: P301 | D11: 25/03/2025 | E11: 27/03/2025 | F11: Priya Patel | G11: Female | H11: 07/01/1990 | I11: Mumbai | J11: West | K11: Stationery | L11: Notebook | M11: 6 | N11: 60 | O11: 0 | P11: 360 | Q11: 4 | R11: Card | S11: Neha | T11: PRiya.patel@company.com | U11: 9340540608 | V11: Completed
A12: ORD10011 | B12: C003 | C12: P202 | D12: 19/09/2025 | E12: 23/09/2025 | F12: Rohit Singh | G12: Male | H12: 10/05/1982 | I12: Delhi | J12: North | K12: Home Appliances | L12: Iron | M12: -3 | N12: 2200 | O12: 0 | P12: 35200 | Q12: 2 | R12: Card | S12: Rahul | T12: rohit.singh@company.com | U12: 9521710321 | V12: Pending
A13: ORD10012 | B13: C008 | C13: P201 | D13: 08/03/2025 | E13: 15/03/2025 | F13: Kavya Nair | G13: Female | H13: 23/01/1982 | I13: Ahmedabad | J13: West | K13: Home Appliances | L13: Mixer | M13: 10 | N13: 3500 | O13: 5 | P13: 33250 | Q13: 5 | R13: Card | S13: Aisha | T13: kavya.nair@company.com | U13: 9123535241 | V13: Cancelled
... A39: ORD10038 | B39: C006 | C39: P201 | D39: 08/03/2026 | E39: 20/03/2026 | F39: Sneha Joshi | G39: Female | H39: 21/06/1980 | I39: Delhi | J39: North | K39: Home Appliances | L39: Mixer | M39: 20 | N39: 3500 | O39: 10 | P39: 63000 | Q39: 3 | R39: Card | S39: Rahul | T39: sneha.joshi@company.com | U39: 9283578533 | V39: Cancelled
A40: ORD10039 | B40: C008 | C40: P302 | D40: 13/02/2025 | E40: 19/02/2025 | F40: Kavya Nair | G40: Female | H40: 17/06/1979 | I40: Pune | J40: West | K40: Stationery | L40: Pen | M40: 5 | N40: 1200 | O40: 0 | P40: 100 | Q40: 1 | R40: Cash | S40: Rahul | T40: kavya.nair@company.com | U40: 9963005771 | V40: Cancelled
A41: ORD10040 | B41: C010 | C41: P203 | D41: 05/10/2025 | E41: 15/10/2025 | F41: Pooja Shah | G41: Female | H41: 18/06/1992 | I41: Mumbai | J41: West | K41: Home Appliances | L41: Microwave | M41: 20 | N41: 8500 | O41: 0 | P41: 170000 | Q41: 1 | R41: UPI | S41: Neha | T41: pooja.shah@company.com | U41: 9484632635 | V41: Cancelled
A42: ORD10041 | B42: C007 | C42: P301 | D42: 10/02/2026 | E42: 12/02/2026 | F42: Arjun Rao | G42: Male | H42: 06/06/1994 | I42: Bengaluru | J42: South | K42: Stationery | L42: Notebook | M42: 8 | N42: 60 | O42: 15 | P42: 408 | Q42: 5 | R42: UPI | S42: Rahul | T42: arjun.rao@company.com | U42: 9276319484 | V42: Pending
A43: ORD10042 | B43: C010 | C43: P201 | D43: 04/06/2025 | E43: 16/06/2025 | F43: Pooja Shah | G43: Female | H43: 22/09/1988 | I43: Pune | J43: West | K43: Home Appliances | L43: Mixer | M43: 8 | N43: 3500 | O43: 5 | P43: 26600 | Q43: 1 | R43: Card | S43: Neha | T43: pooja.shah@company.com | U43: 9619034852 | V43: Pending
A44: ORD10043 | B44: C009 | C44: P203 | D44: 08/02/2026 | E44: 14/02/2026 | F44: Mohit Verma | G44: Male | H44: 14/07/2001 | I44: Jaipur | J44: North | K44: Home Appliances | L44: Microwave | M44: 1 | N44: 8500 | O44: 0 | P44: 8500 | Q44: 2 | R44: Card | S44: Neha | T44: mohit.verma@company.com | U44: 9636416962 | V44: Pending
A45: ORD10044 | B45: C001 | C45: P303 | D45: 30/03/2025 | E45: 31/03/2025 | F45: amit Sharma | G45: Male | H45: 09/08/1991 | I45: Pune | J45: West | K45: Stationery | L45: Marker | M45: 8 | N45: 45 | O45: 15 | P45: 306 | Q45: 2 | R45: Card | S45: Aisha | T45: amit.sharma@company.com | U45: 9357133880 | V45: Completed
A46: ORD10045 | B46: C006 | C46: P202 | D46: 25/04/2025 | E46: 28/04/2025 | F46: Sneha Joshi | G46: Female | H46: 21/10/1988 | I46: Pune | J46: West | K46: Home Appliances | L46: Iron | M46: 16 | N46: 2200 | O46: 5 | P46: 33440 | Q46: 5 | R46: Card | S46: Aisha | T46: sneha.joshi@company.com | U46: 9575210324 | V46: Cancelled
A47: ORD10046 | B47: C009 | C47: P201 | D47: 13/10/2025 | E47: 23/10/2025 | F47: Mohit Verma | G47: Male | H47: 19/11/2002 | I47: Bengaluru | J47: South | K47: Home Appliances | L47: Mixer | M47: 19 | N47: 3500 | O47: 20 | P47: 53200 | Q47: 3 | R47: Cash | S47: Karan | T47: mohit.verma@company.com | U47: 9276080204 | V47: Cancelled
A48: ORD10047 | B48: C006 | C48: P102 | D48: 11/10/2025 | E48: 14/10/2025 | F48: Sneha Joshi | G48: Female | H48: 06/07/2000 | I48: Pune | J48: West | K48: Electronics | L48: Mouse | M48: 15 | N48: 700 | O48: 15 | P48: 8925 | Q48: 4 | R48: UPI | S48: Neha | T48: sneha.joshicompany.com | U48: 9856624471 | V48: Completed
A49: ORD10048 | B49: C006 | C49: P102 | D49: 27/11/2025 | E49: 03/12/2025 | F49: Sneha Joshi | G49: Female | H49: 26/11/1998 | I49: Jaipur | J49: North | K49: Electronics | L49: Mouse | M49: 19 | N49: 700 | O49: 20 | P49: 10640 | Q49: 1 | R49: Cash | S49: Neha | T49: sneha.joshi@company.com | U49: 9238141322 | V49: Completed
A50: ORD10049 | B50: C009 | C50: P104 | D50: 19/04/2026 | F50: Mohit Verma | G50: Male | H50: 03/06/1996 | I50: Delhi | J50: North | K50: Electronics | L50: Monitor | M50: 19 | N50: 12000 | O50: 0 | P50: 228000 | Q50: 1 | R50: NetBanking | S50: Aisha | T50: mohit.verma@company.com | U50: 9890380030 | V50: Completed
A51: ORD10050 | B51: C004 | C51: P103 | D51: 19/04/2026 | E51: 21/04/2026 | F51: Anita Gupta | G51: Female | H51: 15/03/1987 | I51: Pune | J51: West | K51: Electronics | L51: Keyboard | M51: 6 | N51: 1200 | O51: 5 | P51: 6840 | Q51: 2 | R51: Cash | S51: Ritika | T51: anita.gupta@company.com | U51: 9495893170 | V51: Pending
A52: ORD10051 | B52: C010 | C52: P202 | D52: 28/03/2025 | E52: 07/04/2025 | F52: POoja Shah | G52: Female | H52: 20/02/1979 | I52: Bengaluru | J52: South | K52: Home Appliances | L52: Iron | M52: 7 | N52: 2200 | O52: 15 | P52: 13090 | Q52: 1 | R52: UPI | S52: Aisha | T52: pooja.shah@company.com | U52: 9485166307 | V52: Completed
A53: ORD10052 | B53: C002 | C53: P301 | D53: 25/08/2025 | E53: 28/08/2025 | F53: Priya Patel | G53: Female | H53: 09/08/2000 | I53: Jaipur | J53: North | K53: Stationery | L53: Notebook | M53: 8 | N53: 60 | O53: 10 | P53: 432 | Q53: 5 | R53: Card | S53: Aisha | T53: priya.patel@company.com | U53: 9924709648 | V53: Cancelled
A54: ORD10053 | B54: C005 | C54: P101 | D54: 19/08/2025 | E54: 23/08/2025 | F54: Vikas Mehta | G54: Male | H54: 17/01/1976 | I54: Kolkata | J54: East | K54: Electronics | L54: Laptop | M54: 12 | N54: 55000 | O54: 5 | P54: 627000 | Q54: 2 | R54: UPI | S54: Rahul | T54: vikas.mehta@company.com | U54: 9350554626 | V54: Pending
A55: ORD10054 | B55: C008 | C55: P102 | D55: 27/07/2025 | E55: 05/08/2025 | F55: Kavya Nair | G55: Female | H55: 04/04/1975 | I55: Jaipur | J55: North | K55: Electronics | L55: Mouse | M55: 3 | N55: 700 | O55: 0 | P55: 2100 | Q55: 3 | R55: Card | S55: Karan | T55: kavya.nair@company.com | U55: 9743295580 | V55: Cancelled
A56: ORD10055 | B56: C003 | C56: P301 | D56: 21/02/2025 | E56: 26/02/2025 | F56: RoHit Singh | G56: Male | H56: 11/12/1976 | I56: Ahmedabad | J56: West | K56: Stationery | L56: Notebook | M56: 19 | N56: 60 | O56: 15 | P56: 969 | Q56: 4 | R56: Card | S56: Rahul | T56: rohit.singh@company.com | U56: 9822926495 | V56: Cancelled
A57: ORD10056 | B57: C001 | C57: P301 | D57: 10/08/2025 | E57: 11/08/2025 | F57: Amit Sharma | G57: Male | H57: 03/12/1979 | I57: Jaipur | J57: North | K57: Stationery | L57: Notebook | M57: 9 | N57: 60 | O57: 20 | P57: 432 | Q57: 1 | R57: NetBanking | S57: Neha | T57: amit.sharma@company.com | U57: 9518298190 | V57: Pending
A58: ORD10057 | B58: C001 | C58: P102 | D58: 24/03/2026 | E58: 30/03/2026 | F58: Amit Sharma | G58: Male | H58: 27/12/1978 | I58: Bengaluru | J58: South | K58: Electronics | L58: Mouse | M58: 6 | N58: 700 | O58: 0 | P58: 4200 | Q58: 4 | R58: UPI | S58: Rahul | T58: amit.sharmcompany.com | U58: 9366223547 | V58: Cancelled
A59: ORD10058 | B59: C003 | C59: P303 | D59: 13/03/2026 | E59: 19/03/2026 | F59: Rohit Singh | G59: Male | H59: 15/04/1975 | I59: Delhi | J59: North | K59: Stationery | L59: Marker | M59: 18 | N59: 45 | O59: 5 | P59: 769.5 | Q59: 1 | R59: Card | S59: Aisha | T59: rohit.singh@company.com | U59: 9701988524 | V59: Pending
A60: ORD10059 | B60: C007 | C60: P302 | D60: 15/06/2025 | E60: 26/06/2025 | F60: Arjun Rao | G60: Male | H60: 19/12/1988 | I60: Jaipur | J60: North | K60: Stationery | L60: Pen | M60: 8 | N60: 20 | O60: 5 | P60: 152 | Q60: 1 | R60: Card | S60: Ritika | T60: arjun.rao@company.com | U60: 9836327649 | V60: completed
A61: ORD10060 | B61: C005 | C61: P102 | D61: 05/03/2025 | E61: 06/03/2025 | F61: Vikas Mehta | G61: Male | H61: 07/03/1979 | I61: Jaipur | J61: North | K61: Electronics | L61: Mouse | M61: 8 | N61: 700 | O61: 10 | P61: 5040 | Q61: 1 | R61: NetBanking | S61: Aisha | T61: Vikas.mehta@company.com | U61: 9261800516 | V61: Cancelled
A62: ORD10061 | B62: C008 | C62: P302 | D62: 09/04/2026 | E62: 19/04/2026 | F62: Kavya Nair | G62: Female | H62: 17/12/2003 | I62: Delhi | J62: North | K62: Stationery | L62: Pen | M62: 7 | N62: 20 | O62: 15 | P62: 119 | Q62: 5 | R62: Card | S62: Rahul | T62: kavya.nair@company.com | U62: 9950802015 | V62: Completed
... A74: ORD10073 | B74: C008 | C74: P103 | D74: 13/12/2025 | E74: 23/12/2025 | F74: Kavya Nair | G74: Female | H74: 22/09/1981 | I74: Jaipur | J74: North | K74: Electronics | L74: Keyboard | M74: 1 | N74: 1200 | O74: 5 | P74: 1140 | Q74: 3 | R74: UPI | S74: Aisha | T74: kavya.nair@company.com | U74: 9808988530 | V74: Cancelled
A75: ORD10074 | B75: C010 | C75: P202 | D75: 04/02/2026 | E75: 16/02/2026 | F75: Pooja Shah | G75: Female | H75: 20/06/1980 | J75: South | K75: Home Appliances | L75: Iron | M75: 1 | N75: 2200 | O75: 15 | P75: 1870 | Q75: 4 | R75: Card | S75: Aisha | T75: pooja.shah@company.com | U75: 9286410494 | V75: Completed
A76: ORD10075 | B76: C003 | C76: P103 | D76: 26/01/2026 | E76: 28/01/2026 | F76: Rohit Singh | G76: Male | H76: 02/11/1982 | I76: Pune | J76: West | K76: Electronics | L76: Keyboard | M76: 3 | N76: 1200 | O76: 10 | P76: 3240 | Q76: 5 | R76: Cash | S76: Rahul | T76: rohit.singh@company.com | U76: 9311555196 | V76: Completed
A77: ORD10076 | B77: C008 | C77: P201 | D77: 27/06/2025 | E77: 07/07/2025 | F77: Kavya Nair | G77: Female | H77: 10/01/1980 | I77: Bengaluru | J77: South | K77: Home Appliances | L77: Mixer | M77: 10 | N77: 3500 | O77: 20 | P77: 28000 | Q77: 5 | R77: Card | S77: Ritika | T77: kavya.nair@company.com | U77: 9101810266 | V77: Completed
A78: ORD10077 | B78: C007 | C78: P102 | D78: 17/03/2026 | E78: 19/03/2026 | F78: Arjun Rao | G78: Male | H78: 27/04/1981 | I78: Delhi | J78: North | K78: Electronics | L78: Mouse | M78: 18 | N78: 700 | O78: 5 | P78: 11970 | Q78: 3 | R78: Card | S78: Neha | T78: arjun.rao@company.com | U78: 9464556593 | V78: Cancelled
A79: ORD10078 | B79: C005 | C79: P102 | D79: 09/06/2025 | E79: 18/06/2025 | F79: Vikas Mehta | G79: Male | H79: 12/03/1985 | I79: Bengaluru | J79: South | K79: Electronics | L79: Mouse | M79: 12 | N79: 700 | O79: 15 | P79: 7140 | Q79: 2 | R79: UPI | S79: Rahul | T79: vikas.mehta@company.com | U79: 9338278358 | V79: Completed
A80: ORD10079 | B80: C009 | C80: P103 | D80: 15/11/2025 | E80: 16/11/2025 | F80: Mohit Verma | G80: Male | H80: 15/03/1999 | I80: Mumbai | J80: West | K80: Electronics | L80: Keyboard | M80: 8 | N80: 1200 | O80: 0 | P80: 9600 | Q80: 4 | R80: Card | S80: Rahul | T80: mohit.verma@company.com | U80: 9621410770 | V80: Pending
A81: ORD10080 | B81: C003 | C81: P301 | D81: 06/11/2025 | E81: 10/11/2025 | F81: Rohit Singh | G81: Male | H81: 07/07/1983 | I81: Pune | J81: West | K81: Stationery | L81: Notebook | M81: 2 | N81: 60 | O81: 0 | P81: 120 | Q81: 2 | R81: UPI | S81: Rahul | T81: rohit.singh@company.com | U81: 9981333189 | V81: Completed
A82: ORD10081 | B82: C001 | C82: P303 | D82: 01/01/2025 | E82: 07/01/2025 | F82: Amit Sharma | G82: Male | H82: 06/03/1989 | I82: Pune | J82: West | K82: Stationery | L82: Marker | M82: 10 | N82: 45 | O82: 15 | P82: 382.5 | Q82: 3 | R82: NetBanking | S82: Ritika | T82: amit.sharma@company.com | U82: 9723450355 | V82: Cancelled
A83: ORD10082 | B83: C005 | C83: P201 | D83: 25/04/2026 | E83: 03/05/2026 | F83: Vikas Mehta | G83: Male | H83: 20/06/1982 | I83: Kolkata | J83: East | K83: Home Appliances | L83: Mixer | M83: 12 | N83: 3500 | O83: 5 | P83: 39900 | Q83: 3 | R83: NetBanking | S83: Aisha | T83: vikas.mehta@company.com | U83: 9886243907 | V83: Pending
A84: ORD10083 | B84: C003 | C84: P301 | D84: 19/09/2025 | E84: 27/09/2025 | F84: Rohit Singh | G84: Male | H84: 23/06/2001 | I84: Mumbai | J84: West | K84: Stationery | L84: Notebook | M84: 2 | N84: 60 | O84: 15 | P84: 102 | Q84: 1 | R84: UPI | S84: Neha | T84: rohit.singh@company.com | U84: 9473931904 | V84: Completed
A85: ORD10084 | B85: C003 | C85: P103 | D85: 18/03/2025 | E85: 21/03/2025 | F85: Rohit Singh | G85: Male | H85: 19/07/1983 | I85: Hyderabad | J85: South | K85: Electronics | L85: Keyboard | M85: 18 | N85: 1200 | O85: 15 | P85: 18360 | Q85: 3 | R85: Card | S85: Neha | T85: rohit.singh@company.com | U85: 9287159610 | V85: Pending
A86: ORD10085 | B86: C008 | C86: P104 | D86: 30/10/2025 | E86: 31/10/2025 | F86: Kavya Nair | G86: Female | H86: 24/03/1993 | I86: Mumbai | J86: West | K86: Electronics | L86: Monitor | M86: 18 | N86: 12000 | O86: 15 | P86: 183600 | Q86: 2 | R86: Cash | S86: Rahul | T86: kavya.nair@company.com | U86: 9876513858 | V86: Completed
A87: ORD10086 | B87: C007 | C87: P302 | D87: 31/10/2025 | E87: 11/11/2025 | F87: Arjun Rao | G87: Male | H87: 10/05/1995 | I87: Ahmedabad | J87: West | K87: Stationery | L87: Pen | M87: 7 | N87: 20 | O87: 0 | P87: 140 | Q87: 2 | R87: Card | S87: Ritika | T87: arjun.rao@company.com | U87: 9237400853 | V87: Cancelled
... A119: ORD10118 | B119: C001 | C119: P303 | D119: 31/05/2025 | E119: 11/06/2025 | F119: Amit Sharma | G119: Male | H119: 07/09/1995 | I119: Pune | J119: West | K119: Stationery | L119: Marker | M119: 16 | N119: 45 | O119: 0 | P119: 720 | Q119: 1 | R119: NetBanking | S119: Aisha | T119: amit.sharma@company.com | U119: 9807154421 | V119: Completed
A120: ORD10119 | B120: C009 | C120: P103 | D120: 30/05/2025 | E120: 02/06/2025 | F120: Mohit Verma | G120: Male | H120: 08/03/1988 | I120: Ahmedabad | J120: West | K120: Electronics | L120: Keyboard | M120: Ten | N120: 1200 | O120: 15 | P120: 7140 | Q120: 4 | R120: UPI | S120: Karan | T120: mohit.verma@company.com | U120: 9919834000 | V120: Pending
A121: ORD10120 | B121: C002 | C121: P104 | D121: 19/08/2025 | E121: 30/08/2025 | F121: Priya Patel | G121: Female | H121: 07/07/1989 | I121: Jaipur | J121: North | K121: Electronics | L121: Monitor | M121: 14 | N121: 12000 | O121: 15 | P121: 142800 | Q121: 2 | R121: NetBanking | S121: Aisha | T121: priya.patel@company.com | U121: 9739798818 | V121: Pending
A122: ORD10121 | B122: C003 | C122: P203 | D122: 14/12/2025 | E122: 16/12/2025 | F122: Rohit Singh | G122: Male | H122: 11/11/1993 | I122: Pune | J122: West | K122: Home Appliances | L122: Microwave | M122: 8 | N122: 8500 | O122: 20 | P122: 54400 | Q122: 3 | R122: Card | S122: Rahul | T122: rohit.singh@company.com | U122: 9208625306 | V122: Completed
A123: ORD10122 | B123: C007 | C123: P303 | D123: 31/01/2026 | E123: 10/02/2026 | F123: Arjun Rao | G123: Male | H123: 01/02/2000 | I123: Bengaluru | J123: South | K123: Stationery | L123: Marker | M123: 3 | N123: 45 | O123: 0 | P123: 135 | Q123: 4 | R123: UPI | S123: Aisha | T123: arjun.rao@company.com | U123: 9970178536 | V123: Cancelled
A124: ORD10123 | B124: C001 | C124: P102 | D124: 03/01/2026 | E124: 04/01/2026 | F124: Amit Sharma | G124: Male | H124: 22/06/1986 | I124: Jaipur | J124: North | K124: Electronics | L124: Mouse | M124: 13 | N124: 700 | O124: 5 | P124: 8645 | Q124: 3 | R124: Card | S124: Neha | T124: amit.sharma@company.com | U124: 9633745195 | V124: Pending
A125: ORD10124 | B125: C004 | C125: P103 | D125: 20/10/2025 | E125: 26/10/2025 | F125: Anita Gupta | G125: Female | H125: 16/02/1986 | I125: Mumbai | J125: West | K125: Electronics | L125: Keyboard | M125: 14 | N125: 1200 | O125: 20 | P125: 13440 | Q125: 5 | R125: NetBanking | S125: Aisha | T125: anita.gupta@company.com | U125: 9922102053 | V125: Completed
A126: ORD10125 | B126: C002 | C126: P303 | D126: 11/05/2025 | E126: 21/05/2025 | F126: Priya Patel | G126: Female | H126: 18/09/1991 | I126: Delhi | J126: North | K126: Stationery | L126: Marker | M126: 2 | N126: 45 | O126: 5 | P126: 85.5 | Q126: 3 | R126: UPI | S126: Ritika | T126: priya.patel@company.com | U126: 9135963930 | V126: Cancelled
A127: ORD10126 | B127: C004 | C127: P103 | D127: 02/01/2026 | E127: 06/01/2026 | F127: Anita Gupta | G127: Female | H127: 04/01/1981 | I127: Bengaluru | J127: South | K127: Electronics | L127: Keyboard | M127: 2 | N127: 1200 | O127: 20 | P127: 1920 | Q127: 3 | R127: Card | S127: Neha | T127: anita.gupta@company.com | U127: 9429405275 | V127: Completed
A128: ORD10127 | B128: C003 | C128: P101 | D128: 20/04/2026 | E128: 26/04/2026 | F128: Rohit Singh | G128: Male | H128: 12/10/2004 | I128: Bengaluru | J128: South | K128: Electronics | L128: Laptop | M128: 10 | N128: 55000 | O128: 5 | P128: 522500 | Q128: 5 | R128: UPI | S128: Aisha | T128: rohit.singh@company.com | U128: 9521757571 | V128: Pending
A129: ORD10128 | B129: C006 | C129: P201 | D129: 04/08/2025 | E129: 05/08/2025 | F129: Sneha Joshi | G129: Female | H129: 25/03/1984 | I129: Jaipur | J129: North | K129: Home Appliances | L129: Mixer | M129: 15 | N129: 3500 | O129: 10 | P129: 47250 | Q129: 3 | R129: NetBanking | S129: Neha | T129: sneha.joshi@company.com | U129: 9467375455 | V129: Completed
A130: ORD10129 | B130: C002 | C130: P202 | D130: 13/08/2025 | E130: 18/08/2025 | F130: Priya Patel | G130: Female | H130: 09/09/1982 | I130: Bengaluru | J130: South | K130: Home Appliances | L130: Iron | M130: 10 | N130: 2200 | O130: 15 | P130: 18700 | Q130: 4 | R130: Card | S130: Rahul | T130: priya.patel@company.com | U130: 9838809695 | V130: Pending
A131: ORD10130 | B131: C006 | C131: P201 | D131: 16/06/2025 | E131: 24/06/2025 | F131: Sneha Joshi | G131: Female | H131: 15/02/1993 | I131: Pune | J131: West | K131: Home Appliances | L131: Mixer | M131: 11 | N131: 3500 | O131: 5 | P131: 36575 | Q131: 5 | R131: Cash | S131: Ritika | T131: sneha.joshi@company.com | U131: 9296609782 | V131: Cancelled
A132: ORD10131 | B132: C004 | C132: P103 | D132: 27/04/2026 | E132: 30/04/2026 | F132: Anita Gupta | G132: Female | H132: 08/04/2003 | I132: Bengaluru | J132: South | K132: Electronics | L132: Keyboard | M132: 14 | N132: 1200 | O132: 0 | P132: 16800 | Q132: 5 | R132: Cash | S132: Rahul | T132: anita.gupta@company.com | U132: 9848259992 | V132: Cancelled
... A299: ORD10298 | B299: C003 | C299: P101 | D299: 13/01/2025 | E299: 16/01/2025 | F299: Rohit Singh | G299: Male | H299: 03/01/2004 | I299: Hyderabad | J299: South | K299: Electronics | L299: Laptop | M299: 11 | N299: 55000 | O299: 5 | P299: 574750 | Q299: 1 | R299: UPI | S299: Ritika | T299: rohit.singh@company.com | U299: 9482699727 | V299: Cancelled
A300: ORD10299 | B300: C007 | C300: P201 | D300: 05/10/2025 | E300: 17/10/2025 | F300: Arjun Rao | G300: Male | H300: 02/05/1992 | I300: Jaipur | J300: North | K300: Home Appliances | L300: Mixer | M300: 12 | N300: 3500 | O300: 0 | P300: 42000 | Q300: 2 | R300: NetBanking | T300: arjun.rao@company.com | U300: 9332473934 | V300: Pending
A301: ORD10300 | B301: C009 | C301: P303 | D301: 25/02/2026 | E301: 08/03/2026 | F301: Mohit Verma | G301: Male | H301: 26/01/2003 | I301: Hyderabad | J301: South | K301: Stationery | L301: Marker | M301: 15 | N301: 45 | O301: 10 | P301: 607.5 | Q301: 2 | R301: Cash | S301: Karan | T301: mohit.verma@company.com | U301: 9647657382 | V301: Pending
A302: ORD10301 | B302: C001 | C302: P303 | D302: 16/05/2025 | E302: 26/05/2025 | F302: Amit Sharma | G302: Male | H302: 20/05/1987 | I302: Bengaluru | J302: South | K302: Stationery | L302: Marker | M302: 13 | N302: 45 | O302: 0 | P302: 585 | Q302: 5 | R302: NetBanking | S302: Rahul | T302: amit.sharma@company.com | U302: 9736797776 | V302: Pending
A303: ORD10302 | B303: C003 | C303: P101 | D303: 02/01/2026 | E303: 05/01/2026 | F303: Rohit Singh | G303: Male | H303: 07/09/1975 | I303: Bengaluru | J303: South | K303: Electronics | L303: Laptop | M303: 8 | N303: 55000 | O303: 0 | P303: 440000 | Q303: 2 | R303: UPI | S303: Karan | T303: rohit.singh@company.com | U303: 9745773533 | V303: Cancelled
A304: ORD10303 | B304: C006 | C304: P101 | D304: 23/07/2025 | E304: 27/07/2025 | F304: Sneha Joshi | G304: Female | H304: 10/08/1980 | I304: Delhi | J304: North | K304: Electronics | L304: Laptop | M304: 4 | N304: 55000 | O304: 20 | P304: 176000 | Q304: 5 | R304: Cash | S304: Rahul | T304: sneha.joshi@company.com | U304: 9246715757 | V304: Pending
A305: ORD10304 | B305: C008 | C305: P201 | D305: 23/04/2026 | E305: 26/04/2026 | F305: Kavya Nair | G305: Female | H305: 07/04/1989 | I305: Ahmedabad | J305: West | K305: Home Appliances | L305: Mixer | M305: 19 | N305: 3500 | O305: 5 | P305: 63175 | Q305: 1 | R305: Card | S305: Neha | T305: kavya.nair@company.com | U305: 9904065774 | V305: Completed
A306: ORD10305 | B306: C005 | C306: P103 | D306: 02/03/2025 | E306: 06/03/2025 | F306: Vikas Mehta | G306: Male | H306: 20/08/1998 | I306: Jaipur | J306: North | K306: Electronics | L306: Keyboard | M306: 17 | N306: 1200 | O306: 15 | P306: 17340 | Q306: 2 | R306: NetBanking | S306: Rahul | T306: vikas.mehta@company.com | U306: 9652985385 | V306: Completed
A307: ORD10306 | B307: C008 | C307: P202 | D307: 09/02/2026 | E307: 17/02/2026 | F307: Kavya Nair | G307: Female | H307: 03/04/2001 | I307: Hyderabad | J307: South | K307: Home Appliances | L307: Iron | M307: 8 | N307: 2200 | O307: 5 | P307: 16720 | Q307: 3 | R307: Card | S307: Neha | T307: kavya.nair@company.com | U307: 9427001508 | V307: Pending
A308: ORD10307 | B308: C006 | C308: P102 | D308: 16/02/2025 | E308: 26/02/2025 | F308: Sneha Joshi | G308: Female | H308: 05/03/1992 | I308: Mumbai | J308: West | K308: Electronics | L308: Mouse | M308: 17 | N308: 700 | O308: 20 | P308: 9520 | Q308: 4 | R308: NetBanking | S308: Neha | T308: sneha.joshi@company.com | U308: 9666803655 | V308: Completed
A309: ORD10308 | B309: C006 | C309: P203 | D309: 28/08/2025 | E309: 08/09/2025 | F309: Sneha Joshi | G309: Female | H309: 28/12/1976 | I309: Pune | J309: West | K309: Home Appliances | L309: Microwave | M309: 6 | N309: 8500 | O309: 15 | P309: 43350 | Q309: 1 | R309: Cash | S309: Aisha | T309: sneha.joshi@company.com | U309: 9134878547 | V309: Completed
A310: ORD10309 | B310: C010 | C310: P201 | D310: 06/10/2025 | E310: 11/10/2025 | F310: Pooja Shah | G310: Female | H310: 04/09/1986 | I310: Hyderabad | J310: South | K310: Home Appliances | L310: Mixer | M310: 3 | N310: 3500 | O310: 10 | P310: 9450 | Q310: 1 | R310: NetBanking | S310: Rahul | T310: pooja.shah@company.com | U310: 9253593557 | V310: Completed
A311: ORD10310 | B311: C009 | C311: P104 | D311: 17/01/2025 | E311: 29/01/2025 | F311: Mohit Verma | G311: Male | H311: 14/08/1989 | I311: Ahmedabad | J311: West | K311: Electronics | L311: Monitor | M311: 2 | N311: 12000 | O311: 20 | P311: 19200 | Q311: 1 | R311: Card | S311: Aisha | T311: mohit.verma@company.com | U311: 9183094051 | V311: Completed
A312: ORD10311 | B312: C005 | C312: P302 | D312: 13/10/2025 | E312: 16/10/2025 | F312: Vikas Mehta | G312: Male | H312: 02/03/1991 | I312: Delhi | J312: North | K312: Stationery | L312: Pen | M312: 12 | N312: 20 | O312: 20 | P312: 192 | Q312: 2 | R312: Card | S312: Rahul | T312: vikas.mehta@company.com | U312: 9293147620 | V312: Completed
... A370: ORD10369 | B370: C010 | C370: P301 | D370: 01/04/2026 | E370: 05/04/2026 | F370: Pooja Shah | G370: Female | H370: 04/01/1987 | I370: Hyderabad | J370: South | K370: Stationery | L370: Notebook | M370: 19 | N370: 60 | O370: 15 | P370: 969 | Q370: 4 | R370: NetBanking | S370: Neha | T370: pooja.shah@company.com | U370: 9435947486 | V370: Cancelled
A371: ORD10370 | B371: C001 | C371: P101 | E371: 02/02/2025 | F371: Amit Sharma | G371: Male | H371: 14/05/1992 | I371: Delhi | J371: North | K371: Electronics | L371: Laptop | M371: 15 | N371: 55000 | O371: 0 | P371: 825000 | Q371: 5 | R371: Card | S371: Neha | T371: amit.sharma@company.com | U371: 9411668831 | V371: Cancelled
A372: ORD10371 | B372: C009 | C372: P303 | D372: 06/10/2025 | E372: 08/10/2025 | F372: Mohit Verma | G372: Male | H372: 03/05/1989 | I372: Bengaluru | J372: South | K372: Stationery | L372: Marker | M372: 11 | N372: 45 | O372: 5 | P372: 470.25 | Q372: 5 | R372: NetBanking | S372: Karan | T372: mohit.verma@company.com | U372: 9523682403 | V372: Completed
A373: ORD10372 | B373: C006 | C373: P302 | D373: 12/06/2025 | E373: 17/06/2025 | F373: Sneha Joshi | G373: Female | H373: 19/12/1990 | I373: Jaipur | J373: North | K373: Stationery | L373: Pen | M373: 9 | N373: 20 | O373: 10 | P373: 162 | Q373: 1 | R373: Card | S373: Rahul | T373: sneha.joshi@company.com | U373: 9652936744 | V373: Cancelled
A374: ORD10373 | B374: C004 | C374: P303 | D374: 18/11/2025 | E374: 20/11/2025 | F374: Anita Gupta | G374: Female | H374: 09/07/1995 | I374: Bengaluru | J374: South | K374: Stationery | L374: Marker | M374: 5 | N374: 45 | O374: 5 | P374: 213.75 | Q374: 3 | R374: Card | S374: Neha | T374: anita.gupta@company.com | U374: 9726464733 | V374: Pending
A375: ORD10374 | B375: C007 | C375: P102 | D375: 01/11/2025 | E375: 02/11/2025 | F375: Arjun Rao | G375: Male | H375: 23/12/1998 | I375: Hyderabad | J375: South | K375: Electronics | L375: Mouse | M375: 5 | N375: 700 | O375: 10 | P375: 3150 | Q375: 2 | R375: UPI | S375: Rahul | T375: arjun.rao@company.com | U375: 9273520544 | V375: Completed
A376: ORD10375 | B376: C005 | C376: P102 | D376: 24/01/2025 | E376: 31/01/2025 | F376: Vikas Mehta | G376: Male | H376: 23/12/1979 | I376: Kolkata | J376: East | K376: Electronics | L376: Mouse | M376: 1 | N376: 700 | O376: 0 | P376: 700 | Q376: 1 | R376: UPI | S376: Karan | T376: vikas.mehta@company.com | U376: 9374259988 | V376: Completed
A377: ORD10376 | B377: C008 | C377: P102 | D377: 13/02/2026 | E377: 21/02/2026 | F377: Kavya Nair | G377: Female | H377: 15/12/1975 | I377: Mumbai | J377: West | K377: Electronics | L377: Mouse | M377: 13 | N377: 700 | O377: 20 | P377: 7280 | Q377: 2 | R377: Card | S377: Ritika | T377: kavya.nair@company.com | U377: 9538129419 | V377: Completed
A378: ORD10377 | B378: C009 | C378: P104 | D378: 08/02/2025 | E378: 19/02/2025 | F378: Mohit Verma | G378: Male | H378: 17/05/1993 | I378: Pune | J378: West | K378: Electronics | L378: Monitor | M378: 20 | N378: 12000 | O378: 0 | P378: 240000 | Q378: 2 | R378: Card | S378: Neha | T378: mohit.verma@company.com | U378: 9382815686 | V378: Completed
A379: ORD10378 | B379: C007 | C379: P103 | D379: 28/12/2025 | E379: 06/01/2026 | F379: Arjun Rao | G379: Male | H379: 17/09/1976 | I379: Kolkata | J379: East | K379: Electronics | L379: Keyboard | M379: 9 | N379: 1200 | O379: 15 | P379: 9180 | Q379: 1 | R379: UPI | S379: Ritika | T379: arjun.rao@company.com | U379: 9450746157 | V379: Pending
A380: ORD10379 | B380: C007 | C380: P302 | D380: 01/10/2025 | E380: 03/10/2025 | F380: Arjun Rao | G380: Male | H380: 22/12/1996 | I380: Jaipur | J380: North | K380: Stationery | L380: Pen | M380: 3 | N380: 20 | O380: 15 | P380: 51 | Q380: 3 | R380: Cash | S380: Neha | T380: arjun.rao@company.com | U380: 9349012570 | V380: Pending
A381: ORD10380 | B381: C006 | C381: P101 | D381: 18/12/2025 | E381: 19/12/2025 | F381: Sneha Joshi | G381: Female | H381: 25/12/1995 | I381: Delhi | J381: North | K381: Electronics | L381: Laptop | M381: 8 | N381: 55000 | O381: 20 | P381: 352000 | Q381: 5 | R381: Card | S381: Karan | T381: sneha.joshi@company.com | U381: 9442163790 | V381: Pending
A382: ORD10381 | B382: C006 | C382: P301 | D382: 29/09/2025 | E382: 07/10/2025 | F382: Sneha Joshi | G382: Female | H382: 23/06/1985 | I382: Delhi | J382: North | K382: Stationery | L382: Notebook | M382: 17 | N382: 60 | O382: 20 | P382: 816 | Q382: 1 | R382: UPI | S382: Ritika | T382: sneha.joshi@company.com | U382: 9953329223 | V382: Pending
A383: ORD10382 | B383: C003 | C383: P302 | D383: 14/05/2025 | E383: 22/05/2025 | F383: Rohit Singh | G383: Male | H383: 10/02/1984 | I383: Bengaluru | J383: South | K383: Stationery | L383: Pen | M383: 4 | N383: 20 | O383: 15 | P383: 68 | Q383: 3 | R383: NetBanking | S383: Aisha | T383: rohit.singh@company.com | U383: 9202321359 | V383: Pending
... A399: ORD10398 | B399: C007 | C399: P104 | D399: 31/01/2025 | E399: 04/02/2025 | F399: Arjun Rao | G399: Male | H399: 10/12/1978 | I399: Kolkata | J399: East | K399: Electronics | L399: Monitor | M399: 19 | N399: 12000 | O399: 0 | P399: 228000 | Q399: 4 | R399: UPI | S399: Aisha | T399: arjun.rao@company.com | U399: 9136906750 | V399: Pending
A400: ORD10399 | B400: C001 | C400: P102 | E400: 03/11/2025 | F400: Amit Sharma | G400: Male | H400: 01/09/1979 | I400: Bengaluru | J400: South | K400: Electronics | L400: Mouse | M400: 12 | N400: 700 | O400: 15 | P400: 7140 | Q400: 3 | R400: Card | S400: Ritika | T400: amit.sharma@company.com | U400: 9485286324 | V400: Completed
A401: ORD10400 | B401: C008 | C401: P103 | D401: 13/05/2025 | E401: 21/05/2025 | F401: Kavya Nair | G401: Female | H401: 08/04/2001 | I401: Delhi | J401: North | K401: Electronics | L401: Keyboard | M401: 16 | N401: 1200 | O401: 20 | P401: 15360 | Q401: 1 | R401: Cash | S401: Rahul | T401: kavya.nair@company.com | U401: 9414633966 | V401: Pending
A402: ORD10401 | B402: C009 | C402: P203 | D402: 27/12/2025 | E402: 04/01/2026 | F402: Mohit Verma | G402: Male | H402: 01/01/1983 | I402: Hyderabad | J402: South | K402: Home Appliances | L402: Microwave | M402: 10 | N402: 8500 | O402: 5 | P402: 80750 | Q402: 5 | R402: NetBanking | S402: Ritika | T402: mohit.verma@company.com | U402: 9833735234 | V402: Completed
A403: ORD10402 | B403: C008 | C403: P302 | D403: 11/02/2025 | E403: 21/02/2025 | F403: Kavya Nair | G403: Female | H403: 09/08/1989 | I403: Ahmedabad | J403: West | K403: Stationery | L403: Pen | M403: 18 | N403: 20 | O403: 20 | P403: 288 | Q403: 1 | R403: UPI | S403: Ritika | T403: kavya.nair@company.com | U403: 9523689108 | V403: Pending
A404: ORD10403 | B404: C009 | C404: P203 | D404: 13/03/2026 | E404: 19/03/2026 | F404: Mohit Verma | G404: Male | H404: 22/10/1993 | I404: Mumbai | J404: West | K404: Home Appliances | L404: Microwave | M404: 9 | N404: 8500 | O404: 0 | P404: 76500 | Q404: 2 | R404: Card | S404: Ritika | T404: mohit.verma@company.com | U404: 9812909831 | V404: Pending
A405: ORD10404 | B405: C008 | C405: P203 | D405: 01/10/2025 | E405: 12/10/2025 | F405: Kavya Nair | G405: Female | H405: 05/05/2000 | I405: Mumbai | J405: West | K405: Home Appliances | L405: Microwave | M405: 8 | N405: 8500 | O405: 10 | P405: 61200 | Q405: 4 | R405: Cash | S405: Neha | T405: kavya.nair@company.com | U405: 9106290987 | V405: Cancelled
...

Sheet Product_Master
A1: Product_ID | B1: Product_Name | C1: Category | D1: Supplier | E1: Cost_Price | F1: Warranty_Months
A2: P101 | B2: Laptop | C2: Electronics | D2: TechHub | E2: 41250 | F2: 12
A3: P102 | B3: Mouse | C3: Electronics | D3: TechHub | E3: 525 | F3: 24
A4: P103 | B4: Keyboard | C4: Electronics | D4: TechHub | E4: 900 | F4: 6
A5: P104 | B5: Monitor | C5: Electronics | D5: Global Trade | E5: 9000 | F5: 24
A6: P201 | B6: Mixer | C6: Home Appliances | D6: Global Trade | E6: 2625 | F6: 6
A7: P202 | B7: Iron | C7: Home Appliances | D7: Global Trade | E7: 1650 | F7: 24
A8: P203 | B8: Microwave | C8: Home Appliances | D8: TechHub | E8: 6375 | F8: 24
A9: P301 | B9: Notebook | C9: Stationery | D9: ABC Corp | E9: 45 | F9: 12
A10: P302 | B10: Pen | C10: Stationery | D10: Prime Supplies | E10: 15 | F10: 12
A11: P303 | B11: Marker | C11: Stationery | D11: TechHub | E11: 33.75 | F11: 12

Sheet Custumer_Master
A1: Customer_ID | B1: Customer_Name | C1: Membership | D1: State | F1: Gender | G1: DOB | H1: Email | I1: City | J1: Region | K1: Birthday Month
A2: C001 | B2: Amit Sharma | C2: Silver | D2: RJ | F2: =VLOOKUP($A2,Sales_data!$B:$V,6,FALSE) -> Male | G2: =VLOOKUP($A2,Sales_data!$B:$V,7,FALSE) -> 09/08/1991 | H2: =VLOOKUP($A2,Sales_data!$B:$V,19,FALSE) -> amit.sharma@company.com | I2: =VLOOKUP($A2,Sales_data!$B:$V,8,FALSE) -> Pune | J2: =VLOOKUP($A2,Sales_data!$B:$V,9,FALSE) -> West | K2: =TEXT(IFERROR(DATEVALUE(G2), G2), "mmmm") -> August
A3: C002 | B3: Priya Patel | C3: Platinum | D3: WB | F3: =VLOOKUP($A3,Sales_data!$B:$V,6,FALSE) -> Female | G3: =VLOOKUP($A3,Sales_data!$B:$V,7,FALSE) -> 07/03/1995 | H3: =VLOOKUP($A3,Sales_data!$B:$V,19,FALSE) -> priYa.patel@company.com | I3: =VLOOKUP($A3,Sales_data!$B:$V,8,FALSE) -> Mumbai | J3: =VLOOKUP($A3,Sales_data!$B:$V,9,FALSE) -> West | K3: =TEXT(IFERROR(DATEVALUE(G3), G3), "mmmm") -> March
A4: C003 | B4: Rohit Singh | C4: Gold | D4: DL | F4: =VLOOKUP($A4,Sales_data!$B:$V,6,FALSE) -> Male | G4: =VLOOKUP($A4,Sales_data!$B:$V,7,FALSE) -> 10/05/1982 | H4: =VLOOKUP($A4,Sales_data!$B:$V,19,FALSE) -> rohit.singh@company.com | I4: =VLOOKUP($A4,Sales_data!$B:$V,8,FALSE) -> Delhi | J4: =VLOOKUP($A4,Sales_data!$B:$V,9,FALSE) -> North | K4: =TEXT(IFERROR(DATEVALUE(G4), G4), "mmmm") -> May
A5: C004 | B5: Anita Gupta | C5: Gold | D5: WB | F5: =VLOOKUP($A5,Sales_data!$B:$V,6,FALSE) -> Female | G5: =VLOOKUP($A5,Sales_data!$B:$V,7,FALSE) -> 16/01/2002 | H5: =VLOOKUP($A5,Sales_data!$B:$V,19,FALSE) -> anita.gupta@company.com | I5: =VLOOKUP($A5,Sales_data!$B:$V,8,FALSE) -> Pune | J5: =VLOOKUP($A5,Sales_data!$B:$V,9,FALSE) -> West | K5: =TEXT(IFERROR(DATEVALUE(G5), G5), "mmmm") -> January
A6: C005 | B6: Vikas Mehta | C6: Gold | D6: DL | F6: =VLOOKUP($A6,Sales_data!$B:$V,6,FALSE) -> Male | G6: =VLOOKUP($A6,Sales_data!$B:$V,7,FALSE) -> 03/08/1991 | H6: =VLOOKUP($A6,Sales_data!$B:$V,19,FALSE) -> vikas.mehta@company.com | I6: =VLOOKUP($A6,Sales_data!$B:$V,8,FALSE) -> Mumbai | J6: =VLOOKUP($A6,Sales_data!$B:$V,9,FALSE) -> West | K6: =TEXT(IFERROR(DATEVALUE(G6), G6), "mmmm") -> August
A7: C006 | B7: Sneha Joshi | C7: Gold | D7: WB | F7: =VLOOKUP($A7,Sales_data!$B:$V,6,FALSE) -> Female | G7: =VLOOKUP($A7,Sales_data!$B:$V,7,FALSE) -> 04/04/1981 | H7: =VLOOKUP($A7,Sales_data!$B:$V,19,FALSE) -> sneha.joshi@company.com | I7: =VLOOKUP($A7,Sales_data!$B:$V,8,FALSE) -> Pune | J7: =VLOOKUP($A7,Sales_data!$B:$V,9,FALSE) -> West | K7: =TEXT(IFERROR(DATEVALUE(G7), G7), "mmmm") -> April
A8: C007 | B8: Arjun Rao | C8: Silver | D8: RJ | F8: =VLOOKUP($A8,Sales_data!$B:$V,6,FALSE) -> Male | G8: =VLOOKUP($A8,Sales_data!$B:$V,7,FALSE) -> 07/02/1988 | H8: =VLOOKUP($A8,Sales_data!$B:$V,19,FALSE) -> arjun.rao@company.com | I8: =VLOOKUP($A8,Sales_data!$B:$V,8,FALSE) -> Hyderabad | J8: =VLOOKUP($A8,Sales_data!$B:$V,9,FALSE) -> South | K8: =TEXT(IFERROR(DATEVALUE(G8), G8), "mmmm") -> February
A9: C008 | B9: Kavya Nair | C9: Silver | D9: WB | F9: =VLOOKUP($A9,Sales_data!$B:$V,6,FALSE) -> Female | G9: =VLOOKUP($A9,Sales_data!$B:$V,7,FALSE) -> 01/08/1976 | H9: =VLOOKUP($A9,Sales_data!$B:$V,19,FALSE) -> KAvya.nair@company.com | I9: =VLOOKUP($A9,Sales_data!$B:$V,8,FALSE) -> Hyderabad | J9: =VLOOKUP($A9,Sales_data!$B:$V,9,FALSE) -> South | K9: =TEXT(IFERROR(DATEVALUE(G9), G9), "mmmm") -> August
A10: C009 | B10: Mohit Verma | C10: Platinum | D10: KA | F10: =VLOOKUP($A10,Sales_data!$B:$V,6,FALSE) -> Male | G10: =VLOOKUP($A10,Sales_data!$B:$V,7,FALSE) -> 13/04/1976 | H10: =VLOOKUP($A10,Sales_data!$B:$V,19,FALSE) -> mohit.verma@company.com | I10: =VLOOKUP($A10,Sales_data!$B:$V,8,FALSE) -> Delhi | J10: =VLOOKUP($A10,Sales_data!$B:$V,9,FALSE) -> North | K10: =TEXT(IFERROR(DATEVALUE(G10), G10), "mmmm") -> April
A11: C010 | B11: Pooja Shah | C11: Silver | D11: WB | F11: =VLOOKUP($A11,Sales_data!$B:$V,6,FALSE) -> Female | G11: =VLOOKUP($A11,Sales_data!$B:$V,7,FALSE) -> 16/09/1994 | H11: =VLOOKUP($A11,Sales_data!$B:$V,19,FALSE) -> pooja.shah@company.com | I11: =VLOOKUP($A11,Sales_data!$B:$V,8,FALSE) -> Bengaluru | J11: =VLOOKUP($A11,Sales_data!$B:$V,9,FALSE) -> South | K11: =TEXT(IFERROR(DATEVALUE(G11), G11), "mmmm") -> September

Sheet Data Cleaning
A1: CLEAN AND MODIFY RAW DATA TO INFORMATION - Pre Requiste Work on - "Complie Data"
A21: Table 1 | C21: Table 2 | E21: Table 3 | G21: Apllied Cleaning And Modification
G22: Changes Done on Coloumn | H22: Changes Done | I22: Result | J22: Format
A23: Sales_Data | C23: Product_Master | E23: Custumer_Master | G23: Order_ID | H23: Replacing second Repated Order ID ORD10002 with ORD10004 & Replacing second Repated Order ID ORD10020 with ORD10049 | I23: 2 Values are not Unique - (ORD10002 & ORD10020) | J23: Genral
G24: Customer_ID | H24: - | I24: All values are in foramt | J24: Genral
G25: Product_ID | H25: - | I25: All values are in foramt | J25: Genral
G26: Order_Date | H26: Foramt Change - Missing Dates | I26: Format Changed from genral to Date | J26: Date
G27: Delivery_Date | H27: Foramt Change - Missing Dates | I27: Format Changed from genral to Date | J27: Date
G28: Customer_Name | H28: Trim and Proper | I28: Alligning all the data and removing extra spaces | J28: Genral
G29: Gender | H29: Trim and Proper | I29: Alligning all the data and removing extra spaces | J29: Genral
G30: DOB | H30: Foramt Change - Missing Dates - Mapped with help of Custumer ID | I30: Format Changed from genral to Date | J30: Date
G31: City | H31: Trim and Proper - Missing Values - Remapped with Custumer Master | I31: Alligning all the data and removing extra spaces | J31: Genral
G32: Region | H32: Trim and Proper - Missing Values - Remapped with Custumer Master | I32: Alligning all the data and removing extra spaces | J32: Genral
G33: Category | H33: Trim and Proper - Re mapped as per Product Master | I33: Alligning all the data and removing extra spaces and Spelling Mistakes | J33: Genral
G34: Product_Name | H34: Trim and Proper - Re mapped as per Product Master | I34: Alligning all the data and removing extra spaces | J34: Genral
G35: Quantity | H35: Data Validation - and fourmula used to remove negative and text numbers | I35: All numbers in between 1 to 50 | J35: Number
... G43: Phone | H43: Used if statement with trim but still 1 number is invalid | I43: Foramt Change | J43: Number

Sheet Final Data
A1: Order_ID | B1: Customer_ID | C1: Product_ID | D1: Order_Date | E1: Delivery_Date | F1: Customer_Name | G1: Gender | H1: DOB | I1: City | J1: Region | K1: State | L1: Category | M1: Product_Name_Final | N1: Quantity | O1: Unit_Price | P1: Discount_% | Q1: New Sales Calculation | R1: Rating | S1: Payment_Mode | T1: Salesperson | U1: Email | V1: Phone | W1: Supplier | X1: Warranty_Months | Y1: Membership | Z1: Warranty_Till(Months) | AA1: Birthday Month | AB1: Custumer Classification | AC1: Custumer Code | AD1: Customer Age | AE1: Delivery Time (Days) | AF1: Delivery Status | AG1: Order Status
A2: ORD10001 | B2: C008 | C2: P202 | D2: 45918 | E2: 22/09/2025 | F2: =VLOOKUP(B2,Custumer_Master!A:D,2,FALSE) -> Kavya Nair | G2: =VLOOKUP($B2,Custumer_Master!$A:$J,6,FALSE) -> Female | H2: =VLOOKUP($B2,Custumer_Master!$A:$J,7,FALSE) -> 01/08/1976 | I2: =VLOOKUP($B2,Custumer_Master!$A:$J,9,FALSE) -> Hyderabad | J2: =VLOOKUP($B2,Custumer_Master!$A:$J,10,FALSE) -> South | K2: =VLOOKUP(B2,Custumer_Master!A:D,4,FALSE) -> WB | L2: =PROPER(TRIM(VLOOKUP('Final Data'!C2,Product_Master!A:F,3,FALSE))) -> Home Appliances | M2: Iron | N2: 4 | O2: =VLOOKUP(C2,Product_Master!A:F,5,FALSE) -> 1650 | P2: 0.1 | Q2: =(N2*O2)-(N2*O2)*P2 -> 5940 | R2: 4 | S2: Cash | T2: Ritika | U2: kavya.nair@company.com | V2: 9431429797 | W2: =VLOOKUP(C2,Product_Master!A:F,4,FALSE) -> Global Trade | X2: =VLOOKUP(C2,Product_Master!A:F,6,FALSE) -> 24 | Y2: =VLOOKUP(B2,Custumer_Master!A:D,3,FALSE) -> Silver | Z2: =EDATE(E2,X2) -> 46652 | AA2: =VLOOKUP(B2,Custumer_Master!A:K,11,) -> August | AB2: Silver | AC2: =PROPER(LEFT(TRIM(F2), 3)) & RIGHT(TRIM(B2), 3) & PROPER(LEFT(TRIM(I2), 2)) -> Kav008Hy | AD2: =DATEDIF(H2, TODAY(), "Y") -> 49 | AE2: =IFERROR(IF(OR(E2="", D2="", LOWER(TRIM(E2))="pending", LOWER(TRIM(D2))="pending"), "Pending", E2 - D2), "Pending") -> 4 | AF2: =IFERROR(IF(OR(E2="", D2="","Pending","Pending"), "Pending", IF((E2 - D2) <= 5, "On Time", "Delayed")), "Pending") -> On Time | AG2: =IF(AF2="Pending","Pending","Completed") -> Completed
A3: ORD10002 | B3: C008 | C3: P104 | D3: 45774 | E3: 04/05/2025 | F3: =VLOOKUP(B3,Custumer_Master!A:D,2,FALSE) -> Kavya Nair | G3: =VLOOKUP($B3,Custumer_Master!$A:$J,6,FALSE) -> Female | H3: =VLOOKUP($B3,Custumer_Master!$A:$J,7,FALSE) -> 01/08/1976 | I3: =VLOOKUP($B3,Custumer_Master!$A:$J,9,FALSE) -> Hyderabad | J3: =VLOOKUP($B3,Custumer_Master!$A:$J,10,FALSE) -> South | K3: =VLOOKUP(B3,Custumer_Master!A:D,4,FALSE) -> WB | L3: =PROPER(TRIM(VLOOKUP('Final Data'!C3,Product_Master!A:F,3,FALSE))) -> Electronics | M3: Monitor | N3: 17 | O3: =VLOOKUP(C3,Product_Master!A:F,5,FALSE) -> 9000 | P3: 0.1 | Q3: =(N3*O3)-(N3*O3)*P3 -> 137700 | R3: 1 | S3: Netbanking | T3: Rahul | U3: kavya.nair@company.com | V3: 9129865339 | W3: =VLOOKUP(C3,Product_Master!A:F,4,FALSE) -> Global Trade | X3: =VLOOKUP(C3,Product_Master!A:F,6,FALSE) -> 24 | Y3: =VLOOKUP(B3,Custumer_Master!A:D,3,FALSE) -> Silver | Z3: =EDATE(E3,X3) -> 46511 | AA3: =VLOOKUP(B3,Custumer_Master!A:K,11,) -> August | AB3: Blacklisted | AC3: =PROPER(LEFT(TRIM(F3), 3)) & RIGHT(TRIM(B3), 3) & PROPER(LEFT(TRIM(I3), 2)) -> Kav008Hy | AD3: =DATEDIF(H3, TODAY(), "Y") -> 49 | AE3: =IFERROR(IF(OR(E3="", D3="", LOWER(TRIM(E3))="pending", LOWER(TRIM(D3))="pending"), "Pending", E3 - D3), "Pending") -> 7 | AF3: =IFERROR(IF(OR(E3="", D3="","Pending","Pending"), "Pending", IF((E3 - D3) <= 5, "On Time", "Delayed")), "Pending") -> Delayed | AG3: =IF(AF3="Pending","Pending","Completed") -> Completed
A4: ORD10003 | B4: C010 | C4: P101 | D4: 45903 | E4: 14/09/2025 | F4: =VLOOKUP(B4,Custumer_Master!A:D,2,FALSE) -> Pooja Shah | G4: =VLOOKUP($B4,Custumer_Master!$A:$J,6,FALSE) -> Female | H4: =VLOOKUP($B4,Custumer_Master!$A:$J,7,FALSE) -> 16/09/1994 | I4: =VLOOKUP($B4,Custumer_Master!$A:$J,9,FALSE) -> Bengaluru | J4: =VLOOKUP($B4,Custumer_Master!$A:$J,10,FALSE) -> South | K4: =VLOOKUP(B4,Custumer_Master!A:D,4,FALSE) -> WB | L4: =PROPER(TRIM(VLOOKUP('Final Data'!C4,Product_Master!A:F,3,FALSE))) -> Electronics | M4: Laptop | N4: 5 | O4: =VLOOKUP(C4,Product_Master!A:F,5,FALSE) -> 41250 | P4: 0.05 | Q4: =(N4*O4)-(N4*O4)*P4 -> 195937.5 | R4: 3 | S4: Netbanking | T4: Aisha | U4: pooja.shah@company.com | V4: 9380975626 | W4: =VLOOKUP(C4,Product_Master!A:F,4,FALSE) -> TechHub | X4: =VLOOKUP(C4,Product_Master!A:F,6,FALSE) -> 12 | Y4: =VLOOKUP(B4,Custumer_Master!A:D,3,FALSE) -> Silver | Z4: =EDATE(E4,X4) -> 46279 | AA4: =VLOOKUP(B4,Custumer_Master!A:K,11,) -> September | AB4: Gold | AC4: =PROPER(LEFT(TRIM(F4), 3)) & RIGHT(TRIM(B4), 3) & PROPER(LEFT(TRIM(I4), 2)) -> Poo010Be | AD4: =DATEDIF(H4, TODAY(), "Y") -> 31 | AE4: =IFERROR(IF(OR(E4="", D4="", LOWER(TRIM(E4))="pending", LOWER(TRIM(D4))="pending"), "Pending", E4 - D4), "Pending") -> 11 | AF4: =IFERROR(IF(OR(E4="", D4="","Pending","Pending"), "Pending", IF((E4 - D4) <= 5, "On Time", "Delayed")), "Pending") -> Delayed | AG4: =IF(AF4="Pending","Pending","Completed") -> Completed
A5: ORD10004 | B5: C008 | C5: P202 | D5: 46102 | E5: 02/04/2026 | F5: =VLOOKUP(B5,Custumer_Master!A:D,2,FALSE) -> Kavya Nair | G5: =VLOOKUP($B5,Custumer_Master!$A:$J,6,FALSE) -> Female | H5: =VLOOKUP($B5,Custumer_Master!$A:$J,7,FALSE) -> 01/08/1976 | I5: =VLOOKUP($B5,Custumer_Master!$A:$J,9,FALSE) -> Hyderabad | J5: =VLOOKUP($B5,Custumer_Master!$A:$J,10,FALSE) -> South | K5: =VLOOKUP(B5,Custumer_Master!A:D,4,FALSE) -> WB | L5: =PROPER(TRIM(VLOOKUP('Final Data'!C5,Product_Master!A:F,3,FALSE))) -> Home Appliances | M5: Iron | N5: 5 | O5: =VLOOKUP(C5,Product_Master!A:F,5,FALSE) -> 1650 | P5: 0.05 | Q5: =(N5*O5)-(N5*O5)*P5 -> 7837.5 | R5: 5 | S5: Netbanking | T5: Aisha | U5: kavya.nair@company.com | V5: 9600261125 | W5: =VLOOKUP(C5,Product_Master!A:F,4,FALSE) -> Global Trade | X5: =VLOOKUP(C5,Product_Master!A:F,6,FALSE) -> 24 | Y5: =VLOOKUP(B5,Custumer_Master!A:D,3,FALSE) -> Silver | Z5: =EDATE(E5,X5) -> 46845 | AA5: =VLOOKUP(B5,Custumer_Master!A:K,11,) -> August | AB5: Silver | AC5: =PROPER(LEFT(TRIM(F5), 3)) & RIGHT(TRIM(B5), 3) & PROPER(LEFT(TRIM(I5), 2)) -> Kav008Hy | AD5: =DATEDIF(H5, TODAY(), "Y") -> 49 | AE5: =IFERROR(IF(OR(E5="", D5="", LOWER(TRIM(E5))="pending", LOWER(TRIM(D5))="pending"), "Pending", E5 - D5), "Pending") -> 12 | AF5: =IFERROR(IF(OR(E5="", D5="","Pending","Pending"), "Pending", IF((E5 - D5) <= 5, "On Time", "Delayed")), "Pending") -> Delayed | AG5: =IF(AF5="Pending","Pending","Completed") -> Completed
A6: ORD10005 | B6: C009 | C6: P103 | D6: 45927 | E6: 07/10/2025 | F6: =VLOOKUP(B6,Custumer_Master!A:D,2,FALSE) -> Mohit Verma | G6: =VLOOKUP($B6,Custumer_Master!$A:$J,6,FALSE) -> Male | H6: =VLOOKUP($B6,Custumer_Master!$A:$J,7,FALSE) -> 13/04/1976 | I6: =VLOOKUP($B6,Custumer_Master!$A:$J,9,FALSE) -> Delhi | J6: =VLOOKUP($B6,Custumer_Master!$A:$J,10,FALSE) -> North | K6: =VLOOKUP(B6,Custumer_Master!A:D,4,FALSE) -> KA | L6: =PROPER(TRIM(VLOOKUP('Final Data'!C6,Product_Master!A:F,3,FALSE))) -> Electronics | M6: Keyboard | N6: 8 | O6: =VLOOKUP(C6,Product_Master!A:F,5,FALSE) -> 900 | P6: 0.05 | Q6: =(N6*O6)-(N6*O6)*P6 -> 6840 | R6: 2 | S6: Card | T6: Aisha | U6: mohit.verma@company.com | V6: 9724635978 | W6: =VLOOKUP(C6,Product_Master!A:F,4,FALSE) -> TechHub | X6: =VLOOKUP(C6,Product_Master!A:F,6,FALSE) -> 6 | Y6: =VLOOKUP(B6,Custumer_Master!A:D,3,FALSE) -> Platinum | Z6: =EDATE(E6,X6) -> 46119 | AA6: =VLOOKUP(B6,Custumer_Master!A:K,11,) -> April | AB6: Blacklisted | AC6: =PROPER(LEFT(TRIM(F6), 3)) & RIGHT(TRIM(B6), 3) & PROPER(LEFT(TRIM(I6), 2)) -> Moh009De | AD6: =DATEDIF(H6, TODAY(), "Y") -> 50 | AE6: =IFERROR(IF(OR(E6="", D6="", LOWER(TRIM(E6))="pending", LOWER(TRIM(D6))="pending"), "Pending", E6 - D6), "Pending") -> 10 | AF6: =IFERROR(IF(OR(E6="", D6="","Pending","Pending"), "Pending", IF((E6 - D6) <= 5, "On Time", "Delayed")), "Pending") -> Delayed | AG6: =IF(AF6="Pending","Pending","Completed") -> Completed
A7: ORD10006 | B7: C007 | C7: P202 | D7: 46026 | E7: 12/01/2026 | F7: =VLOOKUP(B7,Custumer_Master!A:D,2,FALSE) -> Arjun Rao | G7: =VLOOKUP($B7,Custumer_Master!$A:$J,6,FALSE) -> Male | H7: =VLOOKUP($B7,Custumer_Master!$A:$J,7,FALSE) -> 07/02/1988 | I7: =VLOOKUP($B7,Custumer_Master!$A:$J,9,FALSE) -> Hyderabad | J7: =VLOOKUP($B7,Custumer_Master!$A:$J,10,FALSE) -> South | K7: =VLOOKUP(B7,Custumer_Master!A:D,4,FALSE) -> RJ | L7: =PROPER(TRIM(VLOOKUP('Final Data'!C7,Product_Master!A:F,3,FALSE))) -> Home Appliances | M7: Iron | N7: 4 | O7: =VLOOKUP(C7,Product_Master!A:F,5,FALSE) -> 1650 | P7: 0 | Q7: =(N7*O7)-(N7*O7)*P7 -> 6600 | R7: 1 | S7: Upi | T7: Ritika | U7: arjun.rao@company.com | V7: 9780584905 | W7: =VLOOKUP(C7,Product_Master!A:F,4,FALSE) -> Global Trade | X7: =VLOOKUP(C7,Product_Master!A:F,6,FALSE) -> 24 | Y7: =VLOOKUP(B7,Custumer_Master!A:D,3,FALSE) -> Silver | Z7: =EDATE(E7,X7) -> 46764 | AA7: =VLOOKUP(B7,Custumer_Master!A:K,11,) -> February | AB7: Blacklisted | AC7: =PROPER(LEFT(TRIM(F7), 3)) & RIGHT(TRIM(B7), 3) & PROPER(LEFT(TRIM(I7), 2)) -> Arj007Hy | AD7: =DATEDIF(H7, TODAY(), "Y") -> 38 | AE7: =IFERROR(IF(OR(E7="", D7="", LOWER(TRIM(E7))="pending", LOWER(TRIM(D7))="pending"), "Pending", E7 - D7), "Pending") -> 8 | AF7: =IFERROR(IF(OR(E7="", D7="","Pending","Pending"), "Pending", IF((E7 - D7) <= 5, "On Time", "Delayed")), "Pending") -> Delayed | AG7: =IF(AF7="Pending","Pending","Completed") -> Completed
A8: ORD10007 | B8: C008 | C8: P201 | D8: 31/02/2025 | E8: 25/02/2026 | F8: =VLOOKUP(B8,Custumer_Master!A:D,2,FALSE) -> Kavya Nair | G8: =VLOOKUP($B8,Custumer_Master!$A:$J,6,FALSE) -> Female | H8: =VLOOKUP($B8,Custumer_Master!$A:$J,7,FALSE) -> 01/08/1976 | I8: =VLOOKUP($B8,Custumer_Master!$A:$J,9,FALSE) -> Hyderabad | J8: =VLOOKUP($B8,Custumer_Master!$A:$J,10,FALSE) -> South | K8: =VLOOKUP(B8,Custumer_Master!A:D,4,FALSE) -> WB | L8: =PROPER(TRIM(VLOOKUP('Final Data'!C8,Product_Master!A:F,3,FALSE))) -> Home Appliances | M8: Mixer | N8: 2 | O8: =VLOOKUP(C8,Product_Master!A:F,5,FALSE) -> 2625 | P8: 0.05 | Q8: =(N8*O8)-(N8*O8)*P8 -> 4987.5 | R8: 1 | S8: Upi | T8: Ritika | U8: kavya.nair@company.com | V8: 9958252176 | W8: =VLOOKUP(C8,Product_Master!A:F,4,FALSE) -> Global Trade | X8: =VLOOKUP(C8,Product_Master!A:F,6,FALSE) -> 6 | Y8: =VLOOKUP(B8,Custumer_Master!A:D,3,FALSE) -> Silver | Z8: =EDATE(E8,X8) -> 46259 | AA8: =VLOOKUP(B8,Custumer_Master!A:K,11,) -> August | AB8: Blacklisted | AC8: =PROPER(LEFT(TRIM(F8), 3)) & RIGHT(TRIM(B8), 3) & PROPER(LEFT(TRIM(I8), 2)) -> Kav008Hy | AD8: =DATEDIF(H8, TODAY(), "Y") -> 49 | AE8: =IFERROR(IF(OR(E8="", D8="", LOWER(TRIM(E8))="pending", LOWER(TRIM(D8))="pending"), "Pending", E8 - D8), "Pending") -> Pending | AF8: =IFERROR(IF(OR(E8="", D8="","Pending","Pending"), "Pending", IF((E8 - D8) <= 5, "On Time", "Delayed")), "Pending") -> Pending | AG8: =IF(AF8="Pending","Pending","Completed") -> Pending
A9: ORD10008 | B9: C002 | C9: P104 | D9: 45760 | E9: 19/04/2025 | F9: =VLOOKUP(B9,Custumer_Master!A:D,2,FALSE) -> Priya Patel | G9: =VLOOKUP($B9,Custumer_Master!$A:$J,6,FALSE) -> Female | H9: =VLOOKUP($B9,Custumer_Master!$A:$J,7,FALSE) -> 07/03/1995 | I9: =VLOOKUP($B9,Custumer_Master!$A:$J,9,FALSE) -> Mumbai | J9: =VLOOKUP($B9,Custumer_Master!$A:$J,10,FALSE) -> West | K9: =VLOOKUP(B9,Custumer_Master!A:D,4,FALSE) -> WB | L9: =PROPER(TRIM(VLOOKUP('Final Data'!C9,Product_Master!A:F,3,FALSE))) -> Electronics | M9: Monitor | N9: 14 | O9: =VLOOKUP(C9,Product_Master!A:F,5,FALSE) -> 9000 | P9: 0.15 | Q9: =(N9*O9)-(N9*O9)*P9 -> 107100 | R9: 4 | S9: Netbanking | T9: Ritika | U9: priya.patel@company.com | V9: 9705521654 | W9: =VLOOKUP(C9,Product_Master!A:F,4,FALSE) -> Global Trade | X9: =VLOOKUP(C9,Product_Master!A:F,6,FALSE) -> 24 | Y9: =VLOOKUP(B9,Custumer_Master!A:D,3,FALSE) -> Platinum | Z9: =EDATE(E9,X9) -> 46496 | AA9: =VLOOKUP(B9,Custumer_Master!A:K,11,) -> March | AB9: Gold | AC9: =PROPER(LEFT(TRIM(F9), 3)) & RIGHT(TRIM(B9), 3) & PROPER(LEFT(TRIM(I9), 2)) -> Pri002Mu | AD9: =DATEDIF(H9, TODAY(), "Y") -> 31 | AE9: =IFERROR(IF(OR(E9="", D9="", LOWER(TRIM(E9))="pending", LOWER(TRIM(D9))="pending"), "Pending", E9 - D9), "Pending") -> 6 | AF9: =IFERROR(IF(OR(E9="", D9="","Pending","Pending"), "Pending", IF((E9 - D9) <= 5, "On Time", "Delayed")), "Pending") -> Delayed | AG9: =IF(AF9="Pending","Pending","Completed") -> Completed
A10: ORD10009 | B10: C008 | C10: P104 | D10: 46053 | E10: 02/02/2026 | F10: =VLOOKUP(B10,Custumer_Master!A:D,2,FALSE) -> Kavya Nair | G10: =VLOOKUP($B10,Custumer_Master!$A:$J,6,FALSE) -> Female | H10: =VLOOKUP($B10,Custumer_Master!$A:$J,7,FALSE) -> 01/08/1976 | I10: =VLOOKUP($B10,Custumer_Master!$A:$J,9,FALSE) -> Hyderabad | J10: =VLOOKUP($B10,Custumer_Master!$A:$J,10,FALSE) -> South | K10: =VLOOKUP(B10,Custumer_Master!A:D,4,FALSE) -> WB | L10: =PROPER(TRIM(VLOOKUP('Final Data'!C10,Product_Master!A:F,3,FALSE))) -> Electronics | M10: Monitor | N10: 4 | O10: =VLOOKUP(C10,Product_Master!A:F,5,FALSE) -> 9000 | P10: 0.15 | Q10: =(N10*O10)-(N10*O10)*P10 -> 30600 | R10: 4 | S10: Upi | T10: Neha | U10: kavya.nair@company.com | V10: 9588041011 | W10: =VLOOKUP(C10,Product_Master!A:F,4,FALSE) -> Global Trade | X10: =VLOOKUP(C10,Product_Master!A:F,6,FALSE) -> 24 | Y10: =VLOOKUP(B10,Custumer_Master!A:D,3,FALSE) -> Silver | Z10: =EDATE(E10,X10) -> 46785 | AA10: =VLOOKUP(B10,Custumer_Master!A:K,11,) -> August | AB10: Silver | AC10: =PROPER(LEFT(TRIM(F10), 3)) & RIGHT(TRIM(B10), 3) & PROPER(LEFT(TRIM(I10), 2)) -> Kav008Hy | AD10: =DATEDIF(H10, TODAY(), "Y") -> 49 | AE10: =IFERROR(IF(OR(E10="", D10="", LOWER(TRIM(E10))="pending", LOWER(TRIM(D10))="pending"), "Pending", E10 - D10), "Pending") -> 2 | AF10: =IFERROR(IF(OR(E10="", D10="","Pending","Pending"), "Pending", IF((E10 - D10) <= 5, "On Time", "Delayed")), "Pending") -> On Time | AG10: =IF(AF10="Pending","Pending","Completed") -> Completed
A11: ORD10010 | B11: C002 | C11: P301 | D11: 45741 | E11: 27/03/2025 | F11: =VLOOKUP(B11,Custumer_Master!A:D,2,FALSE) -> Priya Patel | G11: =VLOOKUP($B11,Custumer_Master!$A:$J,6,FALSE) -> Female | H11: =VLOOKUP($B11,Custumer_Master!$A:$J,7,FALSE) -> 07/03/1995 | I11: =VLOOKUP($B11,Custumer_Master!$A:$J,9,FALSE) -> Mumbai | J11: =VLOOKUP($B11,Custumer_Master!$A:$J,10,FALSE) -> West | K11: =VLOOKUP(B11,Custumer_Master!A:D,4,FALSE) -> WB | L11: =PROPER(TRIM(VLOOKUP('Final Data'!C11,Product_Master!A:F,3,FALSE))) -> Stationery | M11: Notebook | N11: 6 | O11: =VLOOKUP(C11,Product_Master!A:F,5,FALSE) -> 45 | P11: 0 | Q11: =(N11*O11)-(N11*O11)*P11 -> 270 | R11: 4 | S11: Card | T11: Neha | U11: priya.patel@company.com | V11: 9340540608 | W11: =VLOOKUP(C11,Product_Master!A:F,4,FALSE) -> ABC Corp | X11: =VLOOKUP(C11,Product_Master!A:F,6,FALSE) -> 12 | Y11: =VLOOKUP(B11,Custumer_Master!A:D,3,FALSE) -> Platinum | Z11: =EDATE(E11,X11) -> 46108 | AA11: =VLOOKUP(B11,Custumer_Master!A:K,11,) -> March | AB11: Silver | AC11: =PROPER(LEFT(TRIM(F11), 3)) & RIGHT(TRIM(B11), 3) & PROPER(LEFT(TRIM(I11), 2)) -> Pri002Mu | AD11: =DATEDIF(H11, TODAY(), "Y") -> 31 | AE11: =IFERROR(IF(OR(E11="", D11="", LOWER(TRIM(E11))="pending", LOWER(TRIM(D11))="pending"), "Pending", E11 - D11), "Pending") -> 2 | AF11: =IFERROR(IF(OR(E11="", D11="","Pending","Pending"), "Pending", IF((E11 - D11) <= 5, "On Time", "Delayed")), "Pending") -> On Time | AG11: =IF(AF11="Pending","Pending","Completed") -> Completed
A12: ORD10011 | B12: C003 | C12: P202 | D12: 45919 | E12: 23/09/2025 | F12: =VLOOKUP(B12,Custumer_Master!A:D,2,FALSE) -> Rohit Singh | G12: =VLOOKUP($B12,Custumer_Master!$A:$J,6,FALSE) -> Male | H12: =VLOOKUP($B12,Custumer_Master!$A:$J,7,FALSE) -> 10/05/1982 | I12: =VLOOKUP($B12,Custumer_Master!$A:$J,9,FALSE) -> Delhi | J12: =VLOOKUP($B12,Custumer_Master!$A:$J,10,FALSE) -> North | K12: =VLOOKUP(B12,Custumer_Master!A:D,4,FALSE) -> DL | L12: =PROPER(TRIM(VLOOKUP('Final Data'!C12,Product_Master!A:F,3,FALSE))) -> Home Appliances | M12: Iron | N12: 3 | O12: =VLOOKUP(C12,Product_Master!A:F,5,FALSE) -> 1650 | P12: 0 | Q12: =(N12*O12)-(N12*O12)*P12 -> 4950 | R12: 2 | S12: Card | T12: Rahul | U12: rohit.singh@company.com | V12: 9521710321 | W12: =VLOOKUP(C12,Product_Master!A:F,4,FALSE) -> Global Trade | X12: =VLOOKUP(C12,Product_Master!A:F,6,FALSE) -> 24 | Y12: =VLOOKUP(B12,Custumer_Master!A:D,3,FALSE) -> Gold | Z12: =EDATE(E12,X12) -> 46653 | AA12: =VLOOKUP(B12,Custumer_Master!A:K,11,) -> May | AB12: Blacklisted | AC12: =PROPER(LEFT(TRIM(F12), 3)) & RIGHT(TRIM(B12), 3) & PROPER(LEFT(TRIM(I12), 2)) -> Roh003De | AD12: =DATEDIF(H12, TODAY(), "Y") -> 44 | AE12: =IFERROR(IF(OR(E12="", D12="", LOWER(TRIM(E12))="pending", LOWER(TRIM(D12))="pending"), "Pending", E12 - D12), "Pending") -> 4 | AF12: =IFERROR(IF(OR(E12="", D12="","Pending","Pending"), "Pending", IF((E12 - D12) <= 5, "On Time", "Delayed")), "Pending") -> On Time | AG12: =IF(AF12="Pending","Pending","Completed") -> Completed
A13: ORD10012 | B13: C008 | C13: P201 | D13: 45724 | E13: 15/03/2025 | F13: =VLOOKUP(B13,Custumer_Master!A:D,2,FALSE) -> Kavya Nair | G13: =VLOOKUP($B13,Custumer_Master!$A:$J,6,FALSE) -> Female | H13: =VLOOKUP($B13,Custumer_Master!$A:$J,7,FALSE) -> 01/08/1976 | I13: =VLOOKUP($B13,Custumer_Master!$A:$J,9,FALSE) -> Hyderabad | J13: =VLOOKUP($B13,Custumer_Master!$A:$J,10,FALSE) -> South | K13: =VLOOKUP(B13,Custumer_Master!A:D,4,FALSE) -> WB | L13: =PROPER(TRIM(VLOOKUP('Final Data'!C13,Product_Master!A:F,3,FALSE))) -> Home Appliances | M13: Mixer | N13: 10 | O13: =VLOOKUP(C13,Product_Master!A:F,5,FALSE) -> 2625 | P13: 0.05 | Q13: =(N13*O13)-(N13*O13)*P13 -> 24937.5 | R13: 5 | S13: Card | T13: Aisha | U13: kavya.nair@company.com | V13: 9123535241 | W13: =VLOOKUP(C13,Product_Master!A:F,4,FALSE) -> Global Trade | X13: =VLOOKUP(C13,Product_Master!A:F,6,FALSE) -> 6 | Y13: =VLOOKUP(B13,Custumer_Master!A:D,3,FALSE) -> Silver | Z13: =EDATE(E13,X13) -> 45915 | AA13: =VLOOKUP(B13,Custumer_Master!A:K,11,) -> August | AB13: Silver | AC13: =PROPER(LEFT(TRIM(F13), 3)) & RIGHT(TRIM(B13), 3) & PROPER(LEFT(TRIM(I13), 2)) -> Kav008Hy | AD13: =DATEDIF(H13, TODAY(), "Y") -> 49 | AE13: =IFERROR(IF(OR(E13="", D13="", LOWER(TRIM(E13))="pending", LOWER(TRIM(D13))="pending"), "Pending", E13 - D13), "Pending") -> 7 | AF13: =IFERROR(IF(OR(E13="", D13="","Pending","Pending"), "Pending", IF((E13 - D13) <= 5, "On Time", "Delayed")), "Pending") -> Delayed | AG13: =IF(AF13="Pending","Pending","Completed") -> Completed
A14: ORD10013 | B14: C002 | C14: P202 | D14: 45667 | E14: 15/01/2025 | F14: =VLOOKUP(B14,Custumer_Master!A:D,2,FALSE) -> Priya Patel | G14: =VLOOKUP($B14,Custumer_Master!$A:$J,6,FALSE) -> Female | H14: =VLOOKUP($B14,Custumer_Master!$A:$J,7,FALSE) -> 07/03/1995 | I14: =VLOOKUP($B14,Custumer_Master!$A:$J,9,FALSE) -> Mumbai | J14: =VLOOKUP($B14,Custumer_Master!$A:$J,10,FALSE) -> West | K14: =VLOOKUP(B14,Custumer_Master!A:D,4,FALSE) -> WB | L14: =PROPER(TRIM(VLOOKUP('Final Data'!C14,Product_Master!A:F,3,FALSE))) -> Home Appliances | M14: Iron | N14: 15 | O14: =VLOOKUP(C14,Product_Master!A:F,5,FALSE) -> 1650 | P14: 0.1 | Q14: =(N14*O14)-(N14*O14)*P14 -> 22275 | R14: 1 | S14: Upi | T14: Neha | U14: priya.patel@company.com | V14: 9367316892 | W14: =VLOOKUP(C14,Product_Master!A:F,4,FALSE) -> Global Trade | X14: =VLOOKUP(C14,Product_Master!A:F,6,FALSE) -> 24 | Y14: =VLOOKUP(B14,Custumer_Master!A:D,3,FALSE) -> Platinum | Z14: =EDATE(E14,X14) -> 46402 | AA14: =VLOOKUP(B14,Custumer_Master!A:K,11,) -> March | AB14: Blacklisted | AC14: =PROPER(LEFT(TRIM(F14), 3)) & RIGHT(TRIM(B14), 3) & PROPER(LEFT(TRIM(I14), 2)) -> Pri002Mu | AD14: =DATEDIF(H14, TODAY(), "Y") -> 31 | AE14: =IFERROR(IF(OR(E14="", D14="", LOWER(TRIM(E14))="pending", LOWER(TRIM(D14))="pending"), "Pending", E14 - D14), "Pending") -> 5 | AF14: =IFERROR(IF(OR(E14="", D14="","Pending","Pending"), "Pending", IF((E14 - D14) <= 5, "On Time", "Delayed")), "Pending") -> On Time | AG14: =IF(AF14="Pending","Pending","Completed") -> Completed
A15: ORD10014 | B15: C003 | C15: P202 | D15: 45725 | E15: 13/03/2025 | F15: =VLOOKUP(B15,Custumer_Master!A:D,2,FALSE) -> Rohit Singh | G15: =VLOOKUP($B15,Custumer_Master!$A:$J,6,FALSE) -> Male | H15: =VLOOKUP($B15,Custumer_Master!$A:$J,7,FALSE) -> 10/05/1982 | I15: =VLOOKUP($B15,Custumer_Master!$A:$J,9,FALSE) -> Delhi | J15: =VLOOKUP($B15,Custumer_Master!$A:$J,10,FALSE) -> North | K15: =VLOOKUP(B15,Custumer_Master!A:D,4,FALSE) -> DL | L15: =PROPER(TRIM(VLOOKUP('Final Data'!C15,Product_Master!A:F,3,FALSE))) -> Home Appliances | M15: Iron | N15: 17 | O15: =VLOOKUP(C15,Product_Master!A:F,5,FALSE) -> 1650 | P15: 0.05 | Q15: =(N15*O15)-(N15*O15)*P15 -> 26647.5 | R15: 1 | S15: Cash | T15: Karan | U15: rohit.singh@company.com | V15: 9778489803 | W15: =VLOOKUP(C15,Product_Master!A:F,4,FALSE) -> Global Trade | X15: =VLOOKUP(C15,Product_Master!A:F,6,FALSE) -> 24 | Y15: =VLOOKUP(B15,Custumer_Master!A:D,3,FALSE) -> Gold | Z15: =EDATE(E15,X15) -> 46459 | AA15: =VLOOKUP(B15,Custumer_Master!A:K,11,) -> May | AB15: Blacklisted | AC15: =PROPER(LEFT(TRIM(F15), 3)) & RIGHT(TRIM(B15), 3) & PROPER(LEFT(TRIM(I15), 2)) -> Roh003De | AD15: =DATEDIF(H15, TODAY(), "Y") -> 44 | AE15: =IFERROR(IF(OR(E15="", D15="", LOWER(TRIM(E15))="pending", LOWER(TRIM(D15))="pending"), "Pending", E15 - D15), "Pending") -> 4 | AF15: =IFERROR(IF(OR(E15="", D15="","Pending","Pending"), "Pending", IF((E15 - D15) <= 5, "On Time", "Delayed")), "Pending") -> On Time | AG15: =IF(AF15="Pending","Pending","Completed") -> Completed
A16: ORD10015 | B16: C008 | C16: P201 | D16: 45864 | E16: 07/08/2025 | F16: =VLOOKUP(B16,Custumer_Master!A:D,2,FALSE) -> Kavya Nair | G16: =VLOOKUP($B16,Custumer_Master!$A:$J,6,FALSE) -> Female | H16: =VLOOKUP($B16,Custumer_Master!$A:$J,7,FALSE) -> 01/08/1976 | I16: =VLOOKUP($B16,Custumer_Master!$A:$J,9,FALSE) -> Hyderabad | J16: =VLOOKUP($B16,Custumer_Master!$A:$J,10,FALSE) -> South | K16: =VLOOKUP(B16,Custumer_Master!A:D,4,FALSE) -> WB | L16: =PROPER(TRIM(VLOOKUP('Final Data'!C16,Product_Master!A:F,3,FALSE))) -> Home Appliances | M16: Mixer | N16: 15 | O16: =VLOOKUP(C16,Product_Master!A:F,5,FALSE) -> 2625 | P16: 0.15 | Q16: =(N16*O16)-(N16*O16)*P16 -> 33468.75 | R16: 2 | S16: Cash | T16: Neha | U16: kavya.nair@company.com | V16: 9582960180 | W16: =VLOOKUP(C16,Product_Master!A:F,4,FALSE) -> Global Trade | X16: =VLOOKUP(C16,Product_Master!A:F,6,FALSE) -> 6 | Y16: =VLOOKUP(B16,Custumer_Master!A:D,3,FALSE) -> Silver | Z16: =EDATE(E16,X16) -> 46060 | AA16: =VLOOKUP(B16,Custumer_Master!A:K,11,) -> August | AB16: Blacklisted | AC16: =PROPER(LEFT(TRIM(F16), 3)) & RIGHT(TRIM(B16), 3) & PROPER(LEFT(TRIM(I16), 2)) -> Kav008Hy | AD16: =DATEDIF(H16, TODAY(), "Y") -> 49 | AE16: =IFERROR(IF(OR(E16="", D16="", LOWER(TRIM(E16))="pending", LOWER(TRIM(D16))="pending"), "Pending", E16 - D16), "Pending") -> 12 | AF16: =IFERROR(IF(OR(E16="", D16="","Pending","Pending"), "Pending", IF((E16 - D16) <= 5, "On Time", "Delayed")), "Pending") -> Delayed | AG16: =IF(AF16="Pending","Pending","Completed") -> Completed
A17: ORD10016 | B17: C010 | C17: P103 | D17: 46120 | E17: 11/04/2026 | F17: =VLOOKUP(B17,Custumer_Master!A:D,2,FALSE) -> Pooja Shah | G17: =VLOOKUP($B17,Custumer_Master!$A:$J,6,FALSE) -> Female | H17: =VLOOKUP($B17,Custumer_Master!$A:$J,7,FALSE) -> 16/09/1994 | I17: =VLOOKUP($B17,Custumer_Master!$A:$J,9,FALSE) -> Bengaluru | J17: =VLOOKUP($B17,Custumer_Master!$A:$J,10,FALSE) -> South | K17: =VLOOKUP(B17,Custumer_Master!A:D,4,FALSE) -> WB | L17: =PROPER(TRIM(VLOOKUP('Final Data'!C17,Product_Master!A:F,3,FALSE))) -> Electronics | M17: Keyboard | N17: 3 | O17: =VLOOKUP(C17,Product_Master!A:F,5,FALSE) -> 900 | P17: 0.05 | Q17: =(N17*O17)-(N17*O17)*P17 -> 2565 | R17: 5 | S17: Upi | T17: Ritika | U17: pooja.shah@company.com | V17: 9611394005 | W17: =VLOOKUP(C17,Product_Master!A:F,4,FALSE) -> TechHub | X17: =VLOOKUP(C17,Product_Master!A:F,6,FALSE) -> 6 | Y17: =VLOOKUP(B17,Custumer_Master!A:D,3,FALSE) -> Silver | Z17: =EDATE(E17,X17) -> 46306 | AA17: =VLOOKUP(B17,Custumer_Master!A:K,11,) -> September | AB17: Silver | AC17: =PROPER(LEFT(TRIM(F17), 3)) & RIGHT(TRIM(B17), 3) & PROPER(LEFT(TRIM(I17), 2)) -> Poo010Be | AD17: =DATEDIF(H17, TODAY(), "Y") -> 31 | AE17: =IFERROR(IF(OR(E17="", D17="", LOWER(TRIM(E17))="pending", LOWER(TRIM(D17))="pending"), "Pending", E17 - D17), "Pending") -> 3 | AF17: =IFERROR(IF(OR(E17="", D17="","Pending","Pending"), "Pending", IF((E17 - D17) <= 5, "On Time", "Delayed")), "Pending") -> On Time | AG17: =IF(AF17="Pending","Pending","Completed") -> Completed
A18: ORD10017 | B18: C004 | C18: P203 | D18: 46075 | E18: 03/03/2026 | F18: =VLOOKUP(B18,Custumer_Master!A:D,2,FALSE) -> Anita Gupta | G18: =VLOOKUP($B18,Custumer_Master!$A:$J,6,FALSE) -> Female | H18: =VLOOKUP($B18,Custumer_Master!$A:$J,7,FALSE) -> 16/01/2002 | I18: =VLOOKUP($B18,Custumer_Master!$A:$J,9,FALSE) -> Pune | J18: =VLOOKUP($B18,Custumer_Master!$A:$J,10,FALSE) -> West | K18: =VLOOKUP(B18,Custumer_Master!A:D,4,FALSE) -> WB | L18: =PROPER(TRIM(VLOOKUP('Final Data'!C18,Product_Master!A:F,3,FALSE))) -> Home Appliances | M18: Microwave | N18: 13 | O18: =VLOOKUP(C18,Product_Master!A:F,5,FALSE) -> 6375 | P18: 0.2 | Q18: =(N18*O18)-(N18*O18)*P18 -> 66300 | R18: 4 | S18: Card | T18: Rahul | U18: anita.gupta@company.com | V18: 9692599404 | W18: =VLOOKUP(C18,Product_Master!A:F,4,FALSE) -> TechHub | X18: =VLOOKUP(C18,Product_Master!A:F,6,FALSE) -> 24 | Y18: =VLOOKUP(B18,Custumer_Master!A:D,3,FALSE) -> Gold | Z18: =EDATE(E18,X18) -> 46815 | AA18: =VLOOKUP(B18,Custumer_Master!A:K,11,) -> January | AB18: Gold | AC18: =PROPER(LEFT(TRIM(F18), 3)) & RIGHT(TRIM(B18), 3) & PROPER(LEFT(TRIM(I18), 2)) -> Ani004Pu | AD18: =DATEDIF(H18, TODAY(), "Y") -> 24 | AE18: =IFERROR(IF(OR(E18="", D18="", LOWER(TRIM(E18))="pending", LOWER(TRIM(D18))="pending"), "Pending", E18 - D18), "Pending") -> 9 | AF18: =IFERROR(IF(OR(E18="", D18="","Pending","Pending"), "Pending", IF((E18 - D18) <= 5, "On Time", "Delayed")), "Pending") -> Delayed | AG18: =IF(AF18="Pending","Pending","Completed") -> Completed
A19: ORD10018 | B19: C007 | C19: P203 | D19: 46081 | E19: 05/03/2026 | F19: =VLOOKUP(B19,Custumer_Master!A:D,2,FALSE) -> Arjun Rao | G19: =VLOOKUP($B19,Custumer_Master!$A:$J,6,FALSE) -> Male | H19: =VLOOKUP($B19,Custumer_Master!$A:$J,7,FALSE) -> 07/02/1988 | I19: =VLOOKUP($B19,Custumer_Master!$A:$J,9,FALSE) -> Hyderabad | J19: =VLOOKUP($B19,Custumer_Master!$A:$J,10,FALSE) -> South | K19: =VLOOKUP(B19,Custumer_Master!A:D,4,FALSE) -> RJ | L19: =PROPER(TRIM(VLOOKUP('Final Data'!C19,Product_Master!A:F,3,FALSE))) -> Home Appliances | M19: Microwave | N19: 4 | O19: =VLOOKUP(C19,Product_Master!A:F,5,FALSE) -> 6375 | P19: 0.2 | Q19: =(N19*O19)-(N19*O19)*P19 -> 20400 | R19: 5 | S19: Card | T19: Aisha | U19: arjun.rao@company.com | V19: 9426119622 | W19: =VLOOKUP(C19,Product_Master!A:F,4,FALSE) -> TechHub | X19: =VLOOKUP(C19,Product_Master!A:F,6,FALSE) -> 24 | Y19: =VLOOKUP(B19,Custumer_Master!A:D,3,FALSE) -> Silver | Z19: =EDATE(E19,X19) -> 46817 | AA19: =VLOOKUP(B19,Custumer_Master!A:K,11,) -> February | AB19: Silver | AC19: =PROPER(LEFT(TRIM(F19), 3)) & RIGHT(TRIM(B19), 3) & PROPER(LEFT(TRIM(I19), 2)) -> Arj007Hy | AD19: =DATEDIF(H19, TODAY(), "Y") -> 38 | AE19: =IFERROR(IF(OR(E19="", D19="", LOWER(TRIM(E19))="pending", LOWER(TRIM(D19))="pending"), "Pending", E19 - D19), "Pending") -> 5 | AF19: =IFERROR(IF(OR(E19="", D19="","Pending","Pending"), "Pending", IF((E19 - D19) <= 5, "On Time", "Delayed")), "Pending") -> On Time | AG19: =IF(AF19="Pending","Pending","Completed") -> Completed
A20: ORD10019 | B20: C007 | C20: P102 | D20: 45992 | E20: 04/12/2025 | F20: =VLOOKUP(B20,Custumer_Master!A:D,2,FALSE) -> Arjun Rao | G20: =VLOOKUP($B20,Custumer_Master!$A:$J,6,FALSE) -> Male | H20: =VLOOKUP($B20,Custumer_Master!$A:$J,7,FALSE) -> 07/02/1988 | I20: =VLOOKUP($B20,Custumer_Master!$A:$J,9,FALSE) -> Hyderabad | J20: =VLOOKUP($B20,Custumer_Master!$A:$J,10,FALSE) -> South | K20: =VLOOKUP(B20,Custumer_Master!A:D,4,FALSE) -> RJ | L20: =PROPER(TRIM(VLOOKUP('Final Data'!C20,Product_Master!A:F,3,FALSE))) -> Electronics | M20: Mouse | N20: 9 | O20: =VLOOKUP(C20,Product_Master!A:F,5,FALSE) -> 525 | P20: 0.05 | Q20: =(N20*O20)-(N20*O20)*P20 -> 4488.75 | R20: 3 | S20: Upi | T20: Ritika | U20: arjun.rao@company.com | V20: 9184436009 | W20: =VLOOKUP(C20,Product_Master!A:F,4,FALSE) -> TechHub | X20: =VLOOKUP(C20,Product_Master!A:F,6,FALSE) -> 24 | Y20: =VLOOKUP(B20,Custumer_Master!A:D,3,FALSE) -> Silver | Z20: =EDATE(E20,X20) -> 46725 | AA20: =VLOOKUP(B20,Custumer_Master!A:K,11,) -> February | AB20: Silver | AC20: =PROPER(LEFT(TRIM(F20), 3)) & RIGHT(TRIM(B20), 3) & PROPER(LEFT(TRIM(I20), 2)) -> Arj007Hy | AD20: =DATEDIF(H20, TODAY(), "Y") -> 38 | AE20: =IFERROR(IF(OR(E20="", D20="", LOWER(TRIM(E20))="pending", LOWER(TRIM(D20))="pending"), "Pending", E20 - D20), "Pending") -> 3 | AF20: =IFERROR(IF(OR(E20="", D20="","Pending","Pending"), "Pending", IF((E20 - D20) <= 5, "On Time", "Delayed")), "Pending") -> On Time | AG20: =IF(AF20="Pending","Pending","Completed") -> Completed
... A49: ORD10048 | B49: C006 | C49: P102 | D49: 45988 | E49: 03/12/2025 | F49: =VLOOKUP(B49,Custumer_Master!A:D,2,FALSE) -> Sneha Joshi | G49: =VLOOKUP($B49,Custumer_Master!$A:$J,6,FALSE) -> Female | H49: =VLOOKUP($B49,Custumer_Master!$A:$J,7,FALSE) -> 04/04/1981 | I49: =VLOOKUP($B49,Custumer_Master!$A:$J,9,FALSE) -> Pune | J49: =VLOOKUP($B49,Custumer_Master!$A:$J,10,FALSE) -> West | K49: =VLOOKUP(B49,Custumer_Master!A:D,4,FALSE) -> WB | L49: =PROPER(TRIM(VLOOKUP('Final Data'!C49,Product_Master!A:F,3,FALSE))) -> Electronics | M49: Mouse | N49: 19 | O49: =VLOOKUP(C49,Product_Master!A:F,5,FALSE) -> 525 | P49: 0.2 | Q49: =(N49*O49)-(N49*O49)*P49 -> 7980 | R49: 1 | S49: Cash | T49: Neha | U49: sneha.joshi@company.com | V49: 9238141322 | W49: =VLOOKUP(C49,Product_Master!A:F,4,FALSE) -> TechHub | X49: =VLOOKUP(C49,Product_Master!A:F,6,FALSE) -> 24 | Y49: =VLOOKUP(B49,Custumer_Master!A:D,3,FALSE) -> Gold | Z49: =EDATE(E49,X49) -> 46724 | AA49: =VLOOKUP(B49,Custumer_Master!A:K,11,) -> April | AB49: Blacklisted | AC49: =PROPER(LEFT(TRIM(F49), 3)) & RIGHT(TRIM(B49), 3) & PROPER(LEFT(TRIM(I49), 2)) -> Sne006Pu | AD49: =DATEDIF(H49, TODAY(), "Y") -> 45 | AE49: =IFERROR(IF(OR(E49="", D49="", LOWER(TRIM(E49))="pending", LOWER(TRIM(D49))="pending"), "Pending", E49 - D49), "Pending") -> 6 | AF49: =IFERROR(IF(OR(E49="", D49="","Pending","Pending"), "Pending", IF((E49 - D49) <= 5, "On Time", "Delayed")), "Pending") -> Delayed | AG49: =IF(AF49="Pending","Pending","Completed") -> Completed
A50: ORD10049 | B50: C009 | C50: P104 | D50: 46131 | F50: =VLOOKUP(B50,Custumer_Master!A:D,2,FALSE) -> Mohit Verma | G50: =VLOOKUP($B50,Custumer_Master!$A:$J,6,FALSE) -> Male | H50: =VLOOKUP($B50,Custumer_Master!$A:$J,7,FALSE) -> 13/04/1976 | I50: =VLOOKUP($B50,Custumer_Master!$A:$J,9,FALSE) -> Delhi | J50: =VLOOKUP($B50,Custumer_Master!$A:$J,10,FALSE) -> North | K50: =VLOOKUP(B50,Custumer_Master!A:D,4,FALSE) -> KA | L50: =PROPER(TRIM(VLOOKUP('Final Data'!C50,Product_Master!A:F,3,FALSE))) -> Electronics | M50: Monitor | N50: 19 | O50: =VLOOKUP(C50,Product_Master!A:F,5,FALSE) -> 9000 | P50: 0 | Q50: =(N50*O50)-(N50*O50)*P50 -> 171000 | R50: 1 | S50: Netbanking | T50: Aisha | U50: mohit.verma@company.com | V50: 9890380030 | W50: =VLOOKUP(C50,Product_Master!A:F,4,FALSE) -> Global Trade | X50: =VLOOKUP(C50,Product_Master!A:F,6,FALSE) -> 24 | Y50: =VLOOKUP(B50,Custumer_Master!A:D,3,FALSE) -> Platinum | Z50: =EDATE(E50,X50) -> 731 | AA50: =VLOOKUP(B50,Custumer_Master!A:K,11,) -> April | AB50: Blacklisted | AC50: =PROPER(LEFT(TRIM(F50), 3)) & RIGHT(TRIM(B50), 3) & PROPER(LEFT(TRIM(I50), 2)) -> Moh009De | AD50: =DATEDIF(H50, TODAY(), "Y") -> 50 | AE50: =IFERROR(IF(OR(E50="", D50="", LOWER(TRIM(E50))="pending", LOWER(TRIM(D50))="pending"), "Pending", E50 - D50), "Pending") -> Pending | AF50: =IFERROR(IF(OR(E50="", D50="","Pending","Pending"), "Pending", IF((E50 - D50) <= 5, "On Time", "Delayed")), "Pending") -> Pending | AG50: =IF(AF50="Pending","Pending","Completed") -> Pending
A51: ORD10050 | B51: C004 | C51: P103 | D51: 46131 | E51: 21/04/2026 | F51: =VLOOKUP(B51,Custumer_Master!A:D,2,FALSE) -> Anita Gupta | G51: =VLOOKUP($B51,Custumer_Master!$A:$J,6,FALSE) -> Female | H51: =VLOOKUP($B51,Custumer_Master!$A:$J,7,FALSE) -> 16/01/2002 | I51: =VLOOKUP($B51,Custumer_Master!$A:$J,9,FALSE) -> Pune | J51: =VLOOKUP($B51,Custumer_Master!$A:$J,10,FALSE) -> West | K51: =VLOOKUP(B51,Custumer_Master!A:D,4,FALSE) -> WB | L51: =PROPER(TRIM(VLOOKUP('Final Data'!C51,Product_Master!A:F,3,FALSE))) -> Electronics | M51: Keyboard | N51: 6 | O51: =VLOOKUP(C51,Product_Master!A:F,5,FALSE) -> 900 | P51: 0.05 | Q51: =(N51*O51)-(N51*O51)*P51 -> 5130 | R51: 2 | S51: Cash | T51: Ritika | U51: anita.gupta@company.com | V51: 9495893170 | W51: =VLOOKUP(C51,Product_Master!A:F,4,FALSE) -> TechHub | X51: =VLOOKUP(C51,Product_Master!A:F,6,FALSE) -> 6 | Y51: =VLOOKUP(B51,Custumer_Master!A:D,3,FALSE) -> Gold | Z51: =EDATE(E51,X51) -> 46316 | AA51: =VLOOKUP(B51,Custumer_Master!A:K,11,) -> January | AB51: Blacklisted | AC51: =PROPER(LEFT(TRIM(F51), 3)) & RIGHT(TRIM(B51), 3) & PROPER(LEFT(TRIM(I51), 2)) -> Ani004Pu | AD51: =DATEDIF(H51, TODAY(), "Y") -> 24 | AE51: =IFERROR(IF(OR(E51="", D51="", LOWER(TRIM(E51))="pending", LOWER(TRIM(D51))="pending"), "Pending", E51 - D51), "Pending") -> 2 | AF51: =IFERROR(IF(OR(E51="", D51="","Pending","Pending"), "Pending", IF((E51 - D51) <= 5, "On Time", "Delayed")), "Pending") -> On Time | AG51: =IF(AF51="Pending","Pending","Completed") -> Completed
A52: ORD10051 | B52: C010 | C52: P202 | D52: 45744 | E52: 07/04/2025 | F52: =VLOOKUP(B52,Custumer_Master!A:D,2,FALSE) -> Pooja Shah | G52: =VLOOKUP($B52,Custumer_Master!$A:$J,6,FALSE) -> Female | H52: =VLOOKUP($B52,Custumer_Master!$A:$J,7,FALSE) -> 16/09/1994 | I52: =VLOOKUP($B52,Custumer_Master!$A:$J,9,FALSE) -> Bengaluru | J52: =VLOOKUP($B52,Custumer_Master!$A:$J,10,FALSE) -> South | K52: =VLOOKUP(B52,Custumer_Master!A:D,4,FALSE) -> WB | L52: =PROPER(TRIM(VLOOKUP('Final Data'!C52,Product_Master!A:F,3,FALSE))) -> Home Appliances | M52: Iron | N52: 7 | O52: =VLOOKUP(C52,Product_Master!A:F,5,FALSE) -> 1650 | P52: 0.15 | Q52: =(N52*O52)-(N52*O52)*P52 -> 9817.5 | R52: 1 | S52: Upi | T52: Aisha | U52: pooja.shah@company.com | V52: 9485166307 | W52: =VLOOKUP(C52,Product_Master!A:F,4,FALSE) -> Global Trade | X52: =VLOOKUP(C52,Product_Master!A:F,6,FALSE) -> 24 | Y52: =VLOOKUP(B52,Custumer_Master!A:D,3,FALSE) -> Silver | Z52: =EDATE(E52,X52) -> 46484 | AA52: =VLOOKUP(B52,Custumer_Master!A:K,11,) -> September | AB52: Blacklisted | AC52: =PROPER(LEFT(TRIM(F52), 3)) & RIGHT(TRIM(B52), 3) & PROPER(LEFT(TRIM(I52), 2)) -> Poo010Be | AD52: =DATEDIF(H52, TODAY(), "Y") -> 31 | AE52: =IFERROR(IF(OR(E52="", D52="", LOWER(TRIM(E52))="pending", LOWER(TRIM(D52))="pending"), "Pending", E52 - D52), "Pending") -> 10 | AF52: =IFERROR(IF(OR(E52="", D52="","Pending","Pending"), "Pending", IF((E52 - D52) <= 5, "On Time", "Delayed")), "Pending") -> Delayed | AG52: =IF(AF52="Pending","Pending","Completed") -> Completed
A53: ORD10052 | B53: C002 | C53: P301 | D53: 45894 | E53: 28/08/2025 | F53: =VLOOKUP(B53,Custumer_Master!A:D,2,FALSE) -> Priya Patel | G53: =VLOOKUP($B53,Custumer_Master!$A:$J,6,FALSE) -> Female | H53: =VLOOKUP($B53,Custumer_Master!$A:$J,7,FALSE) -> 07/03/1995 | I53: =VLOOKUP($B53,Custumer_Master!$A:$J,9,FALSE) -> Mumbai | J53: =VLOOKUP($B53,Custumer_Master!$A:$J,10,FALSE) -> West | K53: =VLOOKUP(B53,Custumer_Master!A:D,4,FALSE) -> WB | L53: =PROPER(TRIM(VLOOKUP('Final Data'!C53,Product_Master!A:F,3,FALSE))) -> Stationery | M53: Notebook | N53: 8 | O53: =VLOOKUP(C53,Product_Master!A:F,5,FALSE) -> 45 | P53: 0.1 | Q53: =(N53*O53)-(N53*O53)*P53 -> 324 | R53: 5 | S53: Card | T53: Aisha | U53: priya.patel@company.com | V53: 9924709648 | W53: =VLOOKUP(C53,Product_Master!A:F,4,FALSE) -> ABC Corp | X53: =VLOOKUP(C53,Product_Master!A:F,6,FALSE) -> 12 | Y53: =VLOOKUP(B53,Custumer_Master!A:D,3,FALSE) -> Platinum | Z53: =EDATE(E53,X53) -> 46262 | AA53: =VLOOKUP(B53,Custumer_Master!A:K,11,) -> March | AB53: Silver | AC53: =PROPER(LEFT(TRIM(F53), 3)) & RIGHT(TRIM(B53), 3) & PROPER(LEFT(TRIM(I53), 2)) -> Pri002Mu | AD53: =DATEDIF(H53, TODAY(), "Y") -> 31 | AE53: =IFERROR(IF(OR(E53="", D53="", LOWER(TRIM(E53))="pending", LOWER(TRIM(D53))="pending"), "Pending", E53 - D53), "Pending") -> 3 | AF53: =IFERROR(IF(OR(E53="", D53="","Pending","Pending"), "Pending", IF((E53 - D53) <= 5, "On Time", "Delayed")), "Pending") -> On Time | AG53: =IF(AF53="Pending","Pending","Completed") -> Completed
A54: ORD10053 | B54: C005 | C54: P101 | D54: 45888 | E54: 23/08/2025 | F54: =VLOOKUP(B54,Custumer_Master!A:D,2,FALSE) -> Vikas Mehta | G54: =VLOOKUP($B54,Custumer_Master!$A:$J,6,FALSE) -> Male | H54: =VLOOKUP($B54,Custumer_Master!$A:$J,7,FALSE) -> 03/08/1991 | I54: =VLOOKUP($B54,Custumer_Master!$A:$J,9,FALSE) -> Mumbai | J54: =VLOOKUP($B54,Custumer_Master!$A:$J,10,FALSE) -> West | K54: =VLOOKUP(B54,Custumer_Master!A:D,4,FALSE) -> DL | L54: =PROPER(TRIM(VLOOKUP('Final Data'!C54,Product_Master!A:F,3,FALSE))) -> Electronics | M54: Laptop | N54: 12 | O54: =VLOOKUP(C54,Product_Master!A:F,5,FALSE) -> 41250 | P54: 0.05 | Q54: =(N54*O54)-(N54*O54)*P54 -> 470250 | R54: 2 | S54: Upi | T54: Rahul | U54: vikas.mehta@company.com | V54: 9350554626 | W54: =VLOOKUP(C54,Product_Master!A:F,4,FALSE) -> TechHub | X54: =VLOOKUP(C54,Product_Master!A:F,6,FALSE) -> 12 | Y54: =VLOOKUP(B54,Custumer_Master!A:D,3,FALSE) -> Gold | Z54: =EDATE(E54,X54) -> 46257 | AA54: =VLOOKUP(B54,Custumer_Master!A:K,11,) -> August | AB54: Blacklisted | AC54: =PROPER(LEFT(TRIM(F54), 3)) & RIGHT(TRIM(B54), 3) & PROPER(LEFT(TRIM(I54), 2)) -> Vik005Mu | AD54: =DATEDIF(H54, TODAY(), "Y") -> 34 | AE54: =IFERROR(IF(OR(E54="", D54="", LOWER(TRIM(E54))="pending", LOWER(TRIM(D54))="pending"), "Pending", E54 - D54), "Pending") -> 4 | AF54: =IFERROR(IF(OR(E54="", D54="","Pending","Pending"), "Pending", IF((E54 - D54) <= 5, "On Time", "Delayed")), "Pending") -> On Time | AG54: =IF(AF54="Pending","Pending","Completed") -> Completed
A55: ORD10054 | B55: C008 | C55: P102 | D55: 45865 | E55: 05/08/2025 | F55: =VLOOKUP(B55,Custumer_Master!A:D,2,FALSE) -> Kavya Nair | G55: =VLOOKUP($B55,Custumer_Master!$A:$J,6,FALSE) -> Female | H55: =VLOOKUP($B55,Custumer_Master!$A:$J,7,FALSE) -> 01/08/1976 | I55: =VLOOKUP($B55,Custumer_Master!$A:$J,9,FALSE) -> Hyderabad | J55: =VLOOKUP($B55,Custumer_Master!$A:$J,10,FALSE) -> South | K55: =VLOOKUP(B55,Custumer_Master!A:D,4,FALSE) -> WB | L55: =PROPER(TRIM(VLOOKUP('Final Data'!C55,Product_Master!A:F,3,FALSE))) -> Electronics | M55: Mouse | N55: 3 | O55: =VLOOKUP(C55,Product_Master!A:F,5,FALSE) -> 525 | P55: 0 | Q55: =(N55*O55)-(N55*O55)*P55 -> 1575 | R55: 3 | S55: Card | T55: Karan | U55: kavya.nair@company.com | V55: 9743295580 | W55: =VLOOKUP(C55,Product_Master!A:F,4,FALSE) -> TechHub | X55: =VLOOKUP(C55,Product_Master!A:F,6,FALSE) -> 24 | Y55: =VLOOKUP(B55,Custumer_Master!A:D,3,FALSE) -> Silver | Z55: =EDATE(E55,X55) -> 46604 | AA55: =VLOOKUP(B55,Custumer_Master!A:K,11,) -> August | AB55: Silver | AC55: =PROPER(LEFT(TRIM(F55), 3)) & RIGHT(TRIM(B55), 3) & PROPER(LEFT(TRIM(I55), 2)) -> Kav008Hy | AD55: =DATEDIF(H55, TODAY(), "Y") -> 49 | AE55: =IFERROR(IF(OR(E55="", D55="", LOWER(TRIM(E55))="pending", LOWER(TRIM(D55))="pending"), "Pending", E55 - D55), "Pending") -> 9 | AF55: =IFERROR(IF(OR(E55="", D55="","Pending","Pending"), "Pending", IF((E55 - D55) <= 5, "On Time", "Delayed")), "Pending") -> Delayed | AG55: =IF(AF55="Pending","Pending","Completed") -> Completed
A56: ORD10055 | B56: C003 | C56: P301 | D56: 45709 | E56: 26/02/2025 | F56: =VLOOKUP(B56,Custumer_Master!A:D,2,FALSE) -> Rohit Singh | G56: =VLOOKUP($B56,Custumer_Master!$A:$J,6,FALSE) -> Male | H56: =VLOOKUP($B56,Custumer_Master!$A:$J,7,FALSE) -> 10/05/1982 | I56: =VLOOKUP($B56,Custumer_Master!$A:$J,9,FALSE) -> Delhi | J56: =VLOOKUP($B56,Custumer_Master!$A:$J,10,FALSE) -> North | K56: =VLOOKUP(B56,Custumer_Master!A:D,4,FALSE) -> DL | L56: =PROPER(TRIM(VLOOKUP('Final Data'!C56,Product_Master!A:F,3,FALSE))) -> Stationery | M56: Notebook | N56: 19 | O56: =VLOOKUP(C56,Product_Master!A:F,5,FALSE) -> 45 | P56: 0.15 | Q56: =(N56*O56)-(N56*O56)*P56 -> 726.75 | R56: 4 | S56: Card | T56: Rahul | U56: rohit.singh@company.com | V56: 9822926495 | W56: =VLOOKUP(C56,Product_Master!A:F,4,FALSE) -> ABC Corp | X56: =VLOOKUP(C56,Product_Master!A:F,6,FALSE) -> 12 | Y56: =VLOOKUP(B56,Custumer_Master!A:D,3,FALSE) -> Gold | Z56: =EDATE(E56,X56) -> 46079 | AA56: =VLOOKUP(B56,Custumer_Master!A:K,11,) -> May | AB56: Silver | AC56: =PROPER(LEFT(TRIM(F56), 3)) & RIGHT(TRIM(B56), 3) & PROPER(LEFT(TRIM(I56), 2)) -> Roh003De | AD56: =DATEDIF(H56, TODAY(), "Y") -> 44 | AE56: =IFERROR(IF(OR(E56="", D56="", LOWER(TRIM(E56))="pending", LOWER(TRIM(D56))="pending"), "Pending", E56 - D56), "Pending") -> 5 | AF56: =IFERROR(IF(OR(E56="", D56="","Pending","Pending"), "Pending", IF((E56 - D56) <= 5, "On Time", "Delayed")), "Pending") -> On Time | AG56: =IF(AF56="Pending","Pending","Completed") -> Completed
A57: ORD10056 | B57: C001 | C57: P301 | D57: 45879 | E57: 11/08/2025 | F57: =VLOOKUP(B57,Custumer_Master!A:D,2,FALSE) -> Amit Sharma | G57: =VLOOKUP($B57,Custumer_Master!$A:$J,6,FALSE) -> Male | H57: =VLOOKUP($B57,Custumer_Master!$A:$J,7,FALSE) -> 09/08/1991 | I57: =VLOOKUP($B57,Custumer_Master!$A:$J,9,FALSE) -> Pune | J57: =VLOOKUP($B57,Custumer_Master!$A:$J,10,FALSE) -> West | K57: =VLOOKUP(B57,Custumer_Master!A:D,4,FALSE) -> RJ | L57: =PROPER(TRIM(VLOOKUP('Final Data'!C57,Product_Master!A:F,3,FALSE))) -> Stationery | M57: Notebook | N57: 9 | O57: =VLOOKUP(C57,Product_Master!A:F,5,FALSE) -> 45 | P57: 0.2 | Q57: =(N57*O57)-(N57*O57)*P57 -> 324 | R57: 1 | S57: Netbanking | T57: Neha | U57: amit.sharma@company.com | V57: 9518298190 | W57: =VLOOKUP(C57,Product_Master!A:F,4,FALSE) -> ABC Corp | X57: =VLOOKUP(C57,Product_Master!A:F,6,FALSE) -> 12 | Y57: =VLOOKUP(B57,Custumer_Master!A:D,3,FALSE) -> Silver | Z57: =EDATE(E57,X57) -> 46245 | AA57: =VLOOKUP(B57,Custumer_Master!A:K,11,) -> August | AB57: Blacklisted | AC57: =PROPER(LEFT(TRIM(F57), 3)) & RIGHT(TRIM(B57), 3) & PROPER(LEFT(TRIM(I57), 2)) -> Ami001Pu | AD57: =DATEDIF(H57, TODAY(), "Y") -> 34 | AE57: =IFERROR(IF(OR(E57="", D57="", LOWER(TRIM(E57))="pending", LOWER(TRIM(D57))="pending"), "Pending", E57 - D57), "Pending") -> 1 | AF57: =IFERROR(IF(OR(E57="", D57="","Pending","Pending"), "Pending", IF((E57 - D57) <= 5, "On Time", "Delayed")), "Pending") -> On Time | AG57: =IF(AF57="Pending","Pending","Completed") -> Completed
A58: ORD10057 | B58: C001 | C58: P102 | D58: 46105 | E58: 30/03/2026 | F58: =VLOOKUP(B58,Custumer_Master!A:D,2,FALSE) -> Amit Sharma | G58: =VLOOKUP($B58,Custumer_Master!$A:$J,6,FALSE) -> Male | H58: =VLOOKUP($B58,Custumer_Master!$A:$J,7,FALSE) -> 09/08/1991 | I58: =VLOOKUP($B58,Custumer_Master!$A:$J,9,FALSE) -> Pune | J58: =VLOOKUP($B58,Custumer_Master!$A:$J,10,FALSE) -> West | K58: =VLOOKUP(B58,Custumer_Master!A:D,4,FALSE) -> RJ | L58: =PROPER(TRIM(VLOOKUP('Final Data'!C58,Product_Master!A:F,3,FALSE))) -> Electronics | M58: Mouse | N58: 6 | O58: =VLOOKUP(C58,Product_Master!A:F,5,FALSE) -> 525 | P58: 0 | Q58: =(N58*O58)-(N58*O58)*P58 -> 3150 | R58: 4 | S58: Upi | T58: Rahul | U58: amit.sharma@company.com | V58: 9366223547 | W58: =VLOOKUP(C58,Product_Master!A:F,4,FALSE) -> TechHub | X58: =VLOOKUP(C58,Product_Master!A:F,6,FALSE) -> 24 | Y58: =VLOOKUP(B58,Custumer_Master!A:D,3,FALSE) -> Silver | Z58: =EDATE(E58,X58) -> 46842 | AA58: =VLOOKUP(B58,Custumer_Master!A:K,11,) -> August | AB58: Silver | AC58: =PROPER(LEFT(TRIM(F58), 3)) & RIGHT(TRIM(B58), 3) & PROPER(LEFT(TRIM(I58), 2)) -> Ami001Pu | AD58: =DATEDIF(H58, TODAY(), "Y") -> 34 | AE58: =IFERROR(IF(OR(E58="", D58="", LOWER(TRIM(E58))="pending", LOWER(TRIM(D58))="pending"), "Pending", E58 - D58), "Pending") -> 6 | AF58: =IFERROR(IF(OR(E58="", D58="","Pending","Pending"), "Pending", IF((E58 - D58) <= 5, "On Time", "Delayed")), "Pending") -> Delayed | AG58: =IF(AF58="Pending","Pending","Completed") -> Completed
A59: ORD10058 | B59: C003 | C59: P303 | D59: 46094 | E59: 19/03/2026 | F59: =VLOOKUP(B59,Custumer_Master!A:D,2,FALSE) -> Rohit Singh | G59: =VLOOKUP($B59,Custumer_Master!$A:$J,6,FALSE) -> Male | H59: =VLOOKUP($B59,Custumer_Master!$A:$J,7,FALSE) -> 10/05/1982 | I59: =VLOOKUP($B59,Custumer_Master!$A:$J,9,FALSE) -> Delhi | J59: =VLOOKUP($B59,Custumer_Master!$A:$J,10,FALSE) -> North | K59: =VLOOKUP(B59,Custumer_Master!A:D,4,FALSE) -> DL | L59: =PROPER(TRIM(VLOOKUP('Final Data'!C59,Product_Master!A:F,3,FALSE))) -> Stationery | M59: Marker | N59: 18 | O59: =VLOOKUP(C59,Product_Master!A:F,5,FALSE) -> 33.75 | P59: 0.05 | Q59: =(N59*O59)-(N59*O59)*P59 -> 577.125 | R59: 1 | S59: Card | T59: Aisha | U59: rohit.singh@company.com | V59: 9701988524 | W59: =VLOOKUP(C59,Product_Master!A:F,4,FALSE) -> TechHub | X59: =VLOOKUP(C59,Product_Master!A:F,6,FALSE) -> 12 | Y59: =VLOOKUP(B59,Custumer_Master!A:D,3,FALSE) -> Gold | Z59: =EDATE(E59,X59) -> 46465 | AA59: =VLOOKUP(B59,Custumer_Master!A:K,11,) -> May | AB59: Blacklisted | AC59: =PROPER(LEFT(TRIM(F59), 3)) & RIGHT(TRIM(B59), 3) & PROPER(LEFT(TRIM(I59), 2)) -> Roh003De | AD59: =DATEDIF(H59, TODAY(), "Y") -> 44 | AE59: =IFERROR(IF(OR(E59="", D59="", LOWER(TRIM(E59))="pending", LOWER(TRIM(D59))="pending"), "Pending", E59 - D59), "Pending") -> 6 | AF59: =IFERROR(IF(OR(E59="", D59="","Pending","Pending"), "Pending", IF((E59 - D59) <= 5, "On Time", "Delayed")), "Pending") -> Delayed | AG59: =IF(AF59="Pending","Pending","Completed") -> Completed
A60: ORD10059 | B60: C007 | C60: P302 | D60: 45823 | E60: 26/06/2025 | F60: =VLOOKUP(B60,Custumer_Master!A:D,2,FALSE) -> Arjun Rao | G60: =VLOOKUP($B60,Custumer_Master!$A:$J,6,FALSE) -> Male | H60: =VLOOKUP($B60,Custumer_Master!$A:$J,7,FALSE) -> 07/02/1988 | I60: =VLOOKUP($B60,Custumer_Master!$A:$J,9,FALSE) -> Hyderabad | J60: =VLOOKUP($B60,Custumer_Master!$A:$J,10,FALSE) -> South | K60: =VLOOKUP(B60,Custumer_Master!A:D,4,FALSE) -> RJ | L60: =PROPER(TRIM(VLOOKUP('Final Data'!C60,Product_Master!A:F,3,FALSE))) -> Stationery | M60: Pen | N60: 8 | O60: =VLOOKUP(C60,Product_Master!A:F,5,FALSE) -> 15 | P60: 0.05 | Q60: =(N60*O60)-(N60*O60)*P60 -> 114 | R60: 1 | S60: Card | T60: Ritika | U60: arjun.rao@company.com | V60: 9836327649 | W60: =VLOOKUP(C60,Product_Master!A:F,4,FALSE) -> Prime Supplies | X60: =VLOOKUP(C60,Product_Master!A:F,6,FALSE) -> 12 | Y60: =VLOOKUP(B60,Custumer_Master!A:D,3,FALSE) -> Silver | Z60: =EDATE(E60,X60) -> 46199 | AA60: =VLOOKUP(B60,Custumer_Master!A:K,11,) -> February | AB60: Blacklisted | AC60: =PROPER(LEFT(TRIM(F60), 3)) & RIGHT(TRIM(B60), 3) & PROPER(LEFT(TRIM(I60), 2)) -> Arj007Hy | AD60: =DATEDIF(H60, TODAY(), "Y") -> 38 | AE60: =IFERROR(IF(OR(E60="", D60="", LOWER(TRIM(E60))="pending", LOWER(TRIM(D60))="pending"), "Pending", E60 - D60), "Pending") -> 11 | AF60: =IFERROR(IF(OR(E60="", D60="","Pending","Pending"), "Pending", IF((E60 - D60) <= 5, "On Time", "Delayed")), "Pending") -> Delayed | AG60: =IF(AF60="Pending","Pending","Completed") -> Completed
A61: ORD10060 | B61: C005 | C61: P102 | D61: 45721 | E61: 06/03/2025 | F61: =VLOOKUP(B61,Custumer_Master!A:D,2,FALSE) -> Vikas Mehta | G61: =VLOOKUP($B61,Custumer_Master!$A:$J,6,FALSE) -> Male | H61: =VLOOKUP($B61,Custumer_Master!$A:$J,7,FALSE) -> 03/08/1991 | I61: =VLOOKUP($B61,Custumer_Master!$A:$J,9,FALSE) -> Mumbai | J61: =VLOOKUP($B61,Custumer_Master!$A:$J,10,FALSE) -> West | K61: =VLOOKUP(B61,Custumer_Master!A:D,4,FALSE) -> DL | L61: =PROPER(TRIM(VLOOKUP('Final Data'!C61,Product_Master!A:F,3,FALSE))) -> Electronics | M61: Mouse | N61: 8 | O61: =VLOOKUP(C61,Product_Master!A:F,5,FALSE) -> 525 | P61: 0.1 | Q61: =(N61*O61)-(N61*O61)*P61 -> 3780 | R61: 1 | S61: Netbanking | T61: Aisha | U61: vikas.mehta@company.com | V61: 9261800516 | W61: =VLOOKUP(C61,Product_Master!A:F,4,FALSE) -> TechHub | X61: =VLOOKUP(C61,Product_Master!A:F,6,FALSE) -> 24 | Y61: =VLOOKUP(B61,Custumer_Master!A:D,3,FALSE) -> Gold | Z61: =EDATE(E61,X61) -> 46452 | AA61: =VLOOKUP(B61,Custumer_Master!A:K,11,) -> August | AB61: Blacklisted | AC61: =PROPER(LEFT(TRIM(F61), 3)) & RIGHT(TRIM(B61), 3) & PROPER(LEFT(TRIM(I61), 2)) -> Vik005Mu | AD61: =DATEDIF(H61, TODAY(), "Y") -> 34 | AE61: =IFERROR(IF(OR(E61="", D61="", LOWER(TRIM(E61))="pending", LOWER(TRIM(D61))="pending"), "Pending", E61 - D61), "Pending") -> 1 | AF61: =IFERROR(IF(OR(E61="", D61="","Pending","Pending"), "Pending", IF((E61 - D61) <= 5, "On Time", "Delayed")), "Pending") -> On Time | AG61: =IF(AF61="Pending","Pending","Completed") -> Completed
A62: ORD10061 | B62: C008 | C62: P302 | D62: 46121 | E62: 19/04/2026 | F62: =VLOOKUP(B62,Custumer_Master!A:D,2,FALSE) -> Kavya Nair | G62: =VLOOKUP($B62,Custumer_Master!$A:$J,6,FALSE) -> Female | H62: =VLOOKUP($B62,Custumer_Master!$A:$J,7,FALSE) -> 01/08/1976 | I62: =VLOOKUP($B62,Custumer_Master!$A:$J,9,FALSE) -> Hyderabad | J62: =VLOOKUP($B62,Custumer_Master!$A:$J,10,FALSE) -> South | K62: =VLOOKUP(B62,Custumer_Master!A:D,4,FALSE) -> WB | L62: =PROPER(TRIM(VLOOKUP('Final Data'!C62,Product_Master!A:F,3,FALSE))) -> Stationery | M62: Pen | N62: 7 | O62: =VLOOKUP(C62,Product_Master!A:F,5,FALSE) -> 15 | P62: 0.15 | Q62: =(N62*O62)-(N62*O62)*P62 -> 89.25 | R62: 5 | S62: Card | T62: Rahul | U62: kavya.nair@company.com | V62: 9950802015 | W62: =VLOOKUP(C62,Product_Master!A:F,4,FALSE) -> Prime Supplies | X62: =VLOOKUP(C62,Product_Master!A:F,6,FALSE) -> 12 | Y62: =VLOOKUP(B62,Custumer_Master!A:D,3,FALSE) -> Silver | Z62: =EDATE(E62,X62) -> 46496 | AA62: =VLOOKUP(B62,Custumer_Master!A:K,11,) -> August | AB62: Silver | AC62: =PROPER(LEFT(TRIM(F62), 3)) & RIGHT(TRIM(B62), 3) & PROPER(LEFT(TRIM(I62), 2)) -> Kav008Hy | AD62: =DATEDIF(H62, TODAY(), "Y") -> 49 | AE62: =IFERROR(IF(OR(E62="", D62="", LOWER(TRIM(E62))="pending", LOWER(TRIM(D62))="pending"), "Pending", E62 - D62), "Pending") -> 10 | AF62: =IFERROR(IF(OR(E62="", D62="","Pending","Pending"), "Pending", IF((E62 - D62) <= 5, "On Time", "Delayed")), "Pending") -> Delayed | AG62: =IF(AF62="Pending","Pending","Completed") -> Completed
... A349: ORD10348 | B349: C006 | C349: P202 | D349: 46128 | E349: 19/04/2026 | F349: =VLOOKUP(B349,Custumer_Master!A:D,2,FALSE) -> Sneha Joshi | G349: =VLOOKUP($B349,Custumer_Master!$A:$J,6,FALSE) -> Female | H349: =VLOOKUP($B349,Custumer_Master!$A:$J,7,FALSE) -> 04/04/1981 | I349: =VLOOKUP($B349,Custumer_Master!$A:$J,9,FALSE) -> Pune | J349: =VLOOKUP($B349,Custumer_Master!$A:$J,10,FALSE) -> West | K349: =VLOOKUP(B349,Custumer_Master!A:D,4,FALSE) -> WB | L349: =PROPER(TRIM(VLOOKUP('Final Data'!C349,Product_Master!A:F,3,FALSE))) -> Home Appliances | M349: Iron | N349: 13 | O349: =VLOOKUP(C349,Product_Master!A:F,5,FALSE) -> 1650 | P349: 0.15 | Q349: =(N349*O349)-(N349*O349)*P349 -> 18232.5 | R349: 2 | S349: Netbanking | T349: Neha | U349: sneha.joshi@company.com | V349: 9697433584 | W349: =VLOOKUP(C349,Product_Master!A:F,4,FALSE) -> Global Trade | X349: =VLOOKUP(C349,Product_Master!A:F,6,FALSE) -> 24 | Y349: =VLOOKUP(B349,Custumer_Master!A:D,3,FALSE) -> Gold | Z349: =EDATE(E349,X349) -> 46862 | AA349: =VLOOKUP(B349,Custumer_Master!A:K,11,) -> April | AB349: Blacklisted | AC349: =PROPER(LEFT(TRIM(F349), 3)) & RIGHT(TRIM(B349), 3) & PROPER(LEFT(TRIM(I349), 2)) -> Sne006Pu | AD349: =DATEDIF(H349, TODAY(), "Y") -> 45 | AE349: =IFERROR(IF(OR(E349="", D349="", LOWER(TRIM(E349))="pending", LOWER(TRIM(D349))="pending"), "Pending", E349 - D349), "Pending") -> 3 | AF349: =IFERROR(IF(OR(E349="", D349="","Pending","Pending"), "Pending", IF((E349 - D349) <= 5, "On Time", "Delayed")), "Pending") -> On Time | AG349: =IF(AF349="Pending","Pending","Completed") -> Completed
A350: ORD10349 | B350: C010 | C350: P999 | D350: 45943 | E350: 14/10/2025 | F350: =VLOOKUP(B350,Custumer_Master!A:D,2,FALSE) -> Pooja Shah | G350: =VLOOKUP($B350,Custumer_Master!$A:$J,6,FALSE) -> Female | H350: =VLOOKUP($B350,Custumer_Master!$A:$J,7,FALSE) -> 16/09/1994 | I350: =VLOOKUP($B350,Custumer_Master!$A:$J,9,FALSE) -> Bengaluru | J350: =VLOOKUP($B350,Custumer_Master!$A:$J,10,FALSE) -> South | K350: =VLOOKUP(B350,Custumer_Master!A:D,4,FALSE) -> WB | L350: =PROPER(TRIM(VLOOKUP('Final Data'!C350,Product_Master!A:F,3,FALSE))) -> #N/A | M350: #N/A | N350: 11 | O350: =VLOOKUP(C350,Product_Master!A:F,5,FALSE) -> #N/A | P350: 0.05 | Q350: =(N350*O350)-(N350*O350)*P350 -> #N/A | R350: 1 | S350: Upi | T350: Neha | U350: pooja.shah@company.com | V350: 9837969758 | W350: =VLOOKUP(C350,Product_Master!A:F,4,FALSE) -> #N/A | X350: =VLOOKUP(C350,Product_Master!A:F,6,FALSE) -> #N/A | Y350: =VLOOKUP(B350,Custumer_Master!A:D,3,FALSE) -> Silver | Z350: =EDATE(E350,X350) -> #N/A | AA350: =VLOOKUP(B350,Custumer_Master!A:K,11,) -> September | AB350: Blacklisted | AC350: =PROPER(LEFT(TRIM(F350), 3)) & RIGHT(TRIM(B350), 3) & PROPER(LEFT(TRIM(I350), 2)) -> Poo010Be | AD350: =DATEDIF(H350, TODAY(), "Y") -> 31 | AE350: =IFERROR(IF(OR(E350="", D350="", LOWER(TRIM(E350))="pending", LOWER(TRIM(D350))="pending"), "Pending", E350 - D350), "Pending") -> 1 | AF350: =IFERROR(IF(OR(E350="", D350="","Pending","Pending"), "Pending", IF((E350 - D350) <= 5, "On Time", "Delayed")), "Pending") -> On Time | AG350: =IF(AF350="Pending","Pending","Completed") -> Completed
A351: ORD10350 | B351: C010 | C351: P202 | D351: 45996 | E351: 10/12/2025 | F351: =VLOOKUP(B351,Custumer_Master!A:D,2,FALSE) -> Pooja Shah | G351: =VLOOKUP($B351,Custumer_Master!$A:$J,6,FALSE) -> Female | H351: =VLOOKUP($B351,Custumer_Master!$A:$J,7,FALSE) -> 16/09/1994 | I351: =VLOOKUP($B351,Custumer_Master!$A:$J,9,FALSE) -> Bengaluru | J351: =VLOOKUP($B351,Custumer_Master!$A:$J,10,FALSE) -> South | K351: =VLOOKUP(B351,Custumer_Master!A:D,4,FALSE) -> WB | L351: =PROPER(TRIM(VLOOKUP('Final Data'!C351,Product_Master!A:F,3,FALSE))) -> Home Appliances | M351: Iron | N351: 2 | O351: =VLOOKUP(C351,Product_Master!A:F,5,FALSE) -> 1650 | P351: 0 | Q351: =(N351*O351)-(N351*O351)*P351 -> 3300 | R351: 4 | S351: Upi | T351: Karan | U351: pooja.shah@company.com | V351: 9209736419 | W351: =VLOOKUP(C351,Product_Master!A:F,4,FALSE) -> Global Trade | X351: =VLOOKUP(C351,Product_Master!A:F,6,FALSE) -> 24 | Y351: =VLOOKUP(B351,Custumer_Master!A:D,3,FALSE) -> Silver | Z351: =EDATE(E351,X351) -> 46731 | AA351: =VLOOKUP(B351,Custumer_Master!A:K,11,) -> September | AB351: Silver | AC351: =PROPER(LEFT(TRIM(F351), 3)) & RIGHT(TRIM(B351), 3) & PROPER(LEFT(TRIM(I351), 2)) -> Poo010Be | AD351: =DATEDIF(H351, TODAY(), "Y") -> 31 | AE351: =IFERROR(IF(OR(E351="", D351="", LOWER(TRIM(E351))="pending", LOWER(TRIM(D351))="pending"), "Pending", E351 - D351), "Pending") -> 5 | AF351: =IFERROR(IF(OR(E351="", D351="","Pending","Pending"), "Pending", IF((E351 - D351) <= 5, "On Time", "Delayed")), "Pending") -> On Time | AG351: =IF(AF351="Pending","Pending","Completed") -> Completed
A352: ORD10351 | B352: C007 | C352: P102 | D352: 45868 | E352: 04/08/2025 | F352: =VLOOKUP(B352,Custumer_Master!A:D,2,FALSE) -> Arjun Rao | G352: =VLOOKUP($B352,Custumer_Master!$A:$J,6,FALSE) -> Male | H352: =VLOOKUP($B352,Custumer_Master!$A:$J,7,FALSE) -> 07/02/1988 | I352: =VLOOKUP($B352,Custumer_Master!$A:$J,9,FALSE) -> Hyderabad | J352: =VLOOKUP($B352,Custumer_Master!$A:$J,10,FALSE) -> South | K352: =VLOOKUP(B352,Custumer_Master!A:D,4,FALSE) -> RJ | L352: =PROPER(TRIM(VLOOKUP('Final Data'!C352,Product_Master!A:F,3,FALSE))) -> Electronics | M352: Mouse | N352: 15 | O352: =VLOOKUP(C352,Product_Master!A:F,5,FALSE) -> 525 | P352: 0.15 | Q352: =(N352*O352)-(N352*O352)*P352 -> 6693.75 | R352: 3 | S352: Netbanking | T352: Neha | U352: arjun.rao@company.com | V352: 9645907237 | W352: =VLOOKUP(C352,Product_Master!A:F,4,FALSE) -> TechHub | X352: =VLOOKUP(C352,Product_Master!A:F,6,FALSE) -> 24 | Y352: =VLOOKUP(B352,Custumer_Master!A:D,3,FALSE) -> Silver | Z352: =EDATE(E352,X352) -> 46603 | AA352: =VLOOKUP(B352,Custumer_Master!A:K,11,) -> February | AB352: Silver | AC352: =PROPER(LEFT(TRIM(F352), 3)) & RIGHT(TRIM(B352), 3) & PROPER(LEFT(TRIM(I352), 2)) -> Arj007Hy | AD352: =DATEDIF(H352, TODAY(), "Y") -> 38 | AE352: =IFERROR(IF(OR(E352="", D352="", LOWER(TRIM(E352))="pending", LOWER(TRIM(D352))="pending"), "Pending", E352 - D352), "Pending") -> 5 | AF352: =IFERROR(IF(OR(E352="", D352="","Pending","Pending"), "Pending", IF((E352 - D352) <= 5, "On Time", "Delayed")), "Pending") -> On Time | AG352: =IF(AF352="Pending","Pending","Completed") -> Completed
A353: ORD10352 | B353: C003 | C353: P202 | D353: 45856 | E353: 24/07/2025 | F353: =VLOOKUP(B353,Custumer_Master!A:D,2,FALSE) -> Rohit Singh | G353: =VLOOKUP($B353,Custumer_Master!$A:$J,6,FALSE) -> Male | H353: =VLOOKUP($B353,Custumer_Master!$A:$J,7,FALSE) -> 10/05/1982 | I353: =VLOOKUP($B353,Custumer_Master!$A:$J,9,FALSE) -> Delhi | J353: =VLOOKUP($B353,Custumer_Master!$A:$J,10,FALSE) -> North | K353: =VLOOKUP(B353,Custumer_Master!A:D,4,FALSE) -> DL | L353: =PROPER(TRIM(VLOOKUP('Final Data'!C353,Product_Master!A:F,3,FALSE))) -> Home Appliances | M353: Iron | N353: 5 | O353: =VLOOKUP(C353,Product_Master!A:F,5,FALSE) -> 1650 | P353: 0.15 | Q353: =(N353*O353)-(N353*O353)*P353 -> 7012.5 | R353: 1 | S353: Netbanking | T353: Neha | U353: rohit.singh@company.com | V353: 9566149945 | W353: =VLOOKUP(C353,Product_Master!A:F,4,FALSE) -> Global Trade | X353: =VLOOKUP(C353,Product_Master!A:F,6,FALSE) -> 24 | Y353: =VLOOKUP(B353,Custumer_Master!A:D,3,FALSE) -> Gold | Z353: =EDATE(E353,X353) -> 46592 | AA353: =VLOOKUP(B353,Custumer_Master!A:K,11,) -> May | AB353: Blacklisted | AC353: =PROPER(LEFT(TRIM(F353), 3)) & RIGHT(TRIM(B353), 3) & PROPER(LEFT(TRIM(I353), 2)) -> Roh003De | AD353: =DATEDIF(H353, TODAY(), "Y") -> 44 | AE353: =IFERROR(IF(OR(E353="", D353="", LOWER(TRIM(E353))="pending", LOWER(TRIM(D353))="pending"), "Pending", E353 - D353), "Pending") -> 6 | AF353: =IFERROR(IF(OR(E353="", D353="","Pending","Pending"), "Pending", IF((E353 - D353) <= 5, "On Time", "Delayed")), "Pending") -> Delayed | AG353: =IF(AF353="Pending","Pending","Completed") -> Completed
A354: ORD10353 | B354: C007 | C354: P103 | D354: 46092 | E354: 12/03/2026 | F354: =VLOOKUP(B354,Custumer_Master!A:D,2,FALSE) -> Arjun Rao | G354: =VLOOKUP($B354,Custumer_Master!$A:$J,6,FALSE) -> Male | H354: =VLOOKUP($B354,Custumer_Master!$A:$J,7,FALSE) -> 07/02/1988 | I354: =VLOOKUP($B354,Custumer_Master!$A:$J,9,FALSE) -> Hyderabad | J354: =VLOOKUP($B354,Custumer_Master!$A:$J,10,FALSE) -> South | K354: =VLOOKUP(B354,Custumer_Master!A:D,4,FALSE) -> RJ | L354: =PROPER(TRIM(VLOOKUP('Final Data'!C354,Product_Master!A:F,3,FALSE))) -> Electronics | M354: Keyboard | N354: 15 | O354: =VLOOKUP(C354,Product_Master!A:F,5,FALSE) -> 900 | P354: 0 | Q354: =(N354*O354)-(N354*O354)*P354 -> 13500 | R354: 3 | S354: Netbanking | T354: Aisha | U354: arjun.rao@company.com | V354: 9935018068 | W354: =VLOOKUP(C354,Product_Master!A:F,4,FALSE) -> TechHub | X354: =VLOOKUP(C354,Product_Master!A:F,6,FALSE) -> 6 | Y354: =VLOOKUP(B354,Custumer_Master!A:D,3,FALSE) -> Silver | Z354: =EDATE(E354,X354) -> 46277 | AA354: =VLOOKUP(B354,Custumer_Master!A:K,11,) -> February | AB354: Silver | AC354: =PROPER(LEFT(TRIM(F354), 3)) & RIGHT(TRIM(B354), 3) & PROPER(LEFT(TRIM(I354), 2)) -> Arj007Hy | AD354: =DATEDIF(H354, TODAY(), "Y") -> 38 | AE354: =IFERROR(IF(OR(E354="", D354="", LOWER(TRIM(E354))="pending", LOWER(TRIM(D354))="pending"), "Pending", E354 - D354), "Pending") -> 1 | AF354: =IFERROR(IF(OR(E354="", D354="","Pending","Pending"), "Pending", IF((E354 - D354) <= 5, "On Time", "Delayed")), "Pending") -> On Time | AG354: =IF(AF354="Pending","Pending","Completed") -> Completed
A355: ORD10354 | B355: C006 | C355: P103 | D355: 46120 | E355: 10/04/2026 | F355: =VLOOKUP(B355,Custumer_Master!A:D,2,FALSE) -> Sneha Joshi | G355: =VLOOKUP($B355,Custumer_Master!$A:$J,6,FALSE) -> Female | H355: =VLOOKUP($B355,Custumer_Master!$A:$J,7,FALSE) -> 04/04/1981 | I355: =VLOOKUP($B355,Custumer_Master!$A:$J,9,FALSE) -> Pune | J355: =VLOOKUP($B355,Custumer_Master!$A:$J,10,FALSE) -> West | K355: =VLOOKUP(B355,Custumer_Master!A:D,4,FALSE) -> WB | L355: =PROPER(TRIM(VLOOKUP('Final Data'!C355,Product_Master!A:F,3,FALSE))) -> Electronics | M355: Keyboard | N355: 19 | O355: =VLOOKUP(C355,Product_Master!A:F,5,FALSE) -> 900 | P355: 0 | Q355: =(N355*O355)-(N355*O355)*P355 -> 17100 | R355: 1 | S355: Cash | T355: Rahul | U355: sneha.joshi@company.com | V355: 9171794652 | W355: =VLOOKUP(C355,Product_Master!A:F,4,FALSE) -> TechHub | X355: =VLOOKUP(C355,Product_Master!A:F,6,FALSE) -> 6 | Y355: =VLOOKUP(B355,Custumer_Master!A:D,3,FALSE) -> Gold | Z355: =EDATE(E355,X355) -> 46305 | AA355: =VLOOKUP(B355,Custumer_Master!A:K,11,) -> April | AB355: Blacklisted | AC355: =PROPER(LEFT(TRIM(F355), 3)) & RIGHT(TRIM(B355), 3) & PROPER(LEFT(TRIM(I355), 2)) -> Sne006Pu | AD355: =DATEDIF(H355, TODAY(), "Y") -> 45 | AE355: =IFERROR(IF(OR(E355="", D355="", LOWER(TRIM(E355))="pending", LOWER(TRIM(D355))="pending"), "Pending", E355 - D355), "Pending") -> 2 | AF355: =IFERROR(IF(OR(E355="", D355="","Pending","Pending"), "Pending", IF((E355 - D355) <= 5, "On Time", "Delayed")), "Pending") -> On Time | AG355: =IF(AF355="Pending","Pending","Completed") -> Completed
A356: ORD10355 | B356: C004 | C356: P104 | D356: 45918 | E356: 25/09/2025 | F356: =VLOOKUP(B356,Custumer_Master!A:D,2,FALSE) -> Anita Gupta | G356: =VLOOKUP($B356,Custumer_Master!$A:$J,6,FALSE) -> Female | H356: =VLOOKUP($B356,Custumer_Master!$A:$J,7,FALSE) -> 16/01/2002 | I356: =VLOOKUP($B356,Custumer_Master!$A:$J,9,FALSE) -> Pune | J356: =VLOOKUP($B356,Custumer_Master!$A:$J,10,FALSE) -> West | K356: =VLOOKUP(B356,Custumer_Master!A:D,4,FALSE) -> WB | L356: =PROPER(TRIM(VLOOKUP('Final Data'!C356,Product_Master!A:F,3,FALSE))) -> Electronics | M356: Monitor | N356: 9 | O356: =VLOOKUP(C356,Product_Master!A:F,5,FALSE) -> 9000 | P356: 0.15 | Q356: =(N356*O356)-(N356*O356)*P356 -> 68850 | R356: 3 | S356: Upi | T356: Rahul | U356: anita.gupta@company.com | V356: 9671497416 | W356: =VLOOKUP(C356,Product_Master!A:F,4,FALSE) -> Global Trade | X356: =VLOOKUP(C356,Product_Master!A:F,6,FALSE) -> 24 | Y356: =VLOOKUP(B356,Custumer_Master!A:D,3,FALSE) -> Gold | Z356: =EDATE(E356,X356) -> 46655 | AA356: =VLOOKUP(B356,Custumer_Master!A:K,11,) -> January | AB356: Gold | AC356: =PROPER(LEFT(TRIM(F356), 3)) & RIGHT(TRIM(B356), 3) & PROPER(LEFT(TRIM(I356), 2)) -> Ani004Pu | AD356: =DATEDIF(H356, TODAY(), "Y") -> 24 | AE356: =IFERROR(IF(OR(E356="", D356="", LOWER(TRIM(E356))="pending", LOWER(TRIM(D356))="pending"), "Pending", E356 - D356), "Pending") -> 7 | AF356: =IFERROR(IF(OR(E356="", D356="","Pending","Pending"), "Pending", IF((E356 - D356) <= 5, "On Time", "Delayed")), "Pending") -> Delayed | AG356: =IF(AF356="Pending","Pending","Completed") -> Completed
A357: ORD10356 | B357: C008 | C357: P303 | D357: 45941 | E357: 21/10/2025 | F357: =VLOOKUP(B357,Custumer_Master!A:D,2,FALSE) -> Kavya Nair | G357: =VLOOKUP($B357,Custumer_Master!$A:$J,6,FALSE) -> Female | H357: =VLOOKUP($B357,Custumer_Master!$A:$J,7,FALSE) -> 01/08/1976 | I357: =VLOOKUP($B357,Custumer_Master!$A:$J,9,FALSE) -> Hyderabad | J357: =VLOOKUP($B357,Custumer_Master!$A:$J,10,FALSE) -> South | K357: =VLOOKUP(B357,Custumer_Master!A:D,4,FALSE) -> WB | L357: =PROPER(TRIM(VLOOKUP('Final Data'!C357,Product_Master!A:F,3,FALSE))) -> Stationery | M357: Marker | N357: 5 | O357: =VLOOKUP(C357,Product_Master!A:F,5,FALSE) -> 33.75 | P357: 0.05 | Q357: =(N357*O357)-(N357*O357)*P357 -> 160.3125 | R357: 1 | S357: Card | T357: Neha | U357: kavya.nair@company.com | V357: 9810433484 | W357: =VLOOKUP(C357,Product_Master!A:F,4,FALSE) -> TechHub | X357: =VLOOKUP(C357,Product_Master!A:F,6,FALSE) -> 12 | Y357: =VLOOKUP(B357,Custumer_Master!A:D,3,FALSE) -> Silver | Z357: =EDATE(E357,X357) -> 46316 | AA357: =VLOOKUP(B357,Custumer_Master!A:K,11,) -> August | AB357: Blacklisted | AC357: =PROPER(LEFT(TRIM(F357), 3)) & RIGHT(TRIM(B357), 3) & PROPER(LEFT(TRIM(I357), 2)) -> Kav008Hy | AD357: =DATEDIF(H357, TODAY(), "Y") -> 49 | AE357: =IFERROR(IF(OR(E357="", D357="", LOWER(TRIM(E357))="pending", LOWER(TRIM(D357))="pending"), "Pending", E357 - D357), "Pending") -> 10 | AF357: =IFERROR(IF(OR(E357="", D357="","Pending","Pending"), "Pending", IF((E357 - D357) <= 5, "On Time", "Delayed")), "Pending") -> Delayed | AG357: =IF(AF357="Pending","Pending","Completed") -> Completed
A358: ORD10357 | B358: C006 | C358: P102 | E358: 11/02/2025 | F358: =VLOOKUP(B358,Custumer_Master!A:D,2,FALSE) -> Sneha Joshi | G358: =VLOOKUP($B358,Custumer_Master!$A:$J,6,FALSE) -> Female | H358: =VLOOKUP($B358,Custumer_Master!$A:$J,7,FALSE) -> 04/04/1981 | I358: =VLOOKUP($B358,Custumer_Master!$A:$J,9,FALSE) -> Pune | J358: =VLOOKUP($B358,Custumer_Master!$A:$J,10,FALSE) -> West | K358: =VLOOKUP(B358,Custumer_Master!A:D,4,FALSE) -> WB | L358: =PROPER(TRIM(VLOOKUP('Final Data'!C358,Product_Master!A:F,3,FALSE))) -> Electronics | M358: Mouse | N358: 3 | O358: =VLOOKUP(C358,Product_Master!A:F,5,FALSE) -> 525 | P358: 0.15 | Q358: =(N358*O358)-(N358*O358)*P358 -> 1338.75 | R358: 4 | S358: Cash | T358: Karan | U358: sneha.joshi@company.com | V358: 9990243436 | W358: =VLOOKUP(C358,Product_Master!A:F,4,FALSE) -> TechHub | X358: =VLOOKUP(C358,Product_Master!A:F,6,FALSE) -> 24 | Y358: =VLOOKUP(B358,Custumer_Master!A:D,3,FALSE) -> Gold | Z358: =EDATE(E358,X358) -> 46429 | AA358: =VLOOKUP(B358,Custumer_Master!A:K,11,) -> April | AB358: Silver | AC358: =PROPER(LEFT(TRIM(F358), 3)) & RIGHT(TRIM(B358), 3) & PROPER(LEFT(TRIM(I358), 2)) -> Sne006Pu | AD358: =DATEDIF(H358, TODAY(), "Y") -> 45 | AE358: =IFERROR(IF(OR(E358="", D358="", LOWER(TRIM(E358))="pending", LOWER(TRIM(D358))="pending"), "Pending", E358 - D358), "Pending") -> Pending | AF358: =IFERROR(IF(OR(E358="", D358="","Pending","Pending"), "Pending", IF((E358 - D358) <= 5, "On Time", "Delayed")), "Pending") -> Pending | AG358: =IF(AF358="Pending","Pending","Completed") -> Pending
A359: ORD10358 | B359: C009 | C359: P203 | D359: 46005 | E359: 26/12/2025 | F359: =VLOOKUP(B359,Custumer_Master!A:D,2,FALSE) -> Mohit Verma | G359: =VLOOKUP($B359,Custumer_Master!$A:$J,6,FALSE) -> Male | H359: =VLOOKUP($B359,Custumer_Master!$A:$J,7,FALSE) -> 13/04/1976 | I359: =VLOOKUP($B359,Custumer_Master!$A:$J,9,FALSE) -> Delhi | J359: =VLOOKUP($B359,Custumer_Master!$A:$J,10,FALSE) -> North | K359: =VLOOKUP(B359,Custumer_Master!A:D,4,FALSE) -> KA | L359: =PROPER(TRIM(VLOOKUP('Final Data'!C359,Product_Master!A:F,3,FALSE))) -> Home Appliances | M359: Microwave | N359: 12 | O359: =VLOOKUP(C359,Product_Master!A:F,5,FALSE) -> 6375 | P359: 0.05 | Q359: =(N359*O359)-(N359*O359)*P359 -> 72675 | R359: 3 | S359: Card | T359: Aisha | U359: mohit.verma@company.com | V359: 9396678031 | W359: =VLOOKUP(C359,Product_Master!A:F,4,FALSE) -> TechHub | X359: =VLOOKUP(C359,Product_Master!A:F,6,FALSE) -> 24 | Y359: =VLOOKUP(B359,Custumer_Master!A:D,3,FALSE) -> Platinum | Z359: =EDATE(E359,X359) -> 46747 | AA359: =VLOOKUP(B359,Custumer_Master!A:K,11,) -> April | AB359: Gold | AC359: =PROPER(LEFT(TRIM(F359), 3)) & RIGHT(TRIM(B359), 3) & PROPER(LEFT(TRIM(I359), 2)) -> Moh009De | AD359: =DATEDIF(H359, TODAY(), "Y") -> 50 | AE359: =IFERROR(IF(OR(E359="", D359="", LOWER(TRIM(E359))="pending", LOWER(TRIM(D359))="pending"), "Pending", E359 - D359), "Pending") -> 12 | AF359: =IFERROR(IF(OR(E359="", D359="","Pending","Pending"), "Pending", IF((E359 - D359) <= 5, "On Time", "Delayed")), "Pending") -> Delayed | AG359: =IF(AF359="Pending","Pending","Completed") -> Completed
A360: ORD10359 | B360: C006 | C360: P203 | D360: 46123 | E360: 19/04/2026 | F360: =VLOOKUP(B360,Custumer_Master!A:D,2,FALSE) -> Sneha Joshi | G360: =VLOOKUP($B360,Custumer_Master!$A:$J,6,FALSE) -> Female | H360: =VLOOKUP($B360,Custumer_Master!$A:$J,7,FALSE) -> 04/04/1981 | I360: =VLOOKUP($B360,Custumer_Master!$A:$J,9,FALSE) -> Pune | J360: =VLOOKUP($B360,Custumer_Master!$A:$J,10,FALSE) -> West | K360: =VLOOKUP(B360,Custumer_Master!A:D,4,FALSE) -> WB | L360: =PROPER(TRIM(VLOOKUP('Final Data'!C360,Product_Master!A:F,3,FALSE))) -> Home Appliances | M360: Microwave | N360: 4 | O360: =VLOOKUP(C360,Product_Master!A:F,5,FALSE) -> 6375 | P360: 0.15 | Q360: =(N360*O360)-(N360*O360)*P360 -> 21675 | R360: 4 | S360: Netbanking | T360: Aisha | U360: sneha.joshi@company.com | V360: 9818591245 | W360: =VLOOKUP(C360,Product_Master!A:F,4,FALSE) -> TechHub | X360: =VLOOKUP(C360,Product_Master!A:F,6,FALSE) -> 24 | Y360: =VLOOKUP(B360,Custumer_Master!A:D,3,FALSE) -> Gold | Z360: =EDATE(E360,X360) -> 46862 | AA360: =VLOOKUP(B360,Custumer_Master!A:K,11,) -> April | AB360: Silver | AC360: =PROPER(LEFT(TRIM(F360), 3)) & RIGHT(TRIM(B360), 3) & PROPER(LEFT(TRIM(I360), 2)) -> Sne006Pu | AD360: =DATEDIF(H360, TODAY(), "Y") -> 45 | AE360: =IFERROR(IF(OR(E360="", D360="", LOWER(TRIM(E360))="pending", LOWER(TRIM(D360))="pending"), "Pending", E360 - D360), "Pending") -> 8 | AF360: =IFERROR(IF(OR(E360="", D360="","Pending","Pending"), "Pending", IF((E360 - D360) <= 5, "On Time", "Delayed")), "Pending") -> Delayed | AG360: =IF(AF360="Pending","Pending","Completed") -> Completed
A361: ORD10360 | B361: C003 | C361: P302 | D361: 45766 | E361: 22/04/2025 | F361: =VLOOKUP(B361,Custumer_Master!A:D,2,FALSE) -> Rohit Singh | G361: =VLOOKUP($B361,Custumer_Master!$A:$J,6,FALSE) -> Male | H361: =VLOOKUP($B361,Custumer_Master!$A:$J,7,FALSE) -> 10/05/1982 | I361: =VLOOKUP($B361,Custumer_Master!$A:$J,9,FALSE) -> Delhi | J361: =VLOOKUP($B361,Custumer_Master!$A:$J,10,FALSE) -> North | K361: =VLOOKUP(B361,Custumer_Master!A:D,4,FALSE) -> DL | L361: =PROPER(TRIM(VLOOKUP('Final Data'!C361,Product_Master!A:F,3,FALSE))) -> Stationery | M361: Pen | N361: 16 | O361: =VLOOKUP(C361,Product_Master!A:F,5,FALSE) -> 15 | P361: 0.1 | Q361: =(N361*O361)-(N361*O361)*P361 -> 216 | R361: 4 | S361: Cash | T361: Neha | U361: rohit.singh@company.com | V361: 9505550047 | W361: =VLOOKUP(C361,Product_Master!A:F,4,FALSE) -> Prime Supplies | X361: =VLOOKUP(C361,Product_Master!A:F,6,FALSE) -> 12 | Y361: =VLOOKUP(B361,Custumer_Master!A:D,3,FALSE) -> Gold | Z361: =EDATE(E361,X361) -> 46134 | AA361: =VLOOKUP(B361,Custumer_Master!A:K,11,) -> May | AB361: Silver | AC361: =PROPER(LEFT(TRIM(F361), 3)) & RIGHT(TRIM(B361), 3) & PROPER(LEFT(TRIM(I361), 2)) -> Roh003De | AD361: =DATEDIF(H361, TODAY(), "Y") -> 44 | AE361: =IFERROR(IF(OR(E361="", D361="", LOWER(TRIM(E361))="pending", LOWER(TRIM(D361))="pending"), "Pending", E361 - D361), "Pending") -> 3 | AF361: =IFERROR(IF(OR(E361="", D361="","Pending","Pending"), "Pending", IF((E361 - D361) <= 5, "On Time", "Delayed")), "Pending") -> On Time | AG361: =IF(AF361="Pending","Pending","Completed") -> Completed
A362: ORD10361 | B362: C003 | C362: P301 | D362: 46152 | E362: 18/05/2026 | F362: =VLOOKUP(B362,Custumer_Master!A:D,2,FALSE) -> Rohit Singh | G362: =VLOOKUP($B362,Custumer_Master!$A:$J,6,FALSE) -> Male | H362: =VLOOKUP($B362,Custumer_Master!$A:$J,7,FALSE) -> 10/05/1982 | I362: =VLOOKUP($B362,Custumer_Master!$A:$J,9,FALSE) -> Delhi | J362: =VLOOKUP($B362,Custumer_Master!$A:$J,10,FALSE) -> North | K362: =VLOOKUP(B362,Custumer_Master!A:D,4,FALSE) -> DL | L362: =PROPER(TRIM(VLOOKUP('Final Data'!C362,Product_Master!A:F,3,FALSE))) -> Stationery | M362: Notebook | N362: 3 | O362: =VLOOKUP(C362,Product_Master!A:F,5,FALSE) -> 45 | P362: 0.2 | Q362: =(N362*O362)-(N362*O362)*P362 -> 108 | R362: 4 | S362: Upi | T362: Karan | U362: rohit.singh@company.com | V362: 9469828772 | W362: =VLOOKUP(C362,Product_Master!A:F,4,FALSE) -> ABC Corp | X362: =VLOOKUP(C362,Product_Master!A:F,6,FALSE) -> 12 | Y362: =VLOOKUP(B362,Custumer_Master!A:D,3,FALSE) -> Gold | Z362: =EDATE(E362,X362) -> 46525 | AA362: =VLOOKUP(B362,Custumer_Master!A:K,11,) -> May | AB362: Silver | AC362: =PROPER(LEFT(TRIM(F362), 3)) & RIGHT(TRIM(B362), 3) & PROPER(LEFT(TRIM(I362), 2)) -> Roh003De | AD362: =DATEDIF(H362, TODAY(), "Y") -> 44 | AE362: =IFERROR(IF(OR(E362="", D362="", LOWER(TRIM(E362))="pending", LOWER(TRIM(D362))="pending"), "Pending", E362 - D362), "Pending") -> 8 | AF362: =IFERROR(IF(OR(E362="", D362="","Pending","Pending"), "Pending", IF((E362 - D362) <= 5, "On Time", "Delayed")), "Pending") -> Delayed | AG362: =IF(AF362="Pending","Pending","Completed") -> Completed
A363: ORD10362 | B363: C009 | C363: P202 | D363: 45858 | E363: 26/07/2025 | F363: =VLOOKUP(B363,Custumer_Master!A:D,2,FALSE) -> Mohit Verma | G363: =VLOOKUP($B363,Custumer_Master!$A:$J,6,FALSE) -> Male | H363: =VLOOKUP($B363,Custumer_Master!$A:$J,7,FALSE) -> 13/04/1976 | I363: =VLOOKUP($B363,Custumer_Master!$A:$J,9,FALSE) -> Delhi | J363: =VLOOKUP($B363,Custumer_Master!$A:$J,10,FALSE) -> North | K363: =VLOOKUP(B363,Custumer_Master!A:D,4,FALSE) -> KA | L363: =PROPER(TRIM(VLOOKUP('Final Data'!C363,Product_Master!A:F,3,FALSE))) -> Home Appliances | M363: Iron | N363: 19 | O363: =VLOOKUP(C363,Product_Master!A:F,5,FALSE) -> 1650 | P363: 0.1 | Q363: =(N363*O363)-(N363*O363)*P363 -> 28215 | R363: 2 | S363: Cash | T363: Karan | U363: mohit.verma@company.com | V363: 9885092680 | W363: =VLOOKUP(C363,Product_Master!A:F,4,FALSE) -> Global Trade | X363: =VLOOKUP(C363,Product_Master!A:F,6,FALSE) -> 24 | Y363: =VLOOKUP(B363,Custumer_Master!A:D,3,FALSE) -> Platinum | Z363: =EDATE(E363,X363) -> 46594 | AA363: =VLOOKUP(B363,Custumer_Master!A:K,11,) -> April | AB363: Blacklisted | AC363: =PROPER(LEFT(TRIM(F363), 3)) & RIGHT(TRIM(B363), 3) & PROPER(LEFT(TRIM(I363), 2)) -> Moh009De | AD363: =DATEDIF(H363, TODAY(), "Y") -> 50 | AE363: =IFERROR(IF(OR(E363="", D363="", LOWER(TRIM(E363))="pending", LOWER(TRIM(D363))="pending"), "Pending", E363 - D363), "Pending") -> 6 | AF363: =IFERROR(IF(OR(E363="", D363="","Pending","Pending"), "Pending", IF((E363 - D363) <= 5, "On Time", "Delayed")), "Pending") -> Delayed | AG363: =IF(AF363="Pending","Pending","Completed") -> Completed
A364: ORD10363 | B364: C009 | C364: P103 | D364: 46045 | E364: 27/01/2026 | F364: =VLOOKUP(B364,Custumer_Master!A:D,2,FALSE) -> Mohit Verma | G364: =VLOOKUP($B364,Custumer_Master!$A:$J,6,FALSE) -> Male | H364: =VLOOKUP($B364,Custumer_Master!$A:$J,7,FALSE) -> 13/04/1976 | I364: =VLOOKUP($B364,Custumer_Master!$A:$J,9,FALSE) -> Delhi | J364: =VLOOKUP($B364,Custumer_Master!$A:$J,10,FALSE) -> North | K364: =VLOOKUP(B364,Custumer_Master!A:D,4,FALSE) -> KA | L364: =PROPER(TRIM(VLOOKUP('Final Data'!C364,Product_Master!A:F,3,FALSE))) -> Electronics | M364: Keyboard | N364: 7 | O364: =VLOOKUP(C364,Product_Master!A:F,5,FALSE) -> 900 | P364: 0.2 | Q364: =(N364*O364)-(N364*O364)*P364 -> 5040 | R364: 3 | S364: Card | T364: Neha | U364: mohit.verma@company.com | V364: 9362319457 | W364: =VLOOKUP(C364,Product_Master!A:F,4,FALSE) -> TechHub | X364: =VLOOKUP(C364,Product_Master!A:F,6,FALSE) -> 6 | Y364: =VLOOKUP(B364,Custumer_Master!A:D,3,FALSE) -> Platinum | Z364: =EDATE(E364,X364) -> 46230 | AA364: =VLOOKUP(B364,Custumer_Master!A:K,11,) -> April | AB364: Silver | AC364: =PROPER(LEFT(TRIM(F364), 3)) & RIGHT(TRIM(B364), 3) & PROPER(LEFT(TRIM(I364), 2)) -> Moh009De | AD364: =DATEDIF(H364, TODAY(), "Y") -> 50 | AE364: =IFERROR(IF(OR(E364="", D364="", LOWER(TRIM(E364))="pending", LOWER(TRIM(D364))="pending"), "Pending", E364 - D364), "Pending") -> 4 | AF364: =IFERROR(IF(OR(E364="", D364="","Pending","Pending"), "Pending", IF((E364 - D364) <= 5, "On Time", "Delayed")), "Pending") -> On Time | AG364: =IF(AF364="Pending","Pending","Completed") -> Completed
A365: ORD10364 | B365: C010 | C365: P302 | D365: 46097 | E365: 21/03/2026 | F365: =VLOOKUP(B365,Custumer_Master!A:D,2,FALSE) -> Pooja Shah | G365: =VLOOKUP($B365,Custumer_Master!$A:$J,6,FALSE) -> Female | H365: =VLOOKUP($B365,Custumer_Master!$A:$J,7,FALSE) -> 16/09/1994 | I365: =VLOOKUP($B365,Custumer_Master!$A:$J,9,FALSE) -> Bengaluru | J365: =VLOOKUP($B365,Custumer_Master!$A:$J,10,FALSE) -> South | K365: =VLOOKUP(B365,Custumer_Master!A:D,4,FALSE) -> WB | L365: =PROPER(TRIM(VLOOKUP('Final Data'!C365,Product_Master!A:F,3,FALSE))) -> Stationery | M365: Pen | N365: 20 | O365: =VLOOKUP(C365,Product_Master!A:F,5,FALSE) -> 15 | P365: 0.2 | Q365: =(N365*O365)-(N365*O365)*P365 -> 240 | R365: 5 | S365: Card | T365: Neha | U365: pooja.shah@company.com | V365: 9223945130 | W365: =VLOOKUP(C365,Product_Master!A:F,4,FALSE) -> Prime Supplies | X365: =VLOOKUP(C365,Product_Master!A:F,6,FALSE) -> 12 | Y365: =VLOOKUP(B365,Custumer_Master!A:D,3,FALSE) -> Silver | Z365: =EDATE(E365,X365) -> 46467 | AA365: =VLOOKUP(B365,Custumer_Master!A:K,11,) -> September | AB365: Silver | AC365: =PROPER(LEFT(TRIM(F365), 3)) & RIGHT(TRIM(B365), 3) & PROPER(LEFT(TRIM(I365), 2)) -> Poo010Be | AD365: =DATEDIF(H365, TODAY(), "Y") -> 31 | AE365: =IFERROR(IF(OR(E365="", D365="", LOWER(TRIM(E365))="pending", LOWER(TRIM(D365))="pending"), "Pending", E365 - D365), "Pending") -> 5 | AF365: =IFERROR(IF(OR(E365="", D365="","Pending","Pending"), "Pending", IF((E365 - D365) <= 5, "On Time", "Delayed")), "Pending") -> On Time | AG365: =IF(AF365="Pending","Pending","Completed") -> Completed
A366: ORD10365 | B366: C002 | C366: P103 | D366: 45777 | E366: 07/05/2025 | F366: =VLOOKUP(B366,Custumer_Master!A:D,2,FALSE) -> Priya Patel | G366: =VLOOKUP($B366,Custumer_Master!$A:$J,6,FALSE) -> Female | H366: =VLOOKUP($B366,Custumer_Master!$A:$J,7,FALSE) -> 07/03/1995 | I366: =VLOOKUP($B366,Custumer_Master!$A:$J,9,FALSE) -> Mumbai | J366: =VLOOKUP($B366,Custumer_Master!$A:$J,10,FALSE) -> West | K366: =VLOOKUP(B366,Custumer_Master!A:D,4,FALSE) -> WB | L366: =PROPER(TRIM(VLOOKUP('Final Data'!C366,Product_Master!A:F,3,FALSE))) -> Electronics | M366: Keyboard | N366: 19 | O366: =VLOOKUP(C366,Product_Master!A:F,5,FALSE) -> 900 | P366: 0.05 | Q366: =(N366*O366)-(N366*O366)*P366 -> 16245 | R366: 3 | S366: Card | T366: Ritika | U366: priya.patel@company.com | V366: 9910804926 | W366: =VLOOKUP(C366,Product_Master!A:F,4,FALSE) -> TechHub | X366: =VLOOKUP(C366,Product_Master!A:F,6,FALSE) -> 6 | Y366: =VLOOKUP(B366,Custumer_Master!A:D,3,FALSE) -> Platinum | Z366: =EDATE(E366,X366) -> 45968 | AA366: =VLOOKUP(B366,Custumer_Master!A:K,11,) -> March | AB366: Silver | AC366: =PROPER(LEFT(TRIM(F366), 3)) & RIGHT(TRIM(B366), 3) & PROPER(LEFT(TRIM(I366), 2)) -> Pri002Mu | AD366: =DATEDIF(H366, TODAY(), "Y") -> 31 | AE366: =IFERROR(IF(OR(E366="", D366="", LOWER(TRIM(E366))="pending", LOWER(TRIM(D366))="pending"), "Pending", E366 - D366), "Pending") -> 7 | AF366: =IFERROR(IF(OR(E366="", D366="","Pending","Pending"), "Pending", IF((E366 - D366) <= 5, "On Time", "Delayed")), "Pending") -> Delayed | AG366: =IF(AF366="Pending","Pending","Completed") -> Completed
A367: ORD10366 | B367: C010 | C367: P302 | D367: 45691 | E367: 13/02/2025 | F367: =VLOOKUP(B367,Custumer_Master!A:D,2,FALSE) -> Pooja Shah | G367: =VLOOKUP($B367,Custumer_Master!$A:$J,6,FALSE) -> Female | H367: =VLOOKUP($B367,Custumer_Master!$A:$J,7,FALSE) -> 16/09/1994 | I367: =VLOOKUP($B367,Custumer_Master!$A:$J,9,FALSE) -> Bengaluru | J367: =VLOOKUP($B367,Custumer_Master!$A:$J,10,FALSE) -> South | K367: =VLOOKUP(B367,Custumer_Master!A:D,4,FALSE) -> WB | L367: =PROPER(TRIM(VLOOKUP('Final Data'!C367,Product_Master!A:F,3,FALSE))) -> Stationery | M367: Pen | N367: 5 | O367: =VLOOKUP(C367,Product_Master!A:F,5,FALSE) -> 15 | P367: 0 | Q367: =(N367*O367)-(N367*O367)*P367 -> 75 | R367: 2 | S367: Upi | T367: Rahul | U367: pooja.shah@company.com | V367: 9274269744 | W367: =VLOOKUP(C367,Product_Master!A:F,4,FALSE) -> Prime Supplies | X367: =VLOOKUP(C367,Product_Master!A:F,6,FALSE) -> 12 | Y367: =VLOOKUP(B367,Custumer_Master!A:D,3,FALSE) -> Silver | Z367: =EDATE(E367,X367) -> 46066 | AA367: =VLOOKUP(B367,Custumer_Master!A:K,11,) -> September | AB367: Blacklisted | AC367: =PROPER(LEFT(TRIM(F367), 3)) & RIGHT(TRIM(B367), 3) & PROPER(LEFT(TRIM(I367), 2)) -> Poo010Be | AD367: =DATEDIF(H367, TODAY(), "Y") -> 31 | AE367: =IFERROR(IF(OR(E367="", D367="", LOWER(TRIM(E367))="pending", LOWER(TRIM(D367))="pending"), "Pending", E367 - D367), "Pending") -> 10 | AF367: =IFERROR(IF(OR(E367="", D367="","Pending","Pending"), "Pending", IF((E367 - D367) <= 5, "On Time", "Delayed")), "Pending") -> Delayed | AG367: =IF(AF367="Pending","Pending","Completed") -> Completed
A368: ORD10367 | B368: C002 | C368: P303 | D368: 46088 | E368: 16/03/2026 | F368: =VLOOKUP(B368,Custumer_Master!A:D,2,FALSE) -> Priya Patel | G368: =VLOOKUP($B368,Custumer_Master!$A:$J,6,FALSE) -> Female | H368: =VLOOKUP($B368,Custumer_Master!$A:$J,7,FALSE) -> 07/03/1995 | I368: =VLOOKUP($B368,Custumer_Master!$A:$J,9,FALSE) -> Mumbai | J368: =VLOOKUP($B368,Custumer_Master!$A:$J,10,FALSE) -> West | K368: =VLOOKUP(B368,Custumer_Master!A:D,4,FALSE) -> WB | L368: =PROPER(TRIM(VLOOKUP('Final Data'!C368,Product_Master!A:F,3,FALSE))) -> Stationery | M368: Marker | N368: 16 | O368: =VLOOKUP(C368,Product_Master!A:F,5,FALSE) -> 33.75 | P368: 0.15 | Q368: =(N368*O368)-(N368*O368)*P368 -> 459 | R368: 5 | S368: Cash | T368: Aisha | U368: priya.patel@company.com | V368: 9223196101 | W368: =VLOOKUP(C368,Product_Master!A:F,4,FALSE) -> TechHub | X368: =VLOOKUP(C368,Product_Master!A:F,6,FALSE) -> 12 | Y368: =VLOOKUP(B368,Custumer_Master!A:D,3,FALSE) -> Platinum | Z368: =EDATE(E368,X368) -> 46462 | AA368: =VLOOKUP(B368,Custumer_Master!A:K,11,) -> March | AB368: Silver | AC368: =PROPER(LEFT(TRIM(F368), 3)) & RIGHT(TRIM(B368), 3) & PROPER(LEFT(TRIM(I368), 2)) -> Pri002Mu | AD368: =DATEDIF(H368, TODAY(), "Y") -> 31 | AE368: =IFERROR(IF(OR(E368="", D368="", LOWER(TRIM(E368))="pending", LOWER(TRIM(D368))="pending"), "Pending", E368 - D368), "Pending") -> 9 | AF368: =IFERROR(IF(OR(E368="", D368="","Pending","Pending"), "Pending", IF((E368 - D368) <= 5, "On Time", "Delayed")), "Pending") -> Delayed | AG368: =IF(AF368="Pending","Pending","Completed") -> Completed
A369: ORD10368 | B369: C008 | C369: P202 | D369: 45780 | E369: 15/05/2025 | F369: =VLOOKUP(B369,Custumer_Master!A:D,2,FALSE) -> Kavya Nair | G369: =VLOOKUP($B369,Custumer_Master!$A:$J,6,FALSE) -> Female | H369: =VLOOKUP($B369,Custumer_Master!$A:$J,7,FALSE) -> 01/08/1976 | I369: =VLOOKUP($B369,Custumer_Master!$A:$J,9,FALSE) -> Hyderabad | J369: =VLOOKUP($B369,Custumer_Master!$A:$J,10,FALSE) -> South | K369: =VLOOKUP(B369,Custumer_Master!A:D,4,FALSE) -> WB | L369: =PROPER(TRIM(VLOOKUP('Final Data'!C369,Product_Master!A:F,3,FALSE))) -> Home Appliances | M369: Iron | N369: 1 | O369: =VLOOKUP(C369,Product_Master!A:F,5,FALSE) -> 1650 | P369: 0.1 | Q369: =(N369*O369)-(N369*O369)*P369 -> 1485 | R369: 5 | S369: Card | T369: Rahul | U369: kavya.nair@company.com | V369: 9888477457 | W369: =VLOOKUP(C369,Product_Master!A:F,4,FALSE) -> Global Trade | X369: =VLOOKUP(C369,Product_Master!A:F,6,FALSE) -> 24 | Y369: =VLOOKUP(B369,Custumer_Master!A:D,3,FALSE) -> Silver | Z369: =EDATE(E369,X369) -> 46522 | AA369: =VLOOKUP(B369,Custumer_Master!A:K,11,) -> August | AB369: Silver | AC369: =PROPER(LEFT(TRIM(F369), 3)) & RIGHT(TRIM(B369), 3) & PROPER(LEFT(TRIM(I369), 2)) -> Kav008Hy | AD369: =DATEDIF(H369, TODAY(), "Y") -> 49 | AE369: =IFERROR(IF(OR(E369="", D369="", LOWER(TRIM(E369))="pending", LOWER(TRIM(D369))="pending"), "Pending", E369 - D369), "Pending") -> 12 | AF369: =IFERROR(IF(OR(E369="", D369="","Pending","Pending"), "Pending", IF((E369 - D369) <= 5, "On Time", "Delayed")), "Pending") -> Delayed | AG369: =IF(AF369="Pending","Pending","Completed") -> Completed
A370: ORD10369 | B370: C010 | C370: P301 | D370: 46113 | E370: 05/04/2026 | F370: =VLOOKUP(B370,Custumer_Master!A:D,2,FALSE) -> Pooja Shah | G370: =VLOOKUP($B370,Custumer_Master!$A:$J,6,FALSE) -> Female | H370: =VLOOKUP($B370,Custumer_Master!$A:$J,7,FALSE) -> 16/09/1994 | I370: =VLOOKUP($B370,Custumer_Master!$A:$J,9,FALSE) -> Bengaluru | J370: =VLOOKUP($B370,Custumer_Master!$A:$J,10,FALSE) -> South | K370: =VLOOKUP(B370,Custumer_Master!A:D,4,FALSE) -> WB | L370: =PROPER(TRIM(VLOOKUP('Final Data'!C370,Product_Master!A:F,3,FALSE))) -> Stationery | M370: Notebook | N370: 19 | O370: =VLOOKUP(C370,Product_Master!A:F,5,FALSE) -> 45 | P370: 0.15 | Q370: =(N370*O370)-(N370*O370)*P370 -> 726.75 | R370: 4 | S370: Netbanking | T370: Neha | U370: pooja.shah@company.com | V370: 9435947486 | W370: =VLOOKUP(C370,Product_Master!A:F,4,FALSE) -> ABC Corp | X370: =VLOOKUP(C370,Product_Master!A:F,6,FALSE) -> 12 | Y370: =VLOOKUP(B370,Custumer_Master!A:D,3,FALSE) -> Silver | Z370: =EDATE(E370,X370) -> 46482 | AA370: =VLOOKUP(B370,Custumer_Master!A:K,11,) -> September | AB370: Silver | AC370: =PROPER(LEFT(TRIM(F370), 3)) & RIGHT(TRIM(B370), 3) & PROPER(LEFT(TRIM(I370), 2)) -> Poo010Be | AD370: =DATEDIF(H370, TODAY(), "Y") -> 31 | AE370: =IFERROR(IF(OR(E370="", D370="", LOWER(TRIM(E370))="pending", LOWER(TRIM(D370))="pending"), "Pending", E370 - D370), "Pending") -> 4 | AF370: =IFERROR(IF(OR(E370="", D370="","Pending","Pending"), "Pending", IF((E370 - D370) <= 5, "On Time", "Delayed")), "Pending") -> On Time | AG370: =IF(AF370="Pending","Pending","Completed") -> Completed
A371: ORD10370 | B371: C001 | C371: P101 | E371: 02/02/2025 | F371: =VLOOKUP(B371,Custumer_Master!A:D,2,FALSE) -> Amit Sharma | G371: =VLOOKUP($B371,Custumer_Master!$A:$J,6,FALSE) -> Male | H371: =VLOOKUP($B371,Custumer_Master!$A:$J,7,FALSE) -> 09/08/1991 | I371: =VLOOKUP($B371,Custumer_Master!$A:$J,9,FALSE) -> Pune | J371: =VLOOKUP($B371,Custumer_Master!$A:$J,10,FALSE) -> West | K371: =VLOOKUP(B371,Custumer_Master!A:D,4,FALSE) -> RJ | L371: =PROPER(TRIM(VLOOKUP('Final Data'!C371,Product_Master!A:F,3,FALSE))) -> Electronics | M371: Laptop | N371: 15 | O371: =VLOOKUP(C371,Product_Master!A:F,5,FALSE) -> 41250 | P371: 0 | Q371: =(N371*O371)-(N371*O371)*P371 -> 618750 | R371: 5 | S371: Card | T371: Neha | U371: amit.sharma@company.com | V371: 9411668831 | W371: =VLOOKUP(C371,Product_Master!A:F,4,FALSE) -> TechHub | X371: =VLOOKUP(C371,Product_Master!A:F,6,FALSE) -> 12 | Y371: =VLOOKUP(B371,Custumer_Master!A:D,3,FALSE) -> Silver | Z371: =EDATE(E371,X371) -> 46055 | AA371: =VLOOKUP(B371,Custumer_Master!A:K,11,) -> August | AB371: Platinum | AC371: =PROPER(LEFT(TRIM(F371), 3)) & RIGHT(TRIM(B371), 3) & PROPER(LEFT(TRIM(I371), 2)) -> Ami001Pu | AD371: =DATEDIF(H371, TODAY(), "Y") -> 34 | AE371: =IFERROR(IF(OR(E371="", D371="", LOWER(TRIM(E371))="pending", LOWER(TRIM(D371))="pending"), "Pending", E371 - D371), "Pending") -> Pending | AF371: =IFERROR(IF(OR(E371="", D371="","Pending","Pending"), "Pending", IF((E371 - D371) <= 5, "On Time", "Delayed")), "Pending") -> Pending | AG371: =IF(AF371="Pending","Pending","Completed") -> Pending
A372: ORD10371 | B372: C009 | C372: P303 | D372: 45936 | E372: 08/10/2025 | F372: =VLOOKUP(B372,Custumer_Master!A:D,2,FALSE) -> Mohit Verma | G372: =VLOOKUP($B372,Custumer_Master!$A:$J,6,FALSE) -> Male | H372: =VLOOKUP($B372,Custumer_Master!$A:$J,7,FALSE) -> 13/04/1976 | I372: =VLOOKUP($B372,Custumer_Master!$A:$J,9,FALSE) -> Delhi | J372: =VLOOKUP($B372,Custumer_Master!$A:$J,10,FALSE) -> North | K372: =VLOOKUP(B372,Custumer_Master!A:D,4,FALSE) -> KA | L372: =PROPER(TRIM(VLOOKUP('Final Data'!C372,Product_Master!A:F,3,FALSE))) -> Stationery | M372: Marker | N372: 11 | O372: =VLOOKUP(C372,Product_Master!A:F,5,FALSE) -> 33.75 | P372: 0.05 | Q372: =(N372*O372)-(N372*O372)*P372 -> 352.6875 | R372: 5 | S372: Netbanking | T372: Karan | U372: mohit.verma@company.com | V372: 9523682403 | W372: =VLOOKUP(C372,Product_Master!A:F,4,FALSE) -> TechHub | X372: =VLOOKUP(C372,Product_Master!A:F,6,FALSE) -> 12 | Y372: =VLOOKUP(B372,Custumer_Master!A:D,3,FALSE) -> Platinum | Z372: =EDATE(E372,X372) -> 46303 | AA372: =VLOOKUP(B372,Custumer_Master!A:K,11,) -> April | AB372: Silver | AC372: =PROPER(LEFT(TRIM(F372), 3)) & RIGHT(TRIM(B372), 3) & PROPER(LEFT(TRIM(I372), 2)) -> Moh009De | AD372: =DATEDIF(H372, TODAY(), "Y") -> 50 | AE372: =IFERROR(IF(OR(E372="", D372="", LOWER(TRIM(E372))="pending", LOWER(TRIM(D372))="pending"), "Pending", E372 - D372), "Pending") -> 2 | AF372: =IFERROR(IF(OR(E372="", D372="","Pending","Pending"), "Pending", IF((E372 - D372) <= 5, "On Time", "Delayed")), "Pending") -> On Time | AG372: =IF(AF372="Pending","Pending","Completed") -> Completed
A373: ORD10372 | B373: C006 | C373: P302 | D373: 45820 | E373: 17/06/2025 | F373: =VLOOKUP(B373,Custumer_Master!A:D,2,FALSE) -> Sneha Joshi | G373: =VLOOKUP($B373,Custumer_Master!$A:$J,6,FALSE) -> Female | H373: =VLOOKUP($B373,Custumer_Master!$A:$J,7,FALSE) -> 04/04/1981 | I373: =VLOOKUP($B373,Custumer_Master!$A:$J,9,FALSE) -> Pune | J373: =VLOOKUP($B373,Custumer_Master!$A:$J,10,FALSE) -> West | K373: =VLOOKUP(B373,Custumer_Master!A:D,4,FALSE) -> WB | L373: =PROPER(TRIM(VLOOKUP('Final Data'!C373,Product_Master!A:F,3,FALSE))) -> Stationery | M373: Pen | N373: 9 | O373: =VLOOKUP(C373,Product_Master!A:F,5,FALSE) -> 15 | P373: 0.1 | Q373: =(N373*O373)-(N373*O373)*P373 -> 121.5 | R373: 1 | S373: Card | T373: Rahul | U373: sneha.joshi@company.com | V373: 9652936744 | W373: =VLOOKUP(C373,Product_Master!A:F,4,FALSE) -> Prime Supplies | X373: =VLOOKUP(C373,Product_Master!A:F,6,FALSE) -> 12 | Y373: =VLOOKUP(B373,Custumer_Master!A:D,3,FALSE) -> Gold | Z373: =EDATE(E373,X373) -> 46190 | AA373: =VLOOKUP(B373,Custumer_Master!A:K,11,) -> April | AB373: Blacklisted | AC373: =PROPER(LEFT(TRIM(F373), 3)) & RIGHT(TRIM(B373), 3) & PROPER(LEFT(TRIM(I373), 2)) -> Sne006Pu | AD373: =DATEDIF(H373, TODAY(), "Y") -> 45 | AE373: =IFERROR(IF(OR(E373="", D373="", LOWER(TRIM(E373))="pending", LOWER(TRIM(D373))="pending"), "Pending", E373 - D373), "Pending") -> 5 | AF373: =IFERROR(IF(OR(E373="", D373="","Pending","Pending"), "Pending", IF((E373 - D373) <= 5, "On Time", "Delayed")), "Pending") -> On Time | AG373: =IF(AF373="Pending","Pending","Completed") -> Completed
A374: ORD10373 | B374: C004 | C374: P303 | D374: 45979 | E374: 20/11/2025 | F374: =VLOOKUP(B374,Custumer_Master!A:D,2,FALSE) -> Anita Gupta | G374: =VLOOKUP($B374,Custumer_Master!$A:$J,6,FALSE) -> Female | H374: =VLOOKUP($B374,Custumer_Master!$A:$J,7,FALSE) -> 16/01/2002 | I374: =VLOOKUP($B374,Custumer_Master!$A:$J,9,FALSE) -> Pune | J374: =VLOOKUP($B374,Custumer_Master!$A:$J,10,FALSE) -> West | K374: =VLOOKUP(B374,Custumer_Master!A:D,4,FALSE) -> WB | L374: =PROPER(TRIM(VLOOKUP('Final Data'!C374,Product_Master!A:F,3,FALSE))) -> Stationery | M374: Marker | N374: 5 | O374: =VLOOKUP(C374,Product_Master!A:F,5,FALSE) -> 33.75 | P374: 0.05 | Q374: =(N374*O374)-(N374*O374)*P374 -> 160.3125 | R374: 3 | S374: Card | T374: Neha | U374: anita.gupta@company.com | V374: 9726464733 | W374: =VLOOKUP(C374,Product_Master!A:F,4,FALSE) -> TechHub | X374: =VLOOKUP(C374,Product_Master!A:F,6,FALSE) -> 12 | Y374: =VLOOKUP(B374,Custumer_Master!A:D,3,FALSE) -> Gold | Z374: =EDATE(E374,X374) -> 46346 | AA374: =VLOOKUP(B374,Custumer_Master!A:K,11,) -> January | AB374: Silver | AC374: =PROPER(LEFT(TRIM(F374), 3)) & RIGHT(TRIM(B374), 3) & PROPER(LEFT(TRIM(I374), 2)) -> Ani004Pu | AD374: =DATEDIF(H374, TODAY(), "Y") -> 24 | AE374: =IFERROR(IF(OR(E374="", D374="", LOWER(TRIM(E374))="pending", LOWER(TRIM(D374))="pending"), "Pending", E374 - D374), "Pending") -> 2 | AF374: =IFERROR(IF(OR(E374="", D374="","Pending","Pending"), "Pending", IF((E374 - D374) <= 5, "On Time", "Delayed")), "Pending") -> On Time | AG374: =IF(AF374="Pending","Pending","Completed") -> Completed
A375: ORD10374 | B375: C007 | C375: P102 | D375: 45962 | E375: 02/11/2025 | F375: =VLOOKUP(B375,Custumer_Master!A:D,2,FALSE) -> Arjun Rao | G375: =VLOOKUP($B375,Custumer_Master!$A:$J,6,FALSE) -> Male | H375: =VLOOKUP($B375,Custumer_Master!$A:$J,7,FALSE) -> 07/02/1988 | I375: =VLOOKUP($B375,Custumer_Master!$A:$J,9,FALSE) -> Hyderabad | J375: =VLOOKUP($B375,Custumer_Master!$A:$J,10,FALSE) -> South | K375: =VLOOKUP(B375,Custumer_Master!A:D,4,FALSE) -> RJ | L375: =PROPER(TRIM(VLOOKUP('Final Data'!C375,Product_Master!A:F,3,FALSE))) -> Electronics | M375: Mouse | N375: 5 | O375: =VLOOKUP(C375,Product_Master!A:F,5,FALSE) -> 525 | P375: 0.1 | Q375: =(N375*O375)-(N375*O375)*P375 -> 2362.5 | R375: 2 | S375: Upi | T375: Rahul | U375: arjun.rao@company.com | V375: 9273520544 | W375: =VLOOKUP(C375,Product_Master!A:F,4,FALSE) -> TechHub | X375: =VLOOKUP(C375,Product_Master!A:F,6,FALSE) -> 24 | Y375: =VLOOKUP(B375,Custumer_Master!A:D,3,FALSE) -> Silver | Z375: =EDATE(E375,X375) -> 46693 | AA375: =VLOOKUP(B375,Custumer_Master!A:K,11,) -> February | AB375: Blacklisted | AC375: =PROPER(LEFT(TRIM(F375), 3)) & RIGHT(TRIM(B375), 3) & PROPER(LEFT(TRIM(I375), 2)) -> Arj007Hy | AD375: =DATEDIF(H375, TODAY(), "Y") -> 38 | AE375: =IFERROR(IF(OR(E375="", D375="", LOWER(TRIM(E375))="pending", LOWER(TRIM(D375))="pending"), "Pending", E375 - D375), "Pending") -> 1 | AF375: =IFERROR(IF(OR(E375="", D375="","Pending","Pending"), "Pending", IF((E375 - D375) <= 5, "On Time", "Delayed")), "Pending") -> On Time | AG375: =IF(AF375="Pending","Pending","Completed") -> Completed
A376: ORD10375 | B376: C005 | C376: P102 | D376: 45681 | E376: 31/01/2025 | F376: =VLOOKUP(B376,Custumer_Master!A:D,2,FALSE) -> Vikas Mehta | G376: =VLOOKUP($B376,Custumer_Master!$A:$J,6,FALSE) -> Male | H376: =VLOOKUP($B376,Custumer_Master!$A:$J,7,FALSE) -> 03/08/1991 | I376: =VLOOKUP($B376,Custumer_Master!$A:$J,9,FALSE) -> Mumbai | J376: =VLOOKUP($B376,Custumer_Master!$A:$J,10,FALSE) -> West | K376: =VLOOKUP(B376,Custumer_Master!A:D,4,FALSE) -> DL | L376: =PROPER(TRIM(VLOOKUP('Final Data'!C376,Product_Master!A:F,3,FALSE))) -> Electronics | M376: Mouse | N376: 1 | O376: =VLOOKUP(C376,Product_Master!A:F,5,FALSE) -> 525 | P376: 0 | Q376: =(N376*O376)-(N376*O376)*P376 -> 525 | R376: 1 | S376: Upi | T376: Karan | U376: vikas.mehta@company.com | V376: 9374259988 | W376: =VLOOKUP(C376,Product_Master!A:F,4,FALSE) -> TechHub | X376: =VLOOKUP(C376,Product_Master!A:F,6,FALSE) -> 24 | Y376: =VLOOKUP(B376,Custumer_Master!A:D,3,FALSE) -> Gold | Z376: =EDATE(E376,X376) -> 46418 | AA376: =VLOOKUP(B376,Custumer_Master!A:K,11,) -> August | AB376: Blacklisted | AC376: =PROPER(LEFT(TRIM(F376), 3)) & RIGHT(TRIM(B376), 3) & PROPER(LEFT(TRIM(I376), 2)) -> Vik005Mu | AD376: =DATEDIF(H376, TODAY(), "Y") -> 34 | AE376: =IFERROR(IF(OR(E376="", D376="", LOWER(TRIM(E376))="pending", LOWER(TRIM(D376))="pending"), "Pending", E376 - D376), "Pending") -> 7 | AF376: =IFERROR(IF(OR(E376="", D376="","Pending","Pending"), "Pending", IF((E376 - D376) <= 5, "On Time", "Delayed")), "Pending") -> Delayed | AG376: =IF(AF376="Pending","Pending","Completed") -> Completed
A377: ORD10376 | B377: C008 | C377: P102 | D377: 46066 | E377: 21/02/2026 | F377: =VLOOKUP(B377,Custumer_Master!A:D,2,FALSE) -> Kavya Nair | G377: =VLOOKUP($B377,Custumer_Master!$A:$J,6,FALSE) -> Female | H377: =VLOOKUP($B377,Custumer_Master!$A:$J,7,FALSE) -> 01/08/1976 | I377: =VLOOKUP($B377,Custumer_Master!$A:$J,9,FALSE) -> Hyderabad | J377: =VLOOKUP($B377,Custumer_Master!$A:$J,10,FALSE) -> South | K377: =VLOOKUP(B377,Custumer_Master!A:D,4,FALSE) -> WB | L377: =PROPER(TRIM(VLOOKUP('Final Data'!C377,Product_Master!A:F,3,FALSE))) -> Electronics | M377: Mouse | N377: 13 | O377: =VLOOKUP(C377,Product_Master!A:F,5,FALSE) -> 525 | P377: 0.2 | Q377: =(N377*O377)-(N377*O377)*P377 -> 5460 | R377: 2 | S377: Card | T377: Ritika | U377: kavya.nair@company.com | V377: 9538129419 | W377: =VLOOKUP(C377,Product_Master!A:F,4,FALSE) -> TechHub | X377: =VLOOKUP(C377,Product_Master!A:F,6,FALSE) -> 24 | Y377: =VLOOKUP(B377,Custumer_Master!A:D,3,FALSE) -> Silver | Z377: =EDATE(E377,X377) -> 46804 | AA377: =VLOOKUP(B377,Custumer_Master!A:K,11,) -> August | AB377: Blacklisted | AC377: =PROPER(LEFT(TRIM(F377), 3)) & RIGHT(TRIM(B377), 3) & PROPER(LEFT(TRIM(I377), 2)) -> Kav008Hy | AD377: =DATEDIF(H377, TODAY(), "Y") -> 49 | AE377: =IFERROR(IF(OR(E377="", D377="", LOWER(TRIM(E377))="pending", LOWER(TRIM(D377))="pending"), "Pending", E377 - D377), "Pending") -> 8 | AF377: =IFERROR(IF(OR(E377="", D377="","Pending","Pending"), "Pending", IF((E377 - D377) <= 5, "On Time", "Delayed")), "Pending") -> Delayed | AG377: =IF(AF377="Pending","Pending","Completed") -> Completed
A378: ORD10377 | B378: C009 | C378: P104 | D378: 45696 | E378: 19/02/2025 | F378: =VLOOKUP(B378,Custumer_Master!A:D,2,FALSE) -> Mohit Verma | G378: =VLOOKUP($B378,Custumer_Master!$A:$J,6,FALSE) -> Male | H378: =VLOOKUP($B378,Custumer_Master!$A:$J,7,FALSE) -> 13/04/1976 | I378: =VLOOKUP($B378,Custumer_Master!$A:$J,9,FALSE) -> Delhi | J378: =VLOOKUP($B378,Custumer_Master!$A:$J,10,FALSE) -> North | K378: =VLOOKUP(B378,Custumer_Master!A:D,4,FALSE) -> KA | L378: =PROPER(TRIM(VLOOKUP('Final Data'!C378,Product_Master!A:F,3,FALSE))) -> Electronics | M378: Monitor | N378: 20 | O378: =VLOOKUP(C378,Product_Master!A:F,5,FALSE) -> 9000 | P378: 0 | Q378: =(N378*O378)-(N378*O378)*P378 -> 180000 | R378: 2 | S378: Card | T378: Neha | U378: mohit.verma@company.com | V378: 9382815686 | W378: =VLOOKUP(C378,Product_Master!A:F,4,FALSE) -> Global Trade | X378: =VLOOKUP(C378,Product_Master!A:F,6,FALSE) -> 24 | Y378: =VLOOKUP(B378,Custumer_Master!A:D,3,FALSE) -> Platinum | Z378: =EDATE(E378,X378) -> 46437 | AA378: =VLOOKUP(B378,Custumer_Master!A:K,11,) -> April | AB378: Blacklisted | AC378: =PROPER(LEFT(TRIM(F378), 3)) & RIGHT(TRIM(B378), 3) & PROPER(LEFT(TRIM(I378), 2)) -> Moh009De | AD378: =DATEDIF(H378, TODAY(), "Y") -> 50 | AE378: =IFERROR(IF(OR(E378="", D378="", LOWER(TRIM(E378))="pending", LOWER(TRIM(D378))="pending"), "Pending", E378 - D378), "Pending") -> 11 | AF378: =IFERROR(IF(OR(E378="", D378="","Pending","Pending"), "Pending", IF((E378 - D378) <= 5, "On Time", "Delayed")), "Pending") -> Delayed | AG378: =IF(AF378="Pending","Pending","Completed") -> Completed
A379: ORD10378 | B379: C007 | C379: P103 | D379: 46019 | E379: 06/01/2026 | F379: =VLOOKUP(B379,Custumer_Master!A:D,2,FALSE) -> Arjun Rao | G379: =VLOOKUP($B379,Custumer_Master!$A:$J,6,FALSE) -> Male | H379: =VLOOKUP($B379,Custumer_Master!$A:$J,7,FALSE) -> 07/02/1988 | I379: =VLOOKUP($B379,Custumer_Master!$A:$J,9,FALSE) -> Hyderabad | J379: =VLOOKUP($B379,Custumer_Master!$A:$J,10,FALSE) -> South | K379: =VLOOKUP(B379,Custumer_Master!A:D,4,FALSE) -> RJ | L379: =PROPER(TRIM(VLOOKUP('Final Data'!C379,Product_Master!A:F,3,FALSE))) -> Electronics | M379: Keyboard | N379: 9 | O379: =VLOOKUP(C379,Product_Master!A:F,5,FALSE) -> 900 | P379: 0.15 | Q379: =(N379*O379)-(N379*O379)*P379 -> 6885 | R379: 1 | S379: Upi | T379: Ritika | U379: arjun.rao@company.com | V379: 9450746157 | W379: =VLOOKUP(C379,Product_Master!A:F,4,FALSE) -> TechHub | X379: =VLOOKUP(C379,Product_Master!A:F,6,FALSE) -> 6 | Y379: =VLOOKUP(B379,Custumer_Master!A:D,3,FALSE) -> Silver | Z379: =EDATE(E379,X379) -> 46209 | AA379: =VLOOKUP(B379,Custumer_Master!A:K,11,) -> February | AB379: Blacklisted | AC379: =PROPER(LEFT(TRIM(F379), 3)) & RIGHT(TRIM(B379), 3) & PROPER(LEFT(TRIM(I379), 2)) -> Arj007Hy | AD379: =DATEDIF(H379, TODAY(), "Y") -> 38 | AE379: =IFERROR(IF(OR(E379="", D379="", LOWER(TRIM(E379))="pending", LOWER(TRIM(D379))="pending"), "Pending", E379 - D379), "Pending") -> 9 | AF379: =IFERROR(IF(OR(E379="", D379="","Pending","Pending"), "Pending", IF((E379 - D379) <= 5, "On Time", "Delayed")), "Pending") -> Delayed | AG379: =IF(AF379="Pending","Pending","Completed") -> Completed
A380: ORD10379 | B380: C007 | C380: P302 | D380: 45931 | E380: 03/10/2025 | F380: =VLOOKUP(B380,Custumer_Master!A:D,2,FALSE) -> Arjun Rao | G380: =VLOOKUP($B380,Custumer_Master!$A:$J,6,FALSE) -> Male | H380: =VLOOKUP($B380,Custumer_Master!$A:$J,7,FALSE) -> 07/02/1988 | I380: =VLOOKUP($B380,Custumer_Master!$A:$J,9,FALSE) -> Hyderabad | J380: =VLOOKUP($B380,Custumer_Master!$A:$J,10,FALSE) -> South | K380: =VLOOKUP(B380,Custumer_Master!A:D,4,FALSE) -> RJ | L380: =PROPER(TRIM(VLOOKUP('Final Data'!C380,Product_Master!A:F,3,FALSE))) -> Stationery | M380: Pen | N380: 3 | O380: =VLOOKUP(C380,Product_Master!A:F,5,FALSE) -> 15 | P380: 0.15 | Q380: =(N380*O380)-(N380*O380)*P380 -> 38.25 | R380: 3 | S380: Cash | T380: Neha | U380: arjun.rao@company.com | V380: 9349012570 | W380: =VLOOKUP(C380,Product_Master!A:F,4,FALSE) -> Prime Supplies | X380: =VLOOKUP(C380,Product_Master!A:F,6,FALSE) -> 12 | Y380: =VLOOKUP(B380,Custumer_Master!A:D,3,FALSE) -> Silver | Z380: =EDATE(E380,X380) -> 46298 | AA380: =VLOOKUP(B380,Custumer_Master!A:K,11,) -> February | AB380: Silver | AC380: =PROPER(LEFT(TRIM(F380), 3)) & RIGHT(TRIM(B380), 3) & PROPER(LEFT(TRIM(I380), 2)) -> Arj007Hy | AD380: =DATEDIF(H380, TODAY(), "Y") -> 38 | AE380: =IFERROR(IF(OR(E380="", D380="", LOWER(TRIM(E380))="pending", LOWER(TRIM(D380))="pending"), "Pending", E380 - D380), "Pending") -> 2 | AF380: =IFERROR(IF(OR(E380="", D380="","Pending","Pending"), "Pending", IF((E380 - D380) <= 5, "On Time", "Delayed")), "Pending") -> On Time | AG380: =IF(AF380="Pending","Pending","Completed") -> Completed
A381: ORD10380 | B381: C006 | C381: P101 | D381: 46009 | E381: 19/12/2025 | F381: =VLOOKUP(B381,Custumer_Master!A:D,2,FALSE) -> Sneha Joshi | G381: =VLOOKUP($B381,Custumer_Master!$A:$J,6,FALSE) -> Female | H381: =VLOOKUP($B381,Custumer_Master!$A:$J,7,FALSE) -> 04/04/1981 | I381: =VLOOKUP($B381,Custumer_Master!$A:$J,9,FALSE) -> Pune | J381: =VLOOKUP($B381,Custumer_Master!$A:$J,10,FALSE) -> West | K381: =VLOOKUP(B381,Custumer_Master!A:D,4,FALSE) -> WB | L381: =PROPER(TRIM(VLOOKUP('Final Data'!C381,Product_Master!A:F,3,FALSE))) -> Electronics | M381: Laptop | N381: 8 | O381: =VLOOKUP(C381,Product_Master!A:F,5,FALSE) -> 41250 | P381: 0.2 | Q381: =(N381*O381)-(N381*O381)*P381 -> 264000 | R381: 5 | S381: Card | T381: Karan | U381: sneha.joshi@company.com | V381: 9442163790 | W381: =VLOOKUP(C381,Product_Master!A:F,4,FALSE) -> TechHub | X381: =VLOOKUP(C381,Product_Master!A:F,6,FALSE) -> 12 | Y381: =VLOOKUP(B381,Custumer_Master!A:D,3,FALSE) -> Gold | Z381: =EDATE(E381,X381) -> 46375 | AA381: =VLOOKUP(B381,Custumer_Master!A:K,11,) -> April | AB381: Gold | AC381: =PROPER(LEFT(TRIM(F381), 3)) & RIGHT(TRIM(B381), 3) & PROPER(LEFT(TRIM(I381), 2)) -> Sne006Pu | AD381: =DATEDIF(H381, TODAY(), "Y") -> 45 | AE381: =IFERROR(IF(OR(E381="", D381="", LOWER(TRIM(E381))="pending", LOWER(TRIM(D381))="pending"), "Pending", E381 - D381), "Pending") -> 1 | AF381: =IFERROR(IF(OR(E381="", D381="","Pending","Pending"), "Pending", IF((E381 - D381) <= 5, "On Time", "Delayed")), "Pending") -> On Time | AG381: =IF(AF381="Pending","Pending","Completed") -> Completed
A382: ORD10381 | B382: C006 | C382: P301 | D382: 45929 | E382: 07/10/2025 | F382: =VLOOKUP(B382,Custumer_Master!A:D,2,FALSE) -> Sneha Joshi | G382: =VLOOKUP($B382,Custumer_Master!$A:$J,6,FALSE) -> Female | H382: =VLOOKUP($B382,Custumer_Master!$A:$J,7,FALSE) -> 04/04/1981 | I382: =VLOOKUP($B382,Custumer_Master!$A:$J,9,FALSE) -> Pune | J382: =VLOOKUP($B382,Custumer_Master!$A:$J,10,FALSE) -> West | K382: =VLOOKUP(B382,Custumer_Master!A:D,4,FALSE) -> WB | L382: =PROPER(TRIM(VLOOKUP('Final Data'!C382,Product_Master!A:F,3,FALSE))) -> Stationery | M382: Notebook | N382: 17 | O382: =VLOOKUP(C382,Product_Master!A:F,5,FALSE) -> 45 | P382: 0.2 | Q382: =(N382*O382)-(N382*O382)*P382 -> 612 | R382: 1 | S382: Upi | T382: Ritika | U382: sneha.joshi@company.com | V382: 9953329223 | W382: =VLOOKUP(C382,Product_Master!A:F,4,FALSE) -> ABC Corp | X382: =VLOOKUP(C382,Product_Master!A:F,6,FALSE) -> 12 | Y382: =VLOOKUP(B382,Custumer_Master!A:D,3,FALSE) -> Gold | Z382: =EDATE(E382,X382) -> 46302 | AA382: =VLOOKUP(B382,Custumer_Master!A:K,11,) -> April | AB382: Blacklisted | AC382: =PROPER(LEFT(TRIM(F382), 3)) & RIGHT(TRIM(B382), 3) & PROPER(LEFT(TRIM(I382), 2)) -> Sne006Pu | AD382: =DATEDIF(H382, TODAY(), "Y") -> 45 | AE382: =IFERROR(IF(OR(E382="", D382="", LOWER(TRIM(E382))="pending", LOWER(TRIM(D382))="pending"), "Pending", E382 - D382), "Pending") -> 8 | AF382: =IFERROR(IF(OR(E382="", D382="","Pending","Pending"), "Pending", IF((E382 - D382) <= 5, "On Time", "Delayed")), "Pending") -> Delayed | AG382: =IF(AF382="Pending","Pending","Completed") -> Completed
A383: ORD10382 | B383: C003 | C383: P302 | D383: 45791 | E383: 22/05/2025 | F383: =VLOOKUP(B383,Custumer_Master!A:D,2,FALSE) -> Rohit Singh | G383: =VLOOKUP($B383,Custumer_Master!$A:$J,6,FALSE) -> Male | H383: =VLOOKUP($B383,Custumer_Master!$A:$J,7,FALSE) -> 10/05/1982 | I383: =VLOOKUP($B383,Custumer_Master!$A:$J,9,FALSE) -> Delhi | J383: =VLOOKUP($B383,Custumer_Master!$A:$J,10,FALSE) -> North | K383: =VLOOKUP(B383,Custumer_Master!A:D,4,FALSE) -> DL | L383: =PROPER(TRIM(VLOOKUP('Final Data'!C383,Product_Master!A:F,3,FALSE))) -> Stationery | M383: Pen | N383: 4 | O383: =VLOOKUP(C383,Product_Master!A:F,5,FALSE) -> 15 | P383: 0.15 | Q383: =(N383*O383)-(N383*O383)*P383 -> 51 | R383: 3 | S383: Netbanking | T383: Aisha | U383: rohit.singh@company.com | V383: 9202321359 | W383: =VLOOKUP(C383,Product_Master!A:F,4,FALSE) -> Prime Supplies | X383: =VLOOKUP(C383,Product_Master!A:F,6,FALSE) -> 12 | Y383: =VLOOKUP(B383,Custumer_Master!A:D,3,FALSE) -> Gold | Z383: =EDATE(E383,X383) -> 46164 | AA383: =VLOOKUP(B383,Custumer_Master!A:K,11,) -> May | AB383: Silver | AC383: =PROPER(LEFT(TRIM(F383), 3)) & RIGHT(TRIM(B383), 3) & PROPER(LEFT(TRIM(I383), 2)) -> Roh003De | AD383: =DATEDIF(H383, TODAY(), "Y") -> 44 | AE383: =IFERROR(IF(OR(E383="", D383="", LOWER(TRIM(E383))="pending", LOWER(TRIM(D383))="pending"), "Pending", E383 - D383), "Pending") -> 8 | AF383: =IFERROR(IF(OR(E383="", D383="","Pending","Pending"), "Pending", IF((E383 - D383) <= 5, "On Time", "Delayed")), "Pending") -> Delayed | AG383: =IF(AF383="Pending","Pending","Completed") -> Completed
... A399: ORD10398 | B399: C007 | C399: P104 | D399: 45688 | E399: 04/02/2025 | F399: =VLOOKUP(B399,Custumer_Master!A:D,2,FALSE) -> Arjun Rao | G399: =VLOOKUP($B399,Custumer_Master!$A:$J,6,FALSE) -> Male | H399: =VLOOKUP($B399,Custumer_Master!$A:$J,7,FALSE) -> 07/02/1988 | I399: =VLOOKUP($B399,Custumer_Master!$A:$J,9,FALSE) -> Hyderabad | J399: =VLOOKUP($B399,Custumer_Master!$A:$J,10,FALSE) -> South | K399: =VLOOKUP(B399,Custumer_Master!A:D,4,FALSE) -> RJ | L399: =PROPER(TRIM(VLOOKUP('Final Data'!C399,Product_Master!A:F,3,FALSE))) -> Electronics | M399: Monitor | N399: 19 | O399: =VLOOKUP(C399,Product_Master!A:F,5,FALSE) -> 9000 | P399: 0 | Q399: =(N399*O399)-(N399*O399)*P399 -> 171000 | R399: 4 | S399: Upi | T399: Aisha | U399: arjun.rao@company.com | V399: 9136906750 | W399: =VLOOKUP(C399,Product_Master!A:F,4,FALSE) -> Global Trade | X399: =VLOOKUP(C399,Product_Master!A:F,6,FALSE) -> 24 | Y399: =VLOOKUP(B399,Custumer_Master!A:D,3,FALSE) -> Silver | Z399: =EDATE(E399,X399) -> 46422 | AA399: =VLOOKUP(B399,Custumer_Master!A:K,11,) -> February | AB399: Platinum | AC399: =PROPER(LEFT(TRIM(F399), 3)) & RIGHT(TRIM(B399), 3) & PROPER(LEFT(TRIM(I399), 2)) -> Arj007Hy | AD399: =DATEDIF(H399, TODAY(), "Y") -> 38 | AE399: =IFERROR(IF(OR(E399="", D399="", LOWER(TRIM(E399))="pending", LOWER(TRIM(D399))="pending"), "Pending", E399 - D399), "Pending") -> 4 | AF399: =IFERROR(IF(OR(E399="", D399="","Pending","Pending"), "Pending", IF((E399 - D399) <= 5, "On Time", "Delayed")), "Pending") -> On Time | AG399: =IF(AF399="Pending","Pending","Completed") -> Completed
A400: ORD10399 | B400: C001 | C400: P102 | E400: 03/11/2025 | F400: =VLOOKUP(B400,Custumer_Master!A:D,2,FALSE) -> Amit Sharma | G400: =VLOOKUP($B400,Custumer_Master!$A:$J,6,FALSE) -> Male | H400: =VLOOKUP($B400,Custumer_Master!$A:$J,7,FALSE) -> 09/08/1991 | I400: =VLOOKUP($B400,Custumer_Master!$A:$J,9,FALSE) -> Pune | J400: =VLOOKUP($B400,Custumer_Master!$A:$J,10,FALSE) -> West | K400: =VLOOKUP(B400,Custumer_Master!A:D,4,FALSE) -> RJ | L400: =PROPER(TRIM(VLOOKUP('Final Data'!C400,Product_Master!A:F,3,FALSE))) -> Electronics | M400: Mouse | N400: 12 | O400: =VLOOKUP(C400,Product_Master!A:F,5,FALSE) -> 525 | P400: 0.15 | Q400: =(N400*O400)-(N400*O400)*P400 -> 5355 | R400: 3 | S400: Card | T400: Ritika | U400: amit.sharma@company.com | V400: 9485286324 | W400: =VLOOKUP(C400,Product_Master!A:F,4,FALSE) -> TechHub | X400: =VLOOKUP(C400,Product_Master!A:F,6,FALSE) -> 24 | Y400: =VLOOKUP(B400,Custumer_Master!A:D,3,FALSE) -> Silver | Z400: =EDATE(E400,X400) -> 46694 | AA400: =VLOOKUP(B400,Custumer_Master!A:K,11,) -> August | AB400: Silver | AC400: =PROPER(LEFT(TRIM(F400), 3)) & RIGHT(TRIM(B400), 3) & PROPER(LEFT(TRIM(I400), 2)) -> Ami001Pu | AD400: =DATEDIF(H400, TODAY(), "Y") -> 34 | AE400: =IFERROR(IF(OR(E400="", D400="", LOWER(TRIM(E400))="pending", LOWER(TRIM(D400))="pending"), "Pending", E400 - D400), "Pending") -> Pending | AF400: =IFERROR(IF(OR(E400="", D400="","Pending","Pending"), "Pending", IF((E400 - D400) <= 5, "On Time", "Delayed")), "Pending") -> Pending | AG400: =IF(AF400="Pending","Pending","Completed") -> Pending
A401: ORD10400 | B401: C008 | C401: P103 | D401: 45790 | E401: 21/05/2025 | F401: =VLOOKUP(B401,Custumer_Master!A:D,2,FALSE) -> Kavya Nair | G401: =VLOOKUP($B401,Custumer_Master!$A:$J,6,FALSE) -> Female | H401: =VLOOKUP($B401,Custumer_Master!$A:$J,7,FALSE) -> 01/08/1976 | I401: =VLOOKUP($B401,Custumer_Master!$A:$J,9,FALSE) -> Hyderabad | J401: =VLOOKUP($B401,Custumer_Master!$A:$J,10,FALSE) -> South | K401: =VLOOKUP(B401,Custumer_Master!A:D,4,FALSE) -> WB | L401: =PROPER(TRIM(VLOOKUP('Final Data'!C401,Product_Master!A:F,3,FALSE))) -> Electronics | M401: Keyboard | N401: 16 | O401: =VLOOKUP(C401,Product_Master!A:F,5,FALSE) -> 900 | P401: 0.2 | Q401: =(N401*O401)-(N401*O401)*P401 -> 11520 | R401: 1 | S401: Cash | T401: Rahul | U401: kavya.nair@company.com | V401: 9414633966 | W401: =VLOOKUP(C401,Product_Master!A:F,4,FALSE) -> TechHub | X401: =VLOOKUP(C401,Product_Master!A:F,6,FALSE) -> 6 | Y401: =VLOOKUP(B401,Custumer_Master!A:D,3,FALSE) -> Silver | Z401: =EDATE(E401,X401) -> 45982 | AA401: =VLOOKUP(B401,Custumer_Master!A:K,11,) -> August | AB401: Blacklisted | AC401: =PROPER(LEFT(TRIM(F401), 3)) & RIGHT(TRIM(B401), 3) & PROPER(LEFT(TRIM(I401), 2)) -> Kav008Hy | AD401: =DATEDIF(H401, TODAY(), "Y") -> 49 | AE401: =IFERROR(IF(OR(E401="", D401="", LOWER(TRIM(E401))="pending", LOWER(TRIM(D401))="pending"), "Pending", E401 - D401), "Pending") -> 8 | AF401: =IFERROR(IF(OR(E401="", D401="","Pending","Pending"), "Pending", IF((E401 - D401) <= 5, "On Time", "Delayed")), "Pending") -> Delayed | AG401: =IF(AF401="Pending","Pending","Completed") -> Completed
A402: ORD10401 | B402: C009 | C402: P203 | D402: 46018 | E402: 04/01/2026 | F402: =VLOOKUP(B402,Custumer_Master!A:D,2,FALSE) -> Mohit Verma | G402: =VLOOKUP($B402,Custumer_Master!$A:$J,6,FALSE) -> Male | H402: =VLOOKUP($B402,Custumer_Master!$A:$J,7,FALSE) -> 13/04/1976 | I402: =VLOOKUP($B402,Custumer_Master!$A:$J,9,FALSE) -> Delhi | J402: =VLOOKUP($B402,Custumer_Master!$A:$J,10,FALSE) -> North | K402: =VLOOKUP(B402,Custumer_Master!A:D,4,FALSE) -> KA | L402: =PROPER(TRIM(VLOOKUP('Final Data'!C402,Product_Master!A:F,3,FALSE))) -> Home Appliances | M402: Microwave | N402: 10 | O402: =VLOOKUP(C402,Product_Master!A:F,5,FALSE) -> 6375 | P402: 0.05 | Q402: =(N402*O402)-(N402*O402)*P402 -> 60562.5 | R402: 5 | S402: Netbanking | T402: Ritika | U402: mohit.verma@company.com | V402: 9833735234 | W402: =VLOOKUP(C402,Product_Master!A:F,4,FALSE) -> TechHub | X402: =VLOOKUP(C402,Product_Master!A:F,6,FALSE) -> 24 | Y402: =VLOOKUP(B402,Custumer_Master!A:D,3,FALSE) -> Platinum | Z402: =EDATE(E402,X402) -> 46756 | AA402: =VLOOKUP(B402,Custumer_Master!A:K,11,) -> April | AB402: Gold | AC402: =PROPER(LEFT(TRIM(F402), 3)) & RIGHT(TRIM(B402), 3) & PROPER(LEFT(TRIM(I402), 2)) -> Moh009De | AD402: =DATEDIF(H402, TODAY(), "Y") -> 50 | AE402: =IFERROR(IF(OR(E402="", D402="", LOWER(TRIM(E402))="pending", LOWER(TRIM(D402))="pending"), "Pending", E402 - D402), "Pending") -> 8 | AF402: =IFERROR(IF(OR(E402="", D402="","Pending","Pending"), "Pending", IF((E402 - D402) <= 5, "On Time", "Delayed")), "Pending") -> Delayed | AG402: =IF(AF402="Pending","Pending","Completed") -> Completed
A403: ORD10402 | B403: C008 | C403: P302 | D403: 45699 | E403: 21/02/2025 | F403: =VLOOKUP(B403,Custumer_Master!A:D,2,FALSE) -> Kavya Nair | G403: =VLOOKUP($B403,Custumer_Master!$A:$J,6,FALSE) -> Female | H403: =VLOOKUP($B403,Custumer_Master!$A:$J,7,FALSE) -> 01/08/1976 | I403: =VLOOKUP($B403,Custumer_Master!$A:$J,9,FALSE) -> Hyderabad | J403: =VLOOKUP($B403,Custumer_Master!$A:$J,10,FALSE) -> South | K403: =VLOOKUP(B403,Custumer_Master!A:D,4,FALSE) -> WB | L403: =PROPER(TRIM(VLOOKUP('Final Data'!C403,Product_Master!A:F,3,FALSE))) -> Stationery | M403: Pen | N403: 18 | O403: =VLOOKUP(C403,Product_Master!A:F,5,FALSE) -> 15 | P403: 0.2 | Q403: =(N403*O403)-(N403*O403)*P403 -> 216 | R403: 1 | S403: Upi | T403: Ritika | U403: kavya.nair@company.com | V403: 9523689108 | W403: =VLOOKUP(C403,Product_Master!A:F,4,FALSE) -> Prime Supplies | X403: =VLOOKUP(C403,Product_Master!A:F,6,FALSE) -> 12 | Y403: =VLOOKUP(B403,Custumer_Master!A:D,3,FALSE) -> Silver | Z403: =EDATE(E403,X403) -> 46074 | AA403: =VLOOKUP(B403,Custumer_Master!A:K,11,) -> August | AB403: Blacklisted | AC403: =PROPER(LEFT(TRIM(F403), 3)) & RIGHT(TRIM(B403), 3) & PROPER(LEFT(TRIM(I403), 2)) -> Kav008Hy | AD403: =DATEDIF(H403, TODAY(), "Y") -> 49 | AE403: =IFERROR(IF(OR(E403="", D403="", LOWER(TRIM(E403))="pending", LOWER(TRIM(D403))="pending"), "Pending", E403 - D403), "Pending") -> 10 | AF403: =IFERROR(IF(OR(E403="", D403="","Pending","Pending"), "Pending", IF((E403 - D403) <= 5, "On Time", "Delayed")), "Pending") -> Delayed | AG403: =IF(AF403="Pending","Pending","Completed") -> Completed
A404: ORD10403 | B404: C009 | C404: P203 | D404: 46094 | E404: 19/03/2026 | F404: =VLOOKUP(B404,Custumer_Master!A:D,2,FALSE) -> Mohit Verma | G404: =VLOOKUP($B404,Custumer_Master!$A:$J,6,FALSE) -> Male | H404: =VLOOKUP($B404,Custumer_Master!$A:$J,7,FALSE) -> 13/04/1976 | I404: =VLOOKUP($B404,Custumer_Master!$A:$J,9,FALSE) -> Delhi | J404: =VLOOKUP($B404,Custumer_Master!$A:$J,10,FALSE) -> North | K404: =VLOOKUP(B404,Custumer_Master!A:D,4,FALSE) -> KA | L404: =PROPER(TRIM(VLOOKUP('Final Data'!C404,Product_Master!A:F,3,FALSE))) -> Home Appliances | M404: Microwave | N404: 9 | O404: =VLOOKUP(C404,Product_Master!A:F,5,FALSE) -> 6375 | P404: 0 | Q404: =(N404*O404)-(N404*O404)*P404 -> 57375 | R404: 2 | S404: Card | T404: Ritika | U404: mohit.verma@company.com | V404: 9812909831 | W404: =VLOOKUP(C404,Product_Master!A:F,4,FALSE) -> TechHub | X404: =VLOOKUP(C404,Product_Master!A:F,6,FALSE) -> 24 | Y404: =VLOOKUP(B404,Custumer_Master!A:D,3,FALSE) -> Platinum | Z404: =EDATE(E404,X404) -> 46831 | AA404: =VLOOKUP(B404,Custumer_Master!A:K,11,) -> April | AB404: Blacklisted | AC404: =PROPER(LEFT(TRIM(F404), 3)) & RIGHT(TRIM(B404), 3) & PROPER(LEFT(TRIM(I404), 2)) -> Moh009De | AD404: =DATEDIF(H404, TODAY(), "Y") -> 50 | AE404: =IFERROR(IF(OR(E404="", D404="", LOWER(TRIM(E404))="pending", LOWER(TRIM(D404))="pending"), "Pending", E404 - D404), "Pending") -> 6 | AF404: =IFERROR(IF(OR(E404="", D404="","Pending","Pending"), "Pending", IF((E404 - D404) <= 5, "On Time", "Delayed")), "Pending") -> Delayed | AG404: =IF(AF404="Pending","Pending","Completed") -> Completed
A405: ORD10404 | B405: C008 | C405: P203 | D405: 45931 | E405: 12/10/2025 | F405: =VLOOKUP(B405,Custumer_Master!A:D,2,FALSE) -> Kavya Nair | G405: =VLOOKUP($B405,Custumer_Master!$A:$J,6,FALSE) -> Female | H405: =VLOOKUP($B405,Custumer_Master!$A:$J,7,FALSE) -> 01/08/1976 | I405: =VLOOKUP($B405,Custumer_Master!$A:$J,9,FALSE) -> Hyderabad | J405: =VLOOKUP($B405,Custumer_Master!$A:$J,10,FALSE) -> South | K405: =VLOOKUP(B405,Custumer_Master!A:D,4,FALSE) -> WB | L405: =PROPER(TRIM(VLOOKUP('Final Data'!C405,Product_Master!A:F,3,FALSE))) -> Home Appliances | M405: Microwave | N405: 8 | O405: =VLOOKUP(C405,Product_Master!A:F,5,FALSE) -> 6375 | P405: 0.1 | Q405: =(N405*O405)-(N405*O405)*P405 -> 45900 | R405: 4 | S405: Cash | T405: Neha | U405: kavya.nair@company.com | V405: 9106290987 | W405: =VLOOKUP(C405,Product_Master!A:F,4,FALSE) -> TechHub | X405: =VLOOKUP(C405,Product_Master!A:F,6,FALSE) -> 24 | Y405: =VLOOKUP(B405,Custumer_Master!A:D,3,FALSE) -> Silver | Z405: =EDATE(E405,X405) -> 46672 | AA405: =VLOOKUP(B405,Custumer_Master!A:K,11,) -> August | AB405: Silver | AC405: =PROPER(LEFT(TRIM(F405), 3)) & RIGHT(TRIM(B405), 3) & PROPER(LEFT(TRIM(I405), 2)) -> Kav008Hy | AD405: =DATEDIF(H405, TODAY(), "Y") -> 49 | AE405: =IFERROR(IF(OR(E405="", D405="", LOWER(TRIM(E405))="pending", LOWER(TRIM(D405))="pending"), "Pending", E405 - D405), "Pending") -> 11 | AF405: =IFERROR(IF(OR(E405="", D405="","Pending","Pending"), "Pending", IF((E405 - D405) <= 5, "On Time", "Delayed")), "Pending") -> Delayed | AG405: =IF(AF405="Pending","Pending","Completed") -> Completed
A406: ORD10405 | B406: C010 | C406: P302 | D406: 46048 | E406: 01/02/2026 | F406: =VLOOKUP(B406,Custumer_Master!A:D,2,FALSE) -> Pooja Shah | G406: =VLOOKUP($B406,Custumer_Master!$A:$J,6,FALSE) -> Female | H406: =VLOOKUP($B406,Custumer_Master!$A:$J,7,FALSE) -> 16/09/1994 | I406: =VLOOKUP($B406,Custumer_Master!$A:$J,9,FALSE) -> Bengaluru | J406: =VLOOKUP($B406,Custumer_Master!$A:$J,10,FALSE) -> South | K406: =VLOOKUP(B406,Custumer_Master!A:D,4,FALSE) -> WB | L406: =PROPER(TRIM(VLOOKUP('Final Data'!C406,Product_Master!A:F,3,FALSE))) -> Stationery | M406: Pen | N406: 3 | O406: =VLOOKUP(C406,Product_Master!A:F,5,FALSE) -> 15 | P406: 0.1 | Q406: =(N406*O406)-(N406*O406)*P406 -> 40.5 | R406: 3 | S406: Card | T406: Karan | U406: pooja.shah@company.com | V406: 9767727724 | W406: =VLOOKUP(C406,Product_Master!A:F,4,FALSE) -> Prime Supplies | X406: =VLOOKUP(C406,Product_Master!A:F,6,FALSE) -> 12 | Y406: =VLOOKUP(B406,Custumer_Master!A:D,3,FALSE) -> Silver | Z406: =EDATE(E406,X406) -> 46419 | AA406: =VLOOKUP(B406,Custumer_Master!A:K,11,) -> September | AB406: Silver | AC406: =PROPER(LEFT(TRIM(F406), 3)) & RIGHT(TRIM(B406), 3) & PROPER(LEFT(TRIM(I406), 2)) -> Poo010Be | AD406: =DATEDIF(H406, TODAY(), "Y") -> 31 | AE406: =IFERROR(IF(OR(E406="", D406="", LOWER(TRIM(E406))="pending", LOWER(TRIM(D406))="pending"), "Pending", E406 - D406), "Pending") -> 6 | AF406: =IFERROR(IF(OR(E406="", D406="","Pending","Pending"), "Pending", IF((E406 - D406) <= 5, "On Time", "Delayed")), "Pending") -> Delayed | AG406: =IF(AF406="Pending","Pending","Completed") -> Completed
A407: ORD10406 | B407: C004 | C407: P203 | D407: 45840 | E407: 12/07/2025 | F407: =VLOOKUP(B407,Custumer_Master!A:D,2,FALSE) -> Anita Gupta | G407: =VLOOKUP($B407,Custumer_Master!$A:$J,6,FALSE) -> Female | H407: =VLOOKUP($B407,Custumer_Master!$A:$J,7,FALSE) -> 16/01/2002 | I407: =VLOOKUP($B407,Custumer_Master!$A:$J,9,FALSE) -> Pune | J407: =VLOOKUP($B407,Custumer_Master!$A:$J,10,FALSE) -> West | K407: =VLOOKUP(B407,Custumer_Master!A:D,4,FALSE) -> WB | L407: =PROPER(TRIM(VLOOKUP('Final Data'!C407,Product_Master!A:F,3,FALSE))) -> Home Appliances | M407: Microwave | N407: 18 | O407: =VLOOKUP(C407,Product_Master!A:F,5,FALSE) -> 6375 | P407: 0.1 | Q407: =(N407*O407)-(N407*O407)*P407 -> 103275 | R407: 4 | S407: Cash | T407: Rahul | U407: anita.gupta@company.com | V407: 9865401727 | W407: =VLOOKUP(C407,Product_Master!A:F,4,FALSE) -> TechHub | X407: =VLOOKUP(C407,Product_Master!A:F,6,FALSE) -> 24 | Y407: =VLOOKUP(B407,Custumer_Master!A:D,3,FALSE) -> Gold | Z407: =EDATE(E407,X407) -> 46580 | AA407: =VLOOKUP(B407,Custumer_Master!A:K,11,) -> January | AB407: Platinum | AC407: =PROPER(LEFT(TRIM(F407), 3)) & RIGHT(TRIM(B407), 3) & PROPER(LEFT(TRIM(I407), 2)) -> Ani004Pu | AD407: =DATEDIF(H407, TODAY(), "Y") -> 24 | AE407: =IFERROR(IF(OR(E407="", D407="", LOWER(TRIM(E407))="pending", LOWER(TRIM(D407))="pending"), "Pending", E407 - D407), "Pending") -> 10 | AF407: =IFERROR(IF(OR(E407="", D407="","Pending","Pending"), "Pending", IF((E407 - D407) <= 5, "On Time", "Delayed")), "Pending") -> Delayed | AG407: =IF(AF407="Pending","Pending","Completed") -> Completed
A408: ORD10407 | B408: C010 | C408: P303 | D408: 45935 | E408: 09/10/2025 | F408: =VLOOKUP(B408,Custumer_Master!A:D,2,FALSE) -> Pooja Shah | G408: =VLOOKUP($B408,Custumer_Master!$A:$J,6,FALSE) -> Female | H408: =VLOOKUP($B408,Custumer_Master!$A:$J,7,FALSE) -> 16/09/1994 | I408: =VLOOKUP($B408,Custumer_Master!$A:$J,9,FALSE) -> Bengaluru | J408: =VLOOKUP($B408,Custumer_Master!$A:$J,10,FALSE) -> South | K408: =VLOOKUP(B408,Custumer_Master!A:D,4,FALSE) -> WB | L408: =PROPER(TRIM(VLOOKUP('Final Data'!C408,Product_Master!A:F,3,FALSE))) -> Stationery | M408: Marker | N408: 5 | O408: =VLOOKUP(C408,Product_Master!A:F,5,FALSE) -> 33.75 | P408: 0.1 | Q408: =(N408*O408)-(N408*O408)*P408 -> 151.875 | R408: 3 | S408: Cash | T408: Neha | U408: pooja.shah@company.com | V408: 9603848571 | W408: =VLOOKUP(C408,Product_Master!A:F,4,FALSE) -> TechHub | X408: =VLOOKUP(C408,Product_Master!A:F,6,FALSE) -> 12 | Y408: =VLOOKUP(B408,Custumer_Master!A:D,3,FALSE) -> Silver | Z408: =EDATE(E408,X408) -> 46304 | AA408: =VLOOKUP(B408,Custumer_Master!A:K,11,) -> September | AB408: Silver | AC408: =PROPER(LEFT(TRIM(F408), 3)) & RIGHT(TRIM(B408), 3) & PROPER(LEFT(TRIM(I408), 2)) -> Poo010Be | AD408: =DATEDIF(H408, TODAY(), "Y") -> 31 | AE408: =IFERROR(IF(OR(E408="", D408="", LOWER(TRIM(E408))="pending", LOWER(TRIM(D408))="pending"), "Pending", E408 - D408), "Pending") -> 4 | AF408: =IFERROR(IF(OR(E408="", D408="","Pending","Pending"), "Pending", IF((E408 - D408) <= 5, "On Time", "Delayed")), "Pending") -> On Time | AG408: =IF(AF408="Pending","Pending","Completed") -> Completed
A409: ORD10408 | B409: C009 | C409: P303 | D409: 45807 | E409: 02/06/2025 | F409: =VLOOKUP(B409,Custumer_Master!A:D,2,FALSE) -> Mohit Verma | G409: =VLOOKUP($B409,Custumer_Master!$A:$J,6,FALSE) -> Male | H409: =VLOOKUP($B409,Custumer_Master!$A:$J,7,FALSE) -> 13/04/1976 | I409: =VLOOKUP($B409,Custumer_Master!$A:$J,9,FALSE) -> Delhi | J409: =VLOOKUP($B409,Custumer_Master!$A:$J,10,FALSE) -> North | K409: =VLOOKUP(B409,Custumer_Master!A:D,4,FALSE) -> KA | L409: =PROPER(TRIM(VLOOKUP('Final Data'!C409,Product_Master!A:F,3,FALSE))) -> Stationery | M409: Marker | N409: 2 | O409: =VLOOKUP(C409,Product_Master!A:F,5,FALSE) -> 33.75 | P409: 0.2 | Q409: =(N409*O409)-(N409*O409)*P409 -> 54 | R409: 5 | S409: Upi | T409: Aisha | U409: mohit.verma@company.com | V409: 9101231789 | W409: =VLOOKUP(C409,Product_Master!A:F,4,FALSE) -> TechHub | X409: =VLOOKUP(C409,Product_Master!A:F,6,FALSE) -> 12 | Y409: =VLOOKUP(B409,Custumer_Master!A:D,3,FALSE) -> Platinum | Z409: =EDATE(E409,X409) -> 46175 | AA409: =VLOOKUP(B409,Custumer_Master!A:K,11,) -> April | AB409: Silver | AC409: =PROPER(LEFT(TRIM(F409), 3)) & RIGHT(TRIM(B409), 3) & PROPER(LEFT(TRIM(I409), 2)) -> Moh009De | AD409: =DATEDIF(H409, TODAY(), "Y") -> 50 | AE409: =IFERROR(IF(OR(E409="", D409="", LOWER(TRIM(E409))="pending", LOWER(TRIM(D409))="pending"), "Pending", E409 - D409), "Pending") -> 3 | AF409: =IFERROR(IF(OR(E409="", D409="","Pending","Pending"), "Pending", IF((E409 - D409) <= 5, "On Time", "Delayed")), "Pending") -> On Time | AG409: =IF(AF409="Pending","Pending","Completed") -> Completed
A410: ORD10409 | B410: C002 | C410: P303 | D410: 45684 | E410: 06/02/2025 | F410: =VLOOKUP(B410,Custumer_Master!A:D,2,FALSE) -> Priya Patel | G410: =VLOOKUP($B410,Custumer_Master!$A:$J,6,FALSE) -> Female | H410: =VLOOKUP($B410,Custumer_Master!$A:$J,7,FALSE) -> 07/03/1995 | I410: =VLOOKUP($B410,Custumer_Master!$A:$J,9,FALSE) -> Mumbai | J410: =VLOOKUP($B410,Custumer_Master!$A:$J,10,FALSE) -> West | K410: =VLOOKUP(B410,Custumer_Master!A:D,4,FALSE) -> WB | L410: =PROPER(TRIM(VLOOKUP('Final Data'!C410,Product_Master!A:F,3,FALSE))) -> Stationery | M410: Marker | N410: 18 | O410: =VLOOKUP(C410,Product_Master!A:F,5,FALSE) -> 33.75 | P410: 0.1 | Q410: =(N410*O410)-(N410*O410)*P410 -> 546.75 | R410: 2 | S410: Netbanking | T410: Neha | U410: priya.patel@company.com | V410: 9485017802 | W410: =VLOOKUP(C410,Product_Master!A:F,4,FALSE) -> TechHub | X410: =VLOOKUP(C410,Product_Master!A:F,6,FALSE) -> 12 | Y410: =VLOOKUP(B410,Custumer_Master!A:D,3,FALSE) -> Platinum | Z410: =EDATE(E410,X410) -> 46059 | AA410: =VLOOKUP(B410,Custumer_Master!A:K,11,) -> March | AB410: Blacklisted | AC410: =PROPER(LEFT(TRIM(F410), 3)) & RIGHT(TRIM(B410), 3) & PROPER(LEFT(TRIM(I410), 2)) -> Pri002Mu | AD410: =DATEDIF(H410, TODAY(), "Y") -> 31 | AE410: =IFERROR(IF(OR(E410="", D410="", LOWER(TRIM(E410))="pending", LOWER(TRIM(D410))="pending"), "Pending", E410 - D410), "Pending") -> 10 | AF410: =IFERROR(IF(OR(E410="", D410="","Pending","Pending"), "Pending", IF((E410 - D410) <= 5, "On Time", "Delayed")), "Pending") -> Delayed | AG410: =IF(AF410="Pending","Pending","Completed") -> Completed
A411: ORD10410 | B411: C003 | C411: P103 | D411: 46015 | E411: 01/01/2026 | F411: =VLOOKUP(B411,Custumer_Master!A:D,2,FALSE) -> Rohit Singh | G411: =VLOOKUP($B411,Custumer_Master!$A:$J,6,FALSE) -> Male | H411: =VLOOKUP($B411,Custumer_Master!$A:$J,7,FALSE) -> 10/05/1982 | I411: =VLOOKUP($B411,Custumer_Master!$A:$J,9,FALSE) -> Delhi | J411: =VLOOKUP($B411,Custumer_Master!$A:$J,10,FALSE) -> North | K411: =VLOOKUP(B411,Custumer_Master!A:D,4,FALSE) -> DL | L411: =PROPER(TRIM(VLOOKUP('Final Data'!C411,Product_Master!A:F,3,FALSE))) -> Electronics | M411: Keyboard | N411: 13 | O411: =VLOOKUP(C411,Product_Master!A:F,5,FALSE) -> 900 | P411: 0.05 | Q411: =(N411*O411)-(N411*O411)*P411 -> 11115 | R411: 4 | S411: Card | T411: Neha | U411: rohit.singh@company.com | V411: 9815464650 | W411: =VLOOKUP(C411,Product_Master!A:F,4,FALSE) -> TechHub | X411: =VLOOKUP(C411,Product_Master!A:F,6,FALSE) -> 6 | Y411: =VLOOKUP(B411,Custumer_Master!A:D,3,FALSE) -> Gold | Z411: =EDATE(E411,X411) -> 46204 | AA411: =VLOOKUP(B411,Custumer_Master!A:K,11,) -> May | AB411: Silver | AC411: =PROPER(LEFT(TRIM(F411), 3)) & RIGHT(TRIM(B411), 3) & PROPER(LEFT(TRIM(I411), 2)) -> Roh003De | AD411: =DATEDIF(H411, TODAY(), "Y") -> 44 | AE411: =IFERROR(IF(OR(E411="", D411="", LOWER(TRIM(E411))="pending", LOWER(TRIM(D411))="pending"), "Pending", E411 - D411), "Pending") -> 8 | AF411: =IFERROR(IF(OR(E411="", D411="","Pending","Pending"), "Pending", IF((E411 - D411) <= 5, "On Time", "Delayed")), "Pending") -> Delayed | AG411: =IF(AF411="Pending","Pending","Completed") -> Completed
A412: ORD10411 | B412: C008 | C412: P302 | D412: 46153 | E412: 17/05/2026 | F412: =VLOOKUP(B412,Custumer_Master!A:D,2,FALSE) -> Kavya Nair | G412: =VLOOKUP($B412,Custumer_Master!$A:$J,6,FALSE) -> Female | H412: =VLOOKUP($B412,Custumer_Master!$A:$J,7,FALSE) -> 01/08/1976 | I412: =VLOOKUP($B412,Custumer_Master!$A:$J,9,FALSE) -> Hyderabad | J412: =VLOOKUP($B412,Custumer_Master!$A:$J,10,FALSE) -> South | K412: =VLOOKUP(B412,Custumer_Master!A:D,4,FALSE) -> WB | L412: =PROPER(TRIM(VLOOKUP('Final Data'!C412,Product_Master!A:F,3,FALSE))) -> Stationery | M412: Pen | N412: 14 | O412: =VLOOKUP(C412,Product_Master!A:F,5,FALSE) -> 15 | P412: 0.2 | Q412: =(N412*O412)-(N412*O412)*P412 -> 168 | R412: 5 | S412: Upi | T412: Rahul | U412: kavya.nair@company.com | V412: 9860715839 | W412: =VLOOKUP(C412,Product_Master!A:F,4,FALSE) -> Prime Supplies | X412: =VLOOKUP(C412,Product_Master!A:F,6,FALSE) -> 12 | Y412: =VLOOKUP(B412,Custumer_Master!A:D,3,FALSE) -> Silver | Z412: =EDATE(E412,X412) -> 46524 | AA412: =VLOOKUP(B412,Custumer_Master!A:K,11,) -> August | AB412: Silver | AC412: =PROPER(LEFT(TRIM(F412), 3)) & RIGHT(TRIM(B412), 3) & PROPER(LEFT(TRIM(I412), 2)) -> Kav008Hy | AD412: =DATEDIF(H412, TODAY(), "Y") -> 49 | AE412: =IFERROR(IF(OR(E412="", D412="", LOWER(TRIM(E412))="pending", LOWER(TRIM(D412))="pending"), "Pending", E412 - D412), "Pending") -> 6 | AF412: =IFERROR(IF(OR(E412="", D412="","Pending","Pending"), "Pending", IF((E412 - D412) <= 5, "On Time", "Delayed")), "Pending") -> Delayed | AG412: =IF(AF412="Pending","Pending","Completed") -> Completed
... A433: ORD10432 | B433: C006 | C433: P104 | D433: 46036 | E433: 24/01/2026 | F433: =VLOOKUP(B433,Custumer_Master!A:D,2,FALSE) -> Sneha Joshi | G433: =VLOOKUP($B433,Custumer_Master!$A:$J,6,FALSE) -> Female | H433: =VLOOKUP($B433,Custumer_Master!$A:$J,7,FALSE) -> 04/04/1981 | I433: =VLOOKUP($B433,Custumer_Master!$A:$J,9,FALSE) -> Pune | J433: =VLOOKUP($B433,Custumer_Master!$A:$J,10,FALSE) -> West | K433: =VLOOKUP(B433,Custumer_Master!A:D,4,FALSE) -> WB | L433: =PROPER(TRIM(VLOOKUP('Final Data'!C433,Product_Master!A:F,3,FALSE))) -> Electronics | M433: Monitor | N433: 7 | O433: =VLOOKUP(C433,Product_Master!A:F,5,FALSE) -> 9000 | P433: 0.05 | Q433: =(N433*O433)-(N433*O433)*P433 -> 59850 | R433: 4 | S433: Card | T433: Karan | U433: sneha.joshi@company.com | V433: 9937007439 | W433: =VLOOKUP(C433,Product_Master!A:F,4,FALSE) -> Global Trade | X433: =VLOOKUP(C433,Product_Master!A:F,6,FALSE) -> 24 | Y433: =VLOOKUP(B433,Custumer_Master!A:D,3,FALSE) -> Gold | Z433: =EDATE(E433,X433) -> 46776 | AA433: =VLOOKUP(B433,Custumer_Master!A:K,11,) -> April | AB433: Gold | AC433: =PROPER(LEFT(TRIM(F433), 3)) & RIGHT(TRIM(B433), 3) & PROPER(LEFT(TRIM(I433), 2)) -> Sne006Pu | AD433: =DATEDIF(H433, TODAY(), "Y") -> 45 | AE433: =IFERROR(IF(OR(E433="", D433="", LOWER(TRIM(E433))="pending", LOWER(TRIM(D433))="pending"), "Pending", E433 - D433), "Pending") -> 10 | AF433: =IFERROR(IF(OR(E433="", D433="","Pending","Pending"), "Pending", IF((E433 - D433) <= 5, "On Time", "Delayed")), "Pending") -> Delayed | AG433: =IF(AF433="Pending","Pending","Completed") -> Completed
A434: ORD10433 | B434: C001 | C434: P302 | D434: 46152 | F434: =VLOOKUP(B434,Custumer_Master!A:D,2,FALSE) -> Amit Sharma | G434: =VLOOKUP($B434,Custumer_Master!$A:$J,6,FALSE) -> Male | H434: =VLOOKUP($B434,Custumer_Master!$A:$J,7,FALSE) -> 09/08/1991 | I434: =VLOOKUP($B434,Custumer_Master!$A:$J,9,FALSE) -> Pune | J434: =VLOOKUP($B434,Custumer_Master!$A:$J,10,FALSE) -> West | K434: =VLOOKUP(B434,Custumer_Master!A:D,4,FALSE) -> RJ | L434: =PROPER(TRIM(VLOOKUP('Final Data'!C434,Product_Master!A:F,3,FALSE))) -> Stationery | M434: Pen | N434: 8 | O434: =VLOOKUP(C434,Product_Master!A:F,5,FALSE) -> 15 | P434: 0 | Q434: =(N434*O434)-(N434*O434)*P434 -> 120 | R434: 4 | S434: Card | T434: Aisha | U434: amit.sharma@company.com | V434: 9657513435 | W434: =VLOOKUP(C434,Product_Master!A:F,4,FALSE) -> Prime Supplies | X434: =VLOOKUP(C434,Product_Master!A:F,6,FALSE) -> 12 | Y434: =VLOOKUP(B434,Custumer_Master!A:D,3,FALSE) -> Silver | Z434: =EDATE(E434,X434) -> 366 | AA434: =VLOOKUP(B434,Custumer_Master!A:K,11,) -> August | AB434: Silver | AC434: =PROPER(LEFT(TRIM(F434), 3)) & RIGHT(TRIM(B434), 3) & PROPER(LEFT(TRIM(I434), 2)) -> Ami001Pu | AD434: =DATEDIF(H434, TODAY(), "Y") -> 34 | AE434: =IFERROR(IF(OR(E434="", D434="", LOWER(TRIM(E434))="pending", LOWER(TRIM(D434))="pending"), "Pending", E434 - D434), "Pending") -> Pending | AF434: =IFERROR(IF(OR(E434="", D434="","Pending","Pending"), "Pending", IF((E434 - D434) <= 5, "On Time", "Delayed")), "Pending") -> Pending | AG434: =IF(AF434="Pending","Pending","Completed") -> Pending
A435: ORD10434 | B435: C008 | C435: P201 | D435: 45689 | E435: 06/02/2025 | F435: =VLOOKUP(B435,Custumer_Master!A:D,2,FALSE) -> Kavya Nair | G435: =VLOOKUP($B435,Custumer_Master!$A:$J,6,FALSE) -> Female | H435: =VLOOKUP($B435,Custumer_Master!$A:$J,7,FALSE) -> 01/08/1976 | I435: =VLOOKUP($B435,Custumer_Master!$A:$J,9,FALSE) -> Hyderabad | J435: =VLOOKUP($B435,Custumer_Master!$A:$J,10,FALSE) -> South | K435: =VLOOKUP(B435,Custumer_Master!A:D,4,FALSE) -> WB | L435: =PROPER(TRIM(VLOOKUP('Final Data'!C435,Product_Master!A:F,3,FALSE))) -> Home Appliances | M435: Mixer | N435: 16 | O435: =VLOOKUP(C435,Product_Master!A:F,5,FALSE) -> 2625 | P435: 0.05 | Q435: =(N435*O435)-(N435*O435)*P435 -> 39900 | R435: 1 | S435: Card | T435: Aisha | U435: kavya.nair@company.com | V435: 9999406260 | W435: =VLOOKUP(C435,Product_Master!A:F,4,FALSE) -> Global Trade | X435: =VLOOKUP(C435,Product_Master!A:F,6,FALSE) -> 6 | Y435: =VLOOKUP(B435,Custumer_Master!A:D,3,FALSE) -> Silver | Z435: =EDATE(E435,X435) -> 45875 | AA435: =VLOOKUP(B435,Custumer_Master!A:K,11,) -> August | AB435: Blacklisted | AC435: =PROPER(LEFT(TRIM(F435), 3)) & RIGHT(TRIM(B435), 3) & PROPER(LEFT(TRIM(I435), 2)) -> Kav008Hy | AD435: =DATEDIF(H435, TODAY(), "Y") -> 49 | AE435: =IFERROR(IF(OR(E435="", D435="", LOWER(TRIM(E435))="pending", LOWER(TRIM(D435))="pending"), "Pending", E435 - D435), "Pending") -> 5 | AF435: =IFERROR(IF(OR(E435="", D435="","Pending","Pending"), "Pending", IF((E435 - D435) <= 5, "On Time", "Delayed")), "Pending") -> On Time | AG435: =IF(AF435="Pending","Pending","Completed") -> Completed
A436: ORD10435 | B436: C001 | C436: P203 | D436: 45710 | E436: 04/03/2025 | F436: =VLOOKUP(B436,Custumer_Master!A:D,2,FALSE) -> Amit Sharma | G436: =VLOOKUP($B436,Custumer_Master!$A:$J,6,FALSE) -> Male | H436: =VLOOKUP($B436,Custumer_Master!$A:$J,7,FALSE) -> 09/08/1991 | I436: =VLOOKUP($B436,Custumer_Master!$A:$J,9,FALSE) -> Pune | J436: =VLOOKUP($B436,Custumer_Master!$A:$J,10,FALSE) -> West | K436: =VLOOKUP(B436,Custumer_Master!A:D,4,FALSE) -> RJ | L436: =PROPER(TRIM(VLOOKUP('Final Data'!C436,Product_Master!A:F,3,FALSE))) -> Home Appliances | M436: Microwave | N436: 12 | O436: =VLOOKUP(C436,Product_Master!A:F,5,FALSE) -> 6375 | P436: 0.1 | Q436: =(N436*O436)-(N436*O436)*P436 -> 68850 | R436: 3 | S436: Card | T436: Ritika | U436: amit.sharma@company.com | V436: 9233727886 | W436: =VLOOKUP(C436,Product_Master!A:F,4,FALSE) -> TechHub | X436: =VLOOKUP(C436,Product_Master!A:F,6,FALSE) -> 24 | Y436: =VLOOKUP(B436,Custumer_Master!A:D,3,FALSE) -> Silver | Z436: =EDATE(E436,X436) -> 46450 | AA436: =VLOOKUP(B436,Custumer_Master!A:K,11,) -> August | AB436: Gold | AC436: =PROPER(LEFT(TRIM(F436), 3)) & RIGHT(TRIM(B436), 3) & PROPER(LEFT(TRIM(I436), 2)) -> Ami001Pu | AD436: =DATEDIF(H436, TODAY(), "Y") -> 34 | AE436: =IFERROR(IF(OR(E436="", D436="", LOWER(TRIM(E436))="pending", LOWER(TRIM(D436))="pending"), "Pending", E436 - D436), "Pending") -> 10 | AF436: =IFERROR(IF(OR(E436="", D436="","Pending","Pending"), "Pending", IF((E436 - D436) <= 5, "On Time", "Delayed")), "Pending") -> Delayed | AG436: =IF(AF436="Pending","Pending","Completed") -> Completed
A437: ORD10436 | B437: C008 | C437: P301 | D437: 45765 | E437: 20/04/2025 | F437: =VLOOKUP(B437,Custumer_Master!A:D,2,FALSE) -> Kavya Nair | G437: =VLOOKUP($B437,Custumer_Master!$A:$J,6,FALSE) -> Female | H437: =VLOOKUP($B437,Custumer_Master!$A:$J,7,FALSE) -> 01/08/1976 | I437: =VLOOKUP($B437,Custumer_Master!$A:$J,9,FALSE) -> Hyderabad | J437: =VLOOKUP($B437,Custumer_Master!$A:$J,10,FALSE) -> South | K437: =VLOOKUP(B437,Custumer_Master!A:D,4,FALSE) -> WB | L437: =PROPER(TRIM(VLOOKUP('Final Data'!C437,Product_Master!A:F,3,FALSE))) -> Stationery | M437: Notebook | N437: 1 | O437: =VLOOKUP(C437,Product_Master!A:F,5,FALSE) -> 45 | P437: 0.2 | Q437: =(N437*O437)-(N437*O437)*P437 -> 36 | R437: 2 | S437: Card | T437: Karan | U437: kavya.nair@company.com | V437: 9831688801 | W437: =VLOOKUP(C437,Product_Master!A:F,4,FALSE) -> ABC Corp | X437: =VLOOKUP(C437,Product_Master!A:F,6,FALSE) -> 12 | Y437: =VLOOKUP(B437,Custumer_Master!A:D,3,FALSE) -> Silver | Z437: =EDATE(E437,X437) -> 46132 | AA437: =VLOOKUP(B437,Custumer_Master!A:K,11,) -> August | AB437: Blacklisted | AC437: =PROPER(LEFT(TRIM(F437), 3)) & RIGHT(TRIM(B437), 3) & PROPER(LEFT(TRIM(I437), 2)) -> Kav008Hy | AD437: =DATEDIF(H437, TODAY(), "Y") -> 49 | AE437: =IFERROR(IF(OR(E437="", D437="", LOWER(TRIM(E437))="pending", LOWER(TRIM(D437))="pending"), "Pending", E437 - D437), "Pending") -> 2 | AF437: =IFERROR(IF(OR(E437="", D437="","Pending","Pending"), "Pending", IF((E437 - D437) <= 5, "On Time", "Delayed")), "Pending") -> On Time | AG437: =IF(AF437="Pending","Pending","Completed") -> Completed
A438: ORD10437 | B438: C003 | C438: P301 | D438: 45967 | E438: 11/11/2025 | F438: =VLOOKUP(B438,Custumer_Master!A:D,2,FALSE) -> Rohit Singh | G438: =VLOOKUP($B438,Custumer_Master!$A:$J,6,FALSE) -> Male | H438: =VLOOKUP($B438,Custumer_Master!$A:$J,7,FALSE) -> 10/05/1982 | I438: =VLOOKUP($B438,Custumer_Master!$A:$J,9,FALSE) -> Delhi | J438: =VLOOKUP($B438,Custumer_Master!$A:$J,10,FALSE) -> North | K438: =VLOOKUP(B438,Custumer_Master!A:D,4,FALSE) -> DL | L438: =PROPER(TRIM(VLOOKUP('Final Data'!C438,Product_Master!A:F,3,FALSE))) -> Stationery | M438: Notebook | N438: 3 | O438: =VLOOKUP(C438,Product_Master!A:F,5,FALSE) -> 45 | P438: 0.15 | Q438: =(N438*O438)-(N438*O438)*P438 -> 114.75 | R438: 4 | S438: Card | T438: Ritika | U438: rohit.singh@company.com | V438: 9982849508 | W438: =VLOOKUP(C438,Product_Master!A:F,4,FALSE) -> ABC Corp | X438: =VLOOKUP(C438,Product_Master!A:F,6,FALSE) -> 12 | Y438: =VLOOKUP(B438,Custumer_Master!A:D,3,FALSE) -> Gold | Z438: =EDATE(E438,X438) -> 46337 | AA438: =VLOOKUP(B438,Custumer_Master!A:K,11,) -> May | AB438: Silver | AC438: =PROPER(LEFT(TRIM(F438), 3)) & RIGHT(TRIM(B438), 3) & PROPER(LEFT(TRIM(I438), 2)) -> Roh003De | AD438: =DATEDIF(H438, TODAY(), "Y") -> 44 | AE438: =IFERROR(IF(OR(E438="", D438="", LOWER(TRIM(E438))="pending", LOWER(TRIM(D438))="pending"), "Pending", E438 - D438), "Pending") -> 5 | AF438: =IFERROR(IF(OR(E438="", D438="","Pending","Pending"), "Pending", IF((E438 - D438) <= 5, "On Time", "Delayed")), "Pending") -> On Time | AG438: =IF(AF438="Pending","Pending","Completed") -> Completed
A439: ORD10438 | B439: C002 | C439: P102 | D439: 45736 | E439: 25/03/2025 | F439: =VLOOKUP(B439,Custumer_Master!A:D,2,FALSE) -> Priya Patel | G439: =VLOOKUP($B439,Custumer_Master!$A:$J,6,FALSE) -> Female | H439: =VLOOKUP($B439,Custumer_Master!$A:$J,7,FALSE) -> 07/03/1995 | I439: =VLOOKUP($B439,Custumer_Master!$A:$J,9,FALSE) -> Mumbai | J439: =VLOOKUP($B439,Custumer_Master!$A:$J,10,FALSE) -> West | K439: =VLOOKUP(B439,Custumer_Master!A:D,4,FALSE) -> WB | L439: =PROPER(TRIM(VLOOKUP('Final Data'!C439,Product_Master!A:F,3,FALSE))) -> Electronics | M439: Mouse | N439: 10 | O439: =VLOOKUP(C439,Product_Master!A:F,5,FALSE) -> 525 | P439: 0.15 | Q439: =(N439*O439)-(N439*O439)*P439 -> 4462.5 | R439: 3 | S439: Netbanking | T439: Ritika | U439: priya.patel@company.com | V439: 9288309246 | W439: =VLOOKUP(C439,Product_Master!A:F,4,FALSE) -> TechHub | X439: =VLOOKUP(C439,Product_Master!A:F,6,FALSE) -> 24 | Y439: =VLOOKUP(B439,Custumer_Master!A:D,3,FALSE) -> Platinum | Z439: =EDATE(E439,X439) -> 46471 | AA439: =VLOOKUP(B439,Custumer_Master!A:K,11,) -> March | AB439: Silver | AC439: =PROPER(LEFT(TRIM(F439), 3)) & RIGHT(TRIM(B439), 3) & PROPER(LEFT(TRIM(I439), 2)) -> Pri002Mu | AD439: =DATEDIF(H439, TODAY(), "Y") -> 31 | AE439: =IFERROR(IF(OR(E439="", D439="", LOWER(TRIM(E439))="pending", LOWER(TRIM(D439))="pending"), "Pending", E439 - D439), "Pending") -> 5 | AF439: =IFERROR(IF(OR(E439="", D439="","Pending","Pending"), "Pending", IF((E439 - D439) <= 5, "On Time", "Delayed")), "Pending") -> On Time | AG439: =IF(AF439="Pending","Pending","Completed") -> Completed
A440: ORD10439 | B440: C007 | C440: P302 | D440: 45952 | E440: 25/10/2025 | F440: =VLOOKUP(B440,Custumer_Master!A:D,2,FALSE) -> Arjun Rao | G440: =VLOOKUP($B440,Custumer_Master!$A:$J,6,FALSE) -> Male | H440: =VLOOKUP($B440,Custumer_Master!$A:$J,7,FALSE) -> 07/02/1988 | I440: =VLOOKUP($B440,Custumer_Master!$A:$J,9,FALSE) -> Hyderabad | J440: =VLOOKUP($B440,Custumer_Master!$A:$J,10,FALSE) -> South | K440: =VLOOKUP(B440,Custumer_Master!A:D,4,FALSE) -> RJ | L440: =PROPER(TRIM(VLOOKUP('Final Data'!C440,Product_Master!A:F,3,FALSE))) -> Stationery | M440: Pen | N440: 2 | O440: =VLOOKUP(C440,Product_Master!A:F,5,FALSE) -> 15 | P440: 0.1 | Q440: =(N440*O440)-(N440*O440)*P440 -> 27 | R440: 2 | S440: Upi | T440: Aisha | U440: arjun.rao@company.com | V440: 9808476235 | W440: =VLOOKUP(C440,Product_Master!A:F,4,FALSE) -> Prime Supplies | X440: =VLOOKUP(C440,Product_Master!A:F,6,FALSE) -> 12 | Y440: =VLOOKUP(B440,Custumer_Master!A:D,3,FALSE) -> Silver | Z440: =EDATE(E440,X440) -> 46320 | AA440: =VLOOKUP(B440,Custumer_Master!A:K,11,) -> February | AB440: Blacklisted | AC440: =PROPER(LEFT(TRIM(F440), 3)) & RIGHT(TRIM(B440), 3) & PROPER(LEFT(TRIM(I440), 2)) -> Arj007Hy | AD440: =DATEDIF(H440, TODAY(), "Y") -> 38 | AE440: =IFERROR(IF(OR(E440="", D440="", LOWER(TRIM(E440))="pending", LOWER(TRIM(D440))="pending"), "Pending", E440 - D440), "Pending") -> 3 | AF440: =IFERROR(IF(OR(E440="", D440="","Pending","Pending"), "Pending", IF((E440 - D440) <= 5, "On Time", "Delayed")), "Pending") -> On Time | AG440: =IF(AF440="Pending","Pending","Completed") -> Completed
A441: ORD10440 | B441: C007 | C441: P302 | D441: 46022 | E441: 05/01/2026 | F441: =VLOOKUP(B441,Custumer_Master!A:D,2,FALSE) -> Arjun Rao | G441: =VLOOKUP($B441,Custumer_Master!$A:$J,6,FALSE) -> Male | H441: =VLOOKUP($B441,Custumer_Master!$A:$J,7,FALSE) -> 07/02/1988 | I441: =VLOOKUP($B441,Custumer_Master!$A:$J,9,FALSE) -> Hyderabad | J441: =VLOOKUP($B441,Custumer_Master!$A:$J,10,FALSE) -> South | K441: =VLOOKUP(B441,Custumer_Master!A:D,4,FALSE) -> RJ | L441: =PROPER(TRIM(VLOOKUP('Final Data'!C441,Product_Master!A:F,3,FALSE))) -> Stationery | M441: Pen | N441: 14 | O441: =VLOOKUP(C441,Product_Master!A:F,5,FALSE) -> 15 | P441: 0.2 | Q441: =(N441*O441)-(N441*O441)*P441 -> 168 | R441: 5 | S441: Cash | T441: Karan | U441: arjun.rao@company.com | V441: 9869056117 | W441: =VLOOKUP(C441,Product_Master!A:F,4,FALSE) -> Prime Supplies | X441: =VLOOKUP(C441,Product_Master!A:F,6,FALSE) -> 12 | Y441: =VLOOKUP(B441,Custumer_Master!A:D,3,FALSE) -> Silver | Z441: =EDATE(E441,X441) -> 46392 | AA441: =VLOOKUP(B441,Custumer_Master!A:K,11,) -> February | AB441: Silver | AC441: =PROPER(LEFT(TRIM(F441), 3)) & RIGHT(TRIM(B441), 3) & PROPER(LEFT(TRIM(I441), 2)) -> Arj007Hy | AD441: =DATEDIF(H441, TODAY(), "Y") -> 38 | AE441: =IFERROR(IF(OR(E441="", D441="", LOWER(TRIM(E441))="pending", LOWER(TRIM(D441))="pending"), "Pending", E441 - D441), "Pending") -> 5 | AF441: =IFERROR(IF(OR(E441="", D441="","Pending","Pending"), "Pending", IF((E441 - D441) <= 5, "On Time", "Delayed")), "Pending") -> On Time | AG441: =IF(AF441="Pending","Pending","Completed") -> Completed
A442: ORD10441 | B442: C001 | C442: P201 | D442: 45829 | E442: 25/06/2025 | F442: =VLOOKUP(B442,Custumer_Master!A:D,2,FALSE) -> Amit Sharma | G442: =VLOOKUP($B442,Custumer_Master!$A:$J,6,FALSE) -> Male | H442: =VLOOKUP($B442,Custumer_Master!$A:$J,7,FALSE) -> 09/08/1991 | I442: =VLOOKUP($B442,Custumer_Master!$A:$J,9,FALSE) -> Pune | J442: =VLOOKUP($B442,Custumer_Master!$A:$J,10,FALSE) -> West | K442: =VLOOKUP(B442,Custumer_Master!A:D,4,FALSE) -> RJ | L442: =PROPER(TRIM(VLOOKUP('Final Data'!C442,Product_Master!A:F,3,FALSE))) -> Home Appliances | M442: Mixer | N442: 4 | O442: =VLOOKUP(C442,Product_Master!A:F,5,FALSE) -> 2625 | P442: 0 | Q442: =(N442*O442)-(N442*O442)*P442 -> 10500 | R442: 2 | S442: Upi | T442: Ritika | U442: amit.sharma@company.com | V442: 9734229772 | W442: =VLOOKUP(C442,Product_Master!A:F,4,FALSE) -> Global Trade | X442: =VLOOKUP(C442,Product_Master!A:F,6,FALSE) -> 6 | Y442: =VLOOKUP(B442,Custumer_Master!A:D,3,FALSE) -> Silver | Z442: =EDATE(E442,X442) -> 46016 | AA442: =VLOOKUP(B442,Custumer_Master!A:K,11,) -> August | AB442: Blacklisted | AC442: =PROPER(LEFT(TRIM(F442), 3)) & RIGHT(TRIM(B442), 3) & PROPER(LEFT(TRIM(I442), 2)) -> Ami001Pu | AD442: =DATEDIF(H442, TODAY(), "Y") -> 34 | AE442: =IFERROR(IF(OR(E442="", D442="", LOWER(TRIM(E442))="pending", LOWER(TRIM(D442))="pending"), "Pending", E442 - D442), "Pending") -> 4 | AF442: =IFERROR(IF(OR(E442="", D442="","Pending","Pending"), "Pending", IF((E442 - D442) <= 5, "On Time", "Delayed")), "Pending") -> On Time | AG442: =IF(AF442="Pending","Pending","Completed") -> Completed
A443: ORD10442 | B443: C007 | C443: P201 | D443: 45812 | E443: 05/06/2025 | F443: =VLOOKUP(B443,Custumer_Master!A:D,2,FALSE) -> Arjun Rao | G443: =VLOOKUP($B443,Custumer_Master!$A:$J,6,FALSE) -> Male | H443: =VLOOKUP($B443,Custumer_Master!$A:$J,7,FALSE) -> 07/02/1988 | I443: =VLOOKUP($B443,Custumer_Master!$A:$J,9,FALSE) -> Hyderabad | J443: =VLOOKUP($B443,Custumer_Master!$A:$J,10,FALSE) -> South | K443: =VLOOKUP(B443,Custumer_Master!A:D,4,FALSE) -> RJ | L443: =PROPER(TRIM(VLOOKUP('Final Data'!C443,Product_Master!A:F,3,FALSE))) -> Home Appliances | M443: Mixer | N443: 9 | O443: =VLOOKUP(C443,Product_Master!A:F,5,FALSE) -> 2625 | P443: 0.05 | Q443: =(N443*O443)-(N443*O443)*P443 -> 22443.75 | R443: 3 | S443: Card | T443: Aisha | U443: arjun.rao@company.com | V443: 9791617906 | W443: =VLOOKUP(C443,Product_Master!A:F,4,FALSE) -> Global Trade | X443: =VLOOKUP(C443,Product_Master!A:F,6,FALSE) -> 6 | Y443: =VLOOKUP(B443,Custumer_Master!A:D,3,FALSE) -> Silver | Z443: =EDATE(E443,X443) -> 45996 | AA443: =VLOOKUP(B443,Custumer_Master!A:K,11,) -> February | AB443: Silver | AC443: =PROPER(LEFT(TRIM(F443), 3)) & RIGHT(TRIM(B443), 3) & PROPER(LEFT(TRIM(I443), 2)) -> Arj007Hy | AD443: =DATEDIF(H443, TODAY(), "Y") -> 38 | AE443: =IFERROR(IF(OR(E443="", D443="", LOWER(TRIM(E443))="pending", LOWER(TRIM(D443))="pending"), "Pending", E443 - D443), "Pending") -> 1 | AF443: =IFERROR(IF(OR(E443="", D443="","Pending","Pending"), "Pending", IF((E443 - D443) <= 5, "On Time", "Delayed")), "Pending") -> On Time | AG443: =IF(AF443="Pending","Pending","Completed") -> Completed
A444: ORD10443 | B444: C003 | C444: P301 | D444: 45807 | E444: 03/06/2025 | F444: =VLOOKUP(B444,Custumer_Master!A:D,2,FALSE) -> Rohit Singh | G444: =VLOOKUP($B444,Custumer_Master!$A:$J,6,FALSE) -> Male | H444: =VLOOKUP($B444,Custumer_Master!$A:$J,7,FALSE) -> 10/05/1982 | I444: =VLOOKUP($B444,Custumer_Master!$A:$J,9,FALSE) -> Delhi | J444: =VLOOKUP($B444,Custumer_Master!$A:$J,10,FALSE) -> North | K444: =VLOOKUP(B444,Custumer_Master!A:D,4,FALSE) -> DL | L444: =PROPER(TRIM(VLOOKUP('Final Data'!C444,Product_Master!A:F,3,FALSE))) -> Stationery | M444: Notebook | N444: 9 | O444: =VLOOKUP(C444,Product_Master!A:F,5,FALSE) -> 45 | P444: 0 | Q444: =(N444*O444)-(N444*O444)*P444 -> 405 | R444: 3 | S444: Upi | T444: Ritika | U444: rohit.singh@company.com | V444: 9286316823 | W444: =VLOOKUP(C444,Product_Master!A:F,4,FALSE) -> ABC Corp | X444: =VLOOKUP(C444,Product_Master!A:F,6,FALSE) -> 12 | Y444: =VLOOKUP(B444,Custumer_Master!A:D,3,FALSE) -> Gold | Z444: =EDATE(E444,X444) -> 46176 | AA444: =VLOOKUP(B444,Custumer_Master!A:K,11,) -> May | AB444: Silver | AC444: =PROPER(LEFT(TRIM(F444), 3)) & RIGHT(TRIM(B444), 3) & PROPER(LEFT(TRIM(I444), 2)) -> Roh003De | AD444: =DATEDIF(H444, TODAY(), "Y") -> 44 | AE444: =IFERROR(IF(OR(E444="", D444="", LOWER(TRIM(E444))="pending", LOWER(TRIM(D444))="pending"), "Pending", E444 - D444), "Pending") -> 4 | AF444: =IFERROR(IF(OR(E444="", D444="","Pending","Pending"), "Pending", IF((E444 - D444) <= 5, "On Time", "Delayed")), "Pending") -> On Time | AG444: =IF(AF444="Pending","Pending","Completed") -> Completed
A445: ORD10444 | B445: C004 | C445: P103 | D445: 45779 | E445: 03/05/2025 | F445: =VLOOKUP(B445,Custumer_Master!A:D,2,FALSE) -> Anita Gupta | G445: =VLOOKUP($B445,Custumer_Master!$A:$J,6,FALSE) -> Female | H445: =VLOOKUP($B445,Custumer_Master!$A:$J,7,FALSE) -> 16/01/2002 | I445: =VLOOKUP($B445,Custumer_Master!$A:$J,9,FALSE) -> Pune | J445: =VLOOKUP($B445,Custumer_Master!$A:$J,10,FALSE) -> West | K445: =VLOOKUP(B445,Custumer_Master!A:D,4,FALSE) -> WB | L445: =PROPER(TRIM(VLOOKUP('Final Data'!C445,Product_Master!A:F,3,FALSE))) -> Electronics | M445: Keyboard | N445: 4 | O445: =VLOOKUP(C445,Product_Master!A:F,5,FALSE) -> 900 | P445: 0 | Q445: =(N445*O445)-(N445*O445)*P445 -> 3600 | R445: 1 | S445: Netbanking | T445: Aisha | U445: anita.gupta@company.com | V445: 9810569252 | W445: =VLOOKUP(C445,Product_Master!A:F,4,FALSE) -> TechHub | X445: =VLOOKUP(C445,Product_Master!A:F,6,FALSE) -> 6 | Y445: =VLOOKUP(B445,Custumer_Master!A:D,3,FALSE) -> Gold | Z445: =EDATE(E445,X445) -> 45964 | AA445: =VLOOKUP(B445,Custumer_Master!A:K,11,) -> January | AB445: Blacklisted | AC445: =PROPER(LEFT(TRIM(F445), 3)) & RIGHT(TRIM(B445), 3) & PROPER(LEFT(TRIM(I445), 2)) -> Ani004Pu | AD445: =DATEDIF(H445, TODAY(), "Y") -> 24 | AE445: =IFERROR(IF(OR(E445="", D445="", LOWER(TRIM(E445))="pending", LOWER(TRIM(D445))="pending"), "Pending", E445 - D445), "Pending") -> 1 | AF445: =IFERROR(IF(OR(E445="", D445="","Pending","Pending"), "Pending", IF((E445 - D445) <= 5, "On Time", "Delayed")), "Pending") -> On Time | AG445: =IF(AF445="Pending","Pending","Completed") -> Completed
A446: ORD10445 | B446: C010 | C446: P101 | D446: 45691 | E446: 13/02/2025 | F446: =VLOOKUP(B446,Custumer_Master!A:D,2,FALSE) -> Pooja Shah | G446: =VLOOKUP($B446,Custumer_Master!$A:$J,6,FALSE) -> Female | H446: =VLOOKUP($B446,Custumer_Master!$A:$J,7,FALSE) -> 16/09/1994 | I446: =VLOOKUP($B446,Custumer_Master!$A:$J,9,FALSE) -> Bengaluru | J446: =VLOOKUP($B446,Custumer_Master!$A:$J,10,FALSE) -> South | K446: =VLOOKUP(B446,Custumer_Master!A:D,4,FALSE) -> WB | L446: =PROPER(TRIM(VLOOKUP('Final Data'!C446,Product_Master!A:F,3,FALSE))) -> Electronics | M446: Laptop | N446: 10 | O446: =VLOOKUP(C446,Product_Master!A:F,5,FALSE) -> 41250 | P446: 0.05 | Q446: =(N446*O446)-(N446*O446)*P446 -> 391875 | R446: 5 | S446: Upi | T446: Neha | U446: pooja.shah@company.com | V446: 9771745925 | W446: =VLOOKUP(C446,Product_Master!A:F,4,FALSE) -> TechHub | X446: =VLOOKUP(C446,Product_Master!A:F,6,FALSE) -> 12 | Y446: =VLOOKUP(B446,Custumer_Master!A:D,3,FALSE) -> Silver | Z446: =EDATE(E446,X446) -> 46066 | AA446: =VLOOKUP(B446,Custumer_Master!A:K,11,) -> September | AB446: Platinum | AC446: =PROPER(LEFT(TRIM(F446), 3)) & RIGHT(TRIM(B446), 3) & PROPER(LEFT(TRIM(I446), 2)) -> Poo010Be | AD446: =DATEDIF(H446, TODAY(), "Y") -> 31 | AE446: =IFERROR(IF(OR(E446="", D446="", LOWER(TRIM(E446))="pending", LOWER(TRIM(D446))="pending"), "Pending", E446 - D446), "Pending") -> 10 | AF446: =IFERROR(IF(OR(E446="", D446="","Pending","Pending"), "Pending", IF((E446 - D446) <= 5, "On Time", "Delayed")), "Pending") -> Delayed | AG446: =IF(AF446="Pending","Pending","Completed") -> Completed
... A501: ORD10500 | B501: C002 | C501: P201 | D501: 45916 | E501: 23/09/2025 | F501: =VLOOKUP(B501,Custumer_Master!A:D,2,FALSE) -> Priya Patel | G501: =VLOOKUP($B501,Custumer_Master!$A:$J,6,FALSE) -> Female | H501: =VLOOKUP($B501,Custumer_Master!$A:$J,7,FALSE) -> 07/03/1995 | I501: =VLOOKUP($B501,Custumer_Master!$A:$J,9,FALSE) -> Mumbai | J501: =VLOOKUP($B501,Custumer_Master!$A:$J,10,FALSE) -> West | K501: =VLOOKUP(B501,Custumer_Master!A:D,4,FALSE) -> WB | L501: =PROPER(TRIM(VLOOKUP('Final Data'!C501,Product_Master!A:F,3,FALSE))) -> Home Appliances | M501: Mixer | N501: 20 | O501: =VLOOKUP(C501,Product_Master!A:F,5,FALSE) -> 2625 | P501: 0 | Q501: =(N501*O501)-(N501*O501)*P501 -> 52500 | R501: 1 | S501: Netbanking | T501: Karan | U501: priya.patel@company.com | V501: 9810334941 | W501: =VLOOKUP(C501,Product_Master!A:F,4,FALSE) -> Global Trade | X501: =VLOOKUP(C501,Product_Master!A:F,6,FALSE) -> 6 | Y501: =VLOOKUP(B501,Custumer_Master!A:D,3,FALSE) -> Platinum | Z501: =EDATE(E501,X501) -> 46104 | AA501: =VLOOKUP(B501,Custumer_Master!A:K,11,) -> March | AB501: Blacklisted | AC501: =PROPER(LEFT(TRIM(F501), 3)) & RIGHT(TRIM(B501), 3) & PROPER(LEFT(TRIM(I501), 2)) -> Pri002Mu | AD501: =DATEDIF(H501, TODAY(), "Y") -> 31 | AE501: =IFERROR(IF(OR(E501="", D501="", LOWER(TRIM(E501))="pending", LOWER(TRIM(D501))="pending"), "Pending", E501 - D501), "Pending") -> 7 | AF501: =IFERROR(IF(OR(E501="", D501="","Pending","Pending"), "Pending", IF((E501 - D501) <= 5, "On Time", "Delayed")), "Pending") -> Delayed | AG501: =IF(AF501="Pending","Pending","Completed") -> Completed

Sheet Question 1
A1: Question 1
A14: Customer ClassificationThe Sales team wants to identify the value of each transaction based on the Sales Amount, Discount Percentage, Customer Rating, and Order Status. Create a new column named Customer Classification and classify each record according to the following rules: | K14: Classification | L14: Rules / Criteria
K15: Platinum | L15: Sales >= ₹1,00,000, Rating>= 4, Discount <= 10%, and Order Status = "Completed"
K16: Gold | L16: Sales between ₹50,000 and ₹99,999, Rating >=3, and Order Status = "Completed"
K17: Silver | L17: Sales below ₹50,000 and Order Status = "Completed"
K18: Blacklisted | L18: Any order with Rating <= 2 OR Order Status = "Cancelled"
K20: Requirements:
K21: 1. Insert a new column named Customer Classification.
K22: 2. Write a single formula to classify every record.
K23: 3. The formula should automatically work for all 500 records.
K24: 4. Do not use helper columns.
K25: 5. Ensure that every record falls into exactly one classification.

Sheet Answer 1
A1: Order_ID | B1: Customer_ID | C1: Product_ID | D1: Order_Date | E1: Delivery_Date | F1: Customer_Name | G1: Gender | H1: DOB | I1: City | J1: Region | K1: State | L1: Category | M1: Product_Name_Final | N1: Quantity | O1: Unit_Price | P1: Discount_% | Q1: New Sales Calculation | R1: Rating | S1: Payment_Mode | T1: Salesperson | U1: Email | V1: Phone | W1: Supplier | X1: Warranty_Months | Y1: Membership | Z1: Warranty_Till(Months) | AA1: Birthday Month | AB1: Custumer Classification
A2: ORD10001 | B2: C008 | C2: P202 | D2: 45918 | E2: 22/09/2025 | F2: Kavya Nair | G2: Female | H2: 01/08/1976 | I2: Hyderabad | J2: South | K2: WB | L2: Home Appliances | M2: Iron | N2: 4 | O2: 1650 | P2: 0.1 | Q2: 5940 | R2: 4 | S2: Cash | T2: Ritika | U2: kavya.nair@company.com | V2: 9431429797 | W2: Global Trade | X2: 24 | Y2: Silver | Z2: 46652 | AA2: August | AB2: =IF(R2<=2, "Blacklisted", IF(AND(Q2>=100000, R2>=4, P2<=10%), "Platinum", IF(AND(Q2>=50000, R2>=3), "Gold", IF(Q2<50000, "Silver", "Blacklisted")))) -> Silver
A3: ORD10002 | B3: C008 | C3: P104 | D3: 45774 | E3: 04/05/2025 | F3: Kavya Nair | G3: Female | H3: 01/08/1976 | I3: Hyderabad | J3: South | K3: WB | L3: Electronics | M3: Monitor | N3: 17 | O3: 9000 | P3: 0.1 | Q3: 137700 | R3: 1 | S3: Netbanking | T3: Rahul | U3: kavya.nair@company.com | V3: 9129865339 | W3: Global Trade | X3: 24 | Y3: Silver | Z3: 46511 | AA3: August | AB3: =IF(R3<=2, "Blacklisted", IF(AND(Q3>=100000, R3>=4, P3<=10%), "Platinum", IF(AND(Q3>=50000, R3>=3), "Gold", IF(Q3<50000, "Silver", "Blacklisted")))) -> Blacklisted | AD3: Row Labels | AE3: Count of Custumer Classification | AF3: Percentage%
A4: ORD10003 | B4: C010 | C4: P101 | D4: 45903 | E4: 14/09/2025 | F4: Pooja Shah | G4: Female | H4: 16/09/1994 | I4: Bengaluru | J4: South | K4: WB | L4: Electronics | M4: Laptop | N4: 5 | O4: 41250 | P4: 0.05 | Q4: 195937.5 | R4: 3 | S4: Netbanking | T4: Aisha | U4: pooja.shah@company.com | V4: 9380975626 | W4: TechHub | X4: 12 | Y4: Silver | Z4: 46279 | AA4: September | AB4: =IF(R4<=2, "Blacklisted", IF(AND(Q4>=100000, R4>=4, P4<=10%), "Platinum", IF(AND(Q4>=50000, R4>=3), "Gold", IF(Q4<50000, "Silver", "Blacklisted")))) -> Gold | AD4: Blacklisted | AE4: 213 | AF4: 0.426
A5: ORD10004 | B5: C008 | C5: P202 | D5: 46102 | E5: 02/04/2026 | F5: Kavya Nair | G5: Female | H5: 01/08/1976 | I5: Hyderabad | J5: South | K5: WB | L5: Home Appliances | M5: Iron | N5: 5 | O5: 1650 | P5: 0.05 | Q5: 7837.5 | R5: 5 | S5: Netbanking | T5: Aisha | U5: kavya.nair@company.com | V5: 9600261125 | W5: Global Trade | X5: 24 | Y5: Silver | Z5: 46845 | AA5: August | AB5: =IF(R5<=2, "Blacklisted", IF(AND(Q5>=100000, R5>=4, P5<=10%), "Platinum", IF(AND(Q5>=50000, R5>=3), "Gold", IF(Q5<50000, "Silver", "Blacklisted")))) -> Silver | AD5: Gold | AE5: 38 | AF5: 0.076
A6: ORD10005 | B6: C009 | C6: P103 | D6: 45927 | E6: 07/10/2025 | F6: Mohit Verma | G6: Male | H6: 13/04/1976 | I6: Delhi | J6: North | K6: KA | L6: Electronics | M6: Keyboard | N6: 8 | O6: 900 | P6: 0.05 | Q6: 6840 | R6: 2 | S6: Card | T6: Aisha | U6: mohit.verma@company.com | V6: 9724635978 | W6: TechHub | X6: 6 | Y6: Platinum | Z6: 46119 | AA6: April | AB6: =IF(R6<=2, "Blacklisted", IF(AND(Q6>=100000, R6>=4, P6<=10%), "Platinum", IF(AND(Q6>=50000, R6>=3), "Gold", IF(Q6<50000, "Silver", "Blacklisted")))) -> Blacklisted | AD6: Platinum | AE6: 15 | AF6: 0.03
A7: ORD10006 | B7: C007 | C7: P202 | D7: 46026 | E7: 12/01/2026 | F7: Arjun Rao | G7: Male | H7: 07/02/1988 | I7: Hyderabad | J7: South | K7: RJ | L7: Home Appliances | M7: Iron | N7: 4 | O7: 1650 | P7: 0 | Q7: 6600 | R7: 1 | S7: Upi | T7: Ritika | U7: arjun.rao@company.com | V7: 9780584905 | W7: Global Trade | X7: 24 | Y7: Silver | Z7: 46764 | AA7: February | AB7: =IF(R7<=2, "Blacklisted", IF(AND(Q7>=100000, R7>=4, P7<=10%), "Platinum", IF(AND(Q7>=50000, R7>=3), "Gold", IF(Q7<50000, "Silver", "Blacklisted")))) -> Blacklisted | AD7: Silver | AE7: 234 | AF7: 0.468
A8: ORD10007 | B8: C008 | C8: P201 | D8: 31/02/2025 | E8: 25/02/2026 | F8: Kavya Nair | G8: Female | H8: 01/08/1976 | I8: Hyderabad | J8: South | K8: WB | L8: Home Appliances | M8: Mixer | N8: 2 | O8: 2625 | P8: 0.05 | Q8: 4987.5 | R8: 1 | S8: Upi | T8: Ritika | U8: kavya.nair@company.com | V8: 9958252176 | W8: Global Trade | X8: 6 | Y8: Silver | Z8: 46259 | AA8: August | AB8: =IF(R8<=2, "Blacklisted", IF(AND(Q8>=100000, R8>=4, P8<=10%), "Platinum", IF(AND(Q8>=50000, R8>=3), "Gold", IF(Q8<50000, "Silver", "Blacklisted")))) -> Blacklisted | AD8: Grand Total | AE8: 500 | AF8: 1
A9: ORD10008 | B9: C002 | C9: P104 | D9: 45760 | E9: 19/04/2025 | F9: Priya Patel | G9: Female | H9: 07/03/1995 | I9: Mumbai | J9: West | K9: WB | L9: Electronics | M9: Monitor | N9: 14 | O9: 9000 | P9: 0.15 | Q9: 107100 | R9: 4 | S9: Netbanking | T9: Ritika | U9: priya.patel@company.com | V9: 9705521654 | W9: Global Trade | X9: 24 | Y9: Platinum | Z9: 46496 | AA9: March | AB9: =IF(R9<=2, "Blacklisted", IF(AND(Q9>=100000, R9>=4, P9<=10%), "Platinum", IF(AND(Q9>=50000, R9>=3), "Gold", IF(Q9<50000, "Silver", "Blacklisted")))) -> Gold
A10: ORD10009 | B10: C008 | C10: P104 | D10: 46053 | E10: 02/02/2026 | F10: Kavya Nair | G10: Female | H10: 01/08/1976 | I10: Hyderabad | J10: South | K10: WB | L10: Electronics | M10: Monitor | N10: 4 | O10: 9000 | P10: 0.15 | Q10: 30600 | R10: 4 | S10: Upi | T10: Neha | U10: kavya.nair@company.com | V10: 9588041011 | W10: Global Trade | X10: 24 | Y10: Silver | Z10: 46785 | AA10: August | AB10: =IF(R10<=2, "Blacklisted", IF(AND(Q10>=100000, R10>=4, P10<=10%), "Platinum", IF(AND(Q10>=50000, R10>=3), "Gold", IF(Q10<50000, "Silver", "Blacklisted")))) -> Silver
A11: ORD10010 | B11: C002 | C11: P301 | D11: 45741 | E11: 27/03/2025 | F11: Priya Patel | G11: Female | H11: 07/03/1995 | I11: Mumbai | J11: West | K11: WB | L11: Stationery | M11: Notebook | N11: 6 | O11: 45 | P11: 0 | Q11: 270 | R11: 4 | S11: Card | T11: Neha | U11: priya.patel@company.com | V11: 9340540608 | W11: ABC Corp | X11: 12 | Y11: Platinum | Z11: 46108 | AA11: March | AB11: =IF(R11<=2, "Blacklisted", IF(AND(Q11>=100000, R11>=4, P11<=10%), "Platinum", IF(AND(Q11>=50000, R11>=3), "Gold", IF(Q11<50000, "Silver", "Blacklisted")))) -> Silver
A12: ORD10011 | B12: C003 | C12: P202 | D12: 45919 | E12: 23/09/2025 | F12: Rohit Singh | G12: Male | H12: 10/05/1982 | I12: Delhi | J12: North | K12: DL | L12: Home Appliances | M12: Iron | N12: 3 | O12: 1650 | P12: 0 | Q12: 4950 | R12: 2 | S12: Card | T12: Rahul | U12: rohit.singh@company.com | V12: 9521710321 | W12: Global Trade | X12: 24 | Y12: Gold | Z12: 46653 | AA12: May | AB12: =IF(R12<=2, "Blacklisted", IF(AND(Q12>=100000, R12>=4, P12<=10%), "Platinum", IF(AND(Q12>=50000, R12>=3), "Gold", IF(Q12<50000, "Silver", "Blacklisted")))) -> Blacklisted
A13: ORD10012 | B13: C008 | C13: P201 | D13: 45724 | E13: 15/03/2025 | F13: Kavya Nair | G13: Female | H13: 01/08/1976 | I13: Hyderabad | J13: South | K13: WB | L13: Home Appliances | M13: Mixer | N13: 10 | O13: 2625 | P13: 0.05 | Q13: 24937.5 | R13: 5 | S13: Card | T13: Aisha | U13: kavya.nair@company.com | V13: 9123535241 | W13: Global Trade | X13: 6 | Y13: Silver | Z13: 45915 | AA13: August | AB13: =IF(R13<=2, "Blacklisted", IF(AND(Q13>=100000, R13>=4, P13<=10%), "Platinum", IF(AND(Q13>=50000, R13>=3), "Gold", IF(Q13<50000, "Silver", "Blacklisted")))) -> Silver
A14: ORD10013 | B14: C002 | C14: P202 | D14: 45667 | E14: 15/01/2025 | F14: Priya Patel | G14: Female | H14: 07/03/1995 | I14: Mumbai | J14: West | K14: WB | L14: Home Appliances | M14: Iron | N14: 15 | O14: 1650 | P14: 0.1 | Q14: 22275 | R14: 1 | S14: Upi | T14: Neha | U14: priya.patel@company.com | V14: 9367316892 | W14: Global Trade | X14: 24 | Y14: Platinum | Z14: 46402 | AA14: March | AB14: =IF(R14<=2, "Blacklisted", IF(AND(Q14>=100000, R14>=4, P14<=10%), "Platinum", IF(AND(Q14>=50000, R14>=3), "Gold", IF(Q14<50000, "Silver", "Blacklisted")))) -> Blacklisted
